Workbook

Sheet README
A1: Assignment 1910090826 — Analytics Workbook (Option A: Public Sector Healthcare)
A2: Healthcare Infrastructure & Resource Planning · public_health_2021_2024.csv · Jan 2021 – Dec 2024 (48 months)
A4: Sheet | B4: Unit | C4: What it contains
A5: Data | B5: – | C5: Cleaned dataset + calculated fields (Year, Quarter, Season, Winter dummy, $/ER visit, ER visits per flu case, ICU>85% flag)
A6: Descriptive_Stats | B6: Unit 4 | C6: Mean, median, SD, variance, CV, quartiles, IQR, skewness, kurtosis, IQR fences and outlier counts (native formulas)
A7: Frequency | B7: Unit 4 | C7: Frequency distributions (COUNTIFS) with relative/cumulative % and histogram charts
A8: Pivot_Tables | B8: Unit 4 | C8: Native PivotTables: ER visits Quarter×Year, % of column total, YoY % difference, Season×Year ICU, annual KPI pivot
A9: Pivot_Formulas | B9: Unit 4 | C9: Formula cross-tabs with calculated fields: % of column total, YoY growth, $/visit, ICU breach counts, Month×Year heat map
A10: Correlation | B10: Unit 4 | C10: CORREL matrix heat map (colour scale) + significance (p-value) matrix
A11: Anomalies | B11: Unit 4 | C11: z-scores, irregular component, ICU threshold breaches, month-on-month change and anomaly flags
A12: SLR | B12: Unit 5 | C12: Simple linear regression ER_Visits ~ Flu_Resp_Cases in Analysis ToolPak layout (live LINEST formulas) + fitted-line chart
A13: MLR_Full | B13: Unit 5 | C13: MLR: Flu + Population density + Vaccination + Winter dummy; ANOVA, coefficients, p-values, VIF, JB normality, Breusch-Pagan, Durbin-Watson
A14: MLR_Refined | B14: Unit 5 | C14: Refined MLR after VIF diagnosis (Flu + Population density + Winter dummy)
A15: Decomposition | B15: Unit 6 | C15: Classical decomposition (2×12 centred MA, ratio-to-MA seasonal indices), additive vs multiplicative comparison
... A20: Forecast_2025 | B20: Sec. 4 | C20: Prediction intervals, staffing index, ICU bed requirement, budget reserve and severe-flu-season stress test
A22: Colour key: yellow cells = inputs/assumptions you may change (all dependent formulas update); green cells = key results.
A23: Holt-Winters smoothing parameters were optimised in Python (min SSE). To re-optimise in Excel: Data ▸ Solver ▸ minimise the SSE cell by changing α, β, γ (constraints 0.01–0.99).
A24: Shapiro-Wilk, White and HAC (Newey-West) tests, and the rolling-origin prediction intervals, are computed in the companion notebook 1910090826_Analytics_Workbook.ipynb.
A25: ICU forecasts and the flu-case forecast for 2025 are produced with the same Holt-Winters procedure in the notebook and entered on Forecast_2025 as inputs.

Sheet Data
A1: Month | B1: Date | C1: Year | D1: Quarter | E1: MonthNum | F1: Season | G1: Winter | H1: t | I1: ER_Visits | J1: ICU_Util_Rate | K1: Pub_Health_Exp | L1: Pop_Density_Idx | M1: Vacc_Coverage | N1: Flu_Resp_Cases | O1: Exp_per_ER_Visit | P1: ER_per_Flu_Case | Q1: ICU_Over_85 | R1: Vacc_Change_pp
A2: 2021-01 | B2: 44197 | C2: =YEAR(B2) -> 2021 | D2: ="Q"&ROUNDUP(MONTH(B2)/3,0) -> Q1 | E2: =MONTH(B2) -> 1 | F2: =CHOOSE(E2,"Winter","Winter","Spring","Spring","Spring","Summer","Summer","Summer","Autumn","Autumn","Autumn","Winter") -> Winter | G2: =IF(F2="Winter",1,0) -> 1 | H2: 1 | I2: 4820 | J2: 78.4 | K2: 1250000 | L2: 102.3 | M2: 61.2 | N2: 1340 | O2: =K2/I2 -> 259.3361 | P2: =I2/N2 -> 3.5970149 | Q2: =IF(J2>85,1,0) -> 0
A3: 2021-02 | B3: 44228 | C3: =YEAR(B3) -> 2021 | D3: ="Q"&ROUNDUP(MONTH(B3)/3,0) -> Q1 | E3: =MONTH(B3) -> 2 | F3: =CHOOSE(E3,"Winter","Winter","Spring","Spring","Spring","Summer","Summer","Summer","Autumn","Autumn","Autumn","Winter") -> Winter | G3: =IF(F3="Winter",1,0) -> 1 | H3: 2 | I3: 4510 | J3: 74.1 | K3: 1180000 | L3: 102.5 | M3: 63.8 | N3: 1180 | O3: =K3/I3 -> 261.6408 | P3: =I3/N3 -> 3.8220339 | Q3: =IF(J3>85,1,0) -> 0 | R3: =M3-M2 -> 2.6
A4: 2021-03 | B4: 44256 | C4: =YEAR(B4) -> 2021 | D4: ="Q"&ROUNDUP(MONTH(B4)/3,0) -> Q1 | E4: =MONTH(B4) -> 3 | F4: =CHOOSE(E4,"Winter","Winter","Spring","Spring","Spring","Summer","Summer","Summer","Autumn","Autumn","Autumn","Winter") -> Spring | G4: =IF(F4="Winter",1,0) -> 0 | H4: 3 | I4: 4180 | J4: 69.5 | K4: 1120000 | L4: 102.8 | M4: 66.1 | N4: 980 | O4: =K4/I4 -> 267.94258 | P4: =I4/N4 -> 4.2653061 | Q4: =IF(J4>85,1,0) -> 0 | R4: =M4-M3 -> 2.3
A5: 2021-04 | B5: 44287 | C5: =YEAR(B5) -> 2021 | D5: ="Q"&ROUNDUP(MONTH(B5)/3,0) -> Q2 | E5: =MONTH(B5) -> 4 | F5: =CHOOSE(E5,"Winter","Winter","Spring","Spring","Spring","Summer","Summer","Summer","Autumn","Autumn","Autumn","Winter") -> Spring | G5: =IF(F5="Winter",1,0) -> 0 | H5: 4 | I5: 3920 | J5: 64.2 | K5: 1080000 | L5: 103 | M5: 68.4 | N5: 820 | O5: =K5/I5 -> 275.5102 | P5: =I5/N5 -> 4.7804878 | Q5: =IF(J5>85,1,0) -> 0 | R5: =M5-M4 -> 2.3
A6: 2021-05 | B6: 44317 | C6: =YEAR(B6) -> 2021 | D6: ="Q"&ROUNDUP(MONTH(B6)/3,0) -> Q2 | E6: =MONTH(B6) -> 5 | F6: =CHOOSE(E6,"Winter","Winter","Spring","Spring","Spring","Summer","Summer","Summer","Autumn","Autumn","Autumn","Winter") -> Spring | G6: =IF(F6="Winter",1,0) -> 0 | H6: 5 | I6: 3710 | J6: 61.8 | K6: 1050000 | L6: 103.2 | M6: 70.2 | N6: 740 | O6: =K6/I6 -> 283.01887 | P6: =I6/N6 -> 5.0135135 | Q6: =IF(J6>85,1,0) -> 0 | R6: =M6-M5 -> 1.8
A7: 2021-06 | B7: 44348 | C7: =YEAR(B7) -> 2021 | D7: ="Q"&ROUNDUP(MONTH(B7)/3,0) -> Q2 | E7: =MONTH(B7) -> 6 | F7: =CHOOSE(E7,"Winter","Winter","Spring","Spring","Spring","Summer","Summer","Summer","Autumn","Autumn","Autumn","Winter") -> Summer | G7: =IF(F7="Winter",1,0) -> 0 | H7: 6 | I7: 3580 | J7: 59.4 | K7: 1020000 | L7: 103.4 | M7: 71.5 | N7: 690 | O7: =K7/I7 -> 284.9162 | P7: =I7/N7 -> 5.1884058 | Q7: =IF(J7>85,1,0) -> 0 | R7: =M7-M6 -> 1.3
A8: 2021-07 | B8: 44378 | C8: =YEAR(B8) -> 2021 | D8: ="Q"&ROUNDUP(MONTH(B8)/3,0) -> Q3 | E8: =MONTH(B8) -> 7 | F8: =CHOOSE(E8,"Winter","Winter","Spring","Spring","Spring","Summer","Summer","Summer","Autumn","Autumn","Autumn","Winter") -> Summer | G8: =IF(F8="Winter",1,0) -> 0 | H8: 7 | I8: 3620 | J8: 60.1 | K8: 1040000 | L8: 103.6 | M8: 72 | N8: 720 | O8: =K8/I8 -> 287.29282 | P8: =I8/N8 -> 5.0277778 | Q8: =IF(J8>85,1,0) -> 0 | R8: =M8-M7 -> 0.5
A9: 2021-08 | B9: 44409 | C9: =YEAR(B9) -> 2021 | D9: ="Q"&ROUNDUP(MONTH(B9)/3,0) -> Q3 | E9: =MONTH(B9) -> 8 | F9: =CHOOSE(E9,"Winter","Winter","Spring","Spring","Spring","Summer","Summer","Summer","Autumn","Autumn","Autumn","Winter") -> Summer | G9: =IF(F9="Winter",1,0) -> 0 | H9: 8 | I9: 3790 | J9: 63.7 | K9: 1070000 | L9: 103.8 | M9: 72.6 | N9: 810 | O9: =K9/I9 -> 282.3219 | P9: =I9/N9 -> 4.6790123 | Q9: =IF(J9>85,1,0) -> 0 | R9: =M9-M8 -> 0.6
A10: 2021-09 | B10: 44440 | C10: =YEAR(B10) -> 2021 | D10: ="Q"&ROUNDUP(MONTH(B10)/3,0) -> Q3 | E10: =MONTH(B10) -> 9 | F10: =CHOOSE(E10,"Winter","Winter","Spring","Spring","Spring","Summer","Summer","Summer","Autumn","Autumn","Autumn","Winter") -> Autumn | G10: =IF(F10="Winter",1,0) -> 0 | H10: 9 | I10: 4120 | J10: 68.9 | K10: 1130000 | L10: 104 | M10: 73.1 | N10: 1020 | O10: =K10/I10 -> 274.27184 | P10: =I10/N10 -> 4.0392157 | Q10: =IF(J10>85,1,0) -> 0 | R10: =M10-M9 -> 0.5
A11: 2021-10 | B11: 44470 | C11: =YEAR(B11) -> 2021 | D11: ="Q"&ROUNDUP(MONTH(B11)/3,0) -> Q4 | E11: =MONTH(B11) -> 10 | F11: =CHOOSE(E11,"Winter","Winter","Spring","Spring","Spring","Summer","Summer","Summer","Autumn","Autumn","Autumn","Winter") -> Autumn | G11: =IF(F11="Winter",1,0) -> 0 | H11: 10 | I11: 4480 | J11: 73.2 | K11: 1190000 | L11: 104.2 | M11: 73.5 | N11: 1190 | O11: =K11/I11 -> 265.625 | P11: =I11/N11 -> 3.7647059 | Q11: =IF(J11>85,1,0) -> 0 | R11: =M11-M10 -> 0.4
A12: 2021-11 | B12: 44501 | C12: =YEAR(B12) -> 2021 | D12: ="Q"&ROUNDUP(MONTH(B12)/3,0) -> Q4 | E12: =MONTH(B12) -> 11 | F12: =CHOOSE(E12,"Winter","Winter","Spring","Spring","Spring","Summer","Summer","Summer","Autumn","Autumn","Autumn","Winter") -> Autumn | G12: =IF(F12="Winter",1,0) -> 0 | H12: 11 | I12: 4910 | J12: 79.8 | K12: 1270000 | L12: 104.4 | M12: 73.8 | N12: 1420 | O12: =K12/I12 -> 258.6558 | P12: =I12/N12 -> 3.4577465 | Q12: =IF(J12>85,1,0) -> 0 | R12: =M12-M11 -> 0.3
A13: 2021-12 | B13: 44531 | C13: =YEAR(B13) -> 2021 | D13: ="Q"&ROUNDUP(MONTH(B13)/3,0) -> Q4 | E13: =MONTH(B13) -> 12 | F13: =CHOOSE(E13,"Winter","Winter","Spring","Spring","Spring","Summer","Summer","Summer","Autumn","Autumn","Autumn","Winter") -> Winter | G13: =IF(F13="Winter",1,0) -> 1 | H13: 12 | I13: 5340 | J13: 86.2 | K13: 1360000 | L13: 104.6 | M13: 74 | N13: 1680 | O13: =K13/I13 -> 254.68165 | P13: =I13/N13 -> 3.1785714 | Q13: =IF(J13>85,1,0) -> 1 | R13: =M13-M12 -> 0.2
A14: 2022-01 | B14: 44562 | C14: =YEAR(B14) -> 2022 | D14: ="Q"&ROUNDUP(MONTH(B14)/3,0) -> Q1 | E14: =MONTH(B14) -> 1 | F14: =CHOOSE(E14,"Winter","Winter","Spring","Spring","Spring","Summer","Summer","Summer","Autumn","Autumn","Autumn","Winter") -> Winter | G14: =IF(F14="Winter",1,0) -> 1 | H14: 13 | I14: 5620 | J14: 89.4 | K14: 1420000 | L14: 104.9 | M14: 74.4 | N14: 1820 | O14: =K14/I14 -> 252.66904 | P14: =I14/N14 -> 3.0879121 | Q14: =IF(J14>85,1,0) -> 1 | R14: =M14-M13 -> 0.4
... A49: 2024-12 | B49: 45627 | C49: =YEAR(B49) -> 2024 | D49: ="Q"&ROUNDUP(MONTH(B49)/3,0) -> Q4 | E49: =MONTH(B49) -> 12 | F49: =CHOOSE(E49,"Winter","Winter","Spring","Spring","Spring","Summer","Summer","Summer","Autumn","Autumn","Autumn","Winter") -> Winter | G49: =IF(F49="Winter",1,0) -> 1 | H49: 48 | I49: 6340 | J49: 97.9 | K49: 1590000 | L49: 114.2 | M49: 90.2 | N49: 2160 | O49: =K49/I49 -> 250.78864 | P49: =I49/N49 -> 2.9351852 | Q49: =IF(J49>85,1,0) -> 1 | R49: =M49-M48 -> 0.3

Sheet Descriptive_Stats
A1: Unit 4 · Central tendency, dispersion and shape
A2: All values are live formulas on the Data sheet
A4: Statistic | B4: ER_Visits | C4: ICU_Util_Rate | D4: Pub_Health_Exp | E4: Pop_Density_Idx | F4: Vacc_Coverage | G4: Flu_Resp_Cases
A5: Count | B5: =COUNT(Data!$I$2:$I$49) -> 48 | C5: =COUNT(Data!$J$2:$J$49) -> 48 | D5: =COUNT(Data!$K$2:$K$49) -> 48 | E5: =COUNT(Data!$L$2:$L$49) -> 48 | F5: =COUNT(Data!$M$2:$M$49) -> 48 | G5: =COUNT(Data!$N$2:$N$49) -> 48
A6: Mean | B6: =AVERAGE(Data!$I$2:$I$49) -> 4745 | C6: =AVERAGE(Data!$J$2:$J$49) -> 75.920833 | D6: =AVERAGE(Data!$K$2:$K$49) -> 1249166.7 | E6: =AVERAGE(Data!$L$2:$L$49) -> 107.92708 | F6: =AVERAGE(Data!$M$2:$M$49) -> 79.652083 | G6: =AVERAGE(Data!$N$2:$N$49) -> 1253.125
A7: Median | B7: =MEDIAN(Data!$I$2:$I$49) -> 4585 | C7: =MEDIAN(Data!$J$2:$J$49) -> 74.35 | D7: =MEDIAN(Data!$K$2:$K$49) -> 1215000 | E7: =MEDIAN(Data!$L$2:$L$49) -> 107.75 | F7: =MEDIAN(Data!$M$2:$M$49) -> 79.85 | G7: =MEDIAN(Data!$N$2:$N$49) -> 1180
A8: Std Dev (sample) | B8: =_xlfn.STDEV.S(Data!$I$2:$I$49) -> 739.37869 | C8: =_xlfn.STDEV.S(Data!$J$2:$J$49) -> 10.468473 | D8: =_xlfn.STDEV.S(Data!$K$2:$K$49) -> 148163.7 | E8: =_xlfn.STDEV.S(Data!$L$2:$L$49) -> 3.5638695 | F8: =_xlfn.STDEV.S(Data!$M$2:$M$49) -> 7.2477726 | G8: =_xlfn.STDEV.S(Data!$N$2:$N$49) -> 417.38882
A9: Variance | B9: =VAR(Data!$I$2:$I$49) -> 546680.85 | C9: =VAR(Data!$J$2:$J$49) -> 109.58892 | D9: =VAR(Data!$K$2:$K$49) -> 2.1952482e+10 | E9: =VAR(Data!$L$2:$L$49) -> 12.701166 | F9: =VAR(Data!$M$2:$M$49) -> 52.530208 | G9: =VAR(Data!$N$2:$N$49) -> 174213.43
A10: Coefficient of variation % | B10: =B6/B7*100 -> 103.48964 | C10: =C6/C7*100 -> 102.11275 | D10: =D6/D7*100 -> 102.81207 | E10: =E6/E7*100 -> 100.16435 | F10: =F6/F7*100 -> 99.752139 | G10: =G6/G7*100 -> 106.19703
A11: Minimum | B11: =MIN(Data!$I$2:$I$49) -> 3580 | C11: =MIN(Data!$J$2:$J$49) -> 59.4 | D11: =MIN(Data!$K$2:$K$49) -> 1020000 | E11: =MIN(Data!$L$2:$L$49) -> 102.3 | F11: =MIN(Data!$M$2:$M$49) -> 61.2 | G11: =MIN(Data!$N$2:$N$49) -> 690
A12: Q1 (25th pct) | B12: =_xlfn.QUARTILE.INC(Data!$I$2:$I$49,1) -> 4170 | C12: =_xlfn.QUARTILE.INC(Data!$J$2:$J$49,1) -> 68.1 | D12: =_xlfn.QUARTILE.INC(Data!$K$2:$K$49,1) -> 1137500 | E12: =_xlfn.QUARTILE.INC(Data!$L$2:$L$49,1) -> 104.825 | F12: =_xlfn.QUARTILE.INC(Data!$M$2:$M$49,1) -> 74.3 | G12: =_xlfn.QUARTILE.INC(Data!$N$2:$N$49,1) -> 897.5
A13: Q3 (75th pct) | B13: =_xlfn.QUARTILE.INC(Data!$I$2:$I$49,3) -> 5287.5 | C13: =_xlfn.QUARTILE.INC(Data!$J$2:$J$49,3) -> 83.45 | D13: =_xlfn.QUARTILE.INC(Data!$K$2:$K$49,3) -> 1345000 | E13: =_xlfn.QUARTILE.INC(Data!$L$2:$L$49,3) -> 110.875 | F13: =_xlfn.QUARTILE.INC(Data!$M$2:$M$49,3) -> 85.225 | G13: =_xlfn.QUARTILE.INC(Data!$N$2:$N$49,3) -> 1562.5
A14: Maximum | B14: =MAX(Data!$I$2:$I$49) -> 6340 | C14: =MAX(Data!$J$2:$J$49) -> 97.9 | D14: =MAX(Data!$K$2:$K$49) -> 1590000 | E14: =MAX(Data!$L$2:$L$49) -> 114.2 | F14: =MAX(Data!$M$2:$M$49) -> 90.2 | G14: =MAX(Data!$N$2:$N$49) -> 2160
A15: Range | B15: =B14-B11 -> 2760 | C15: =C14-C11 -> 38.5 | D15: =D14-D11 -> 570000 | E15: =E14-E11 -> 11.9 | F15: =F14-F11 -> 29 | G15: =G14-G11 -> 1470
A16: Interquartile range (IQR) | B16: =B13-B12 -> 1117.5 | C16: =C13-C12 -> 15.35 | D16: =D13-D12 -> 207500 | E16: =E13-E12 -> 6.05 | F16: =F13-F12 -> 10.925 | G16: =G13-G12 -> 665
A17: Skewness | B17: =SKEW(Data!$I$2:$I$49) -> 0.47048281 | C17: =SKEW(Data!$J$2:$J$49) -> 0.4253656 | D17: =SKEW(Data!$K$2:$K$49) -> 0.60004766 | E17: =SKEW(Data!$L$2:$L$49) -> 0.12234181 | F17: =SKEW(Data!$M$2:$M$49) -> -0.51215267 | G17: =SKEW(Data!$N$2:$N$49) -> 0.60433285
A18: Excess kurtosis | B18: =KURT(Data!$I$2:$I$49) -> -0.69225832 | C18: =KURT(Data!$J$2:$J$49) -> -0.80351441 | D18: =KURT(Data!$K$2:$K$49) -> -0.47168095 | E18: =KURT(Data!$L$2:$L$49) -> -1.215888 | F18: =KURT(Data!$M$2:$M$49) -> -0.29038308 | G18: =KURT(Data!$N$2:$N$49) -> -0.76719637
A19: Std error of mean | B19: =B8/SQRT(B5) -> 106.72012 | C19: =C8/SQRT(C5) -> 1.5109939 | D19: =D8/SQRT(D5) -> 21385.588 | E19: =E8/SQRT(E5) -> 0.51440025 | F19: =F8/SQRT(F5) -> 1.0461259 | G19: =G8/SQRT(G5) -> 60.244888
A20: Lower fence (Q1-1.5×IQR) | B20: =B12-1.5*B16 -> 2493.75 | C20: =C12-1.5*C16 -> 45.075 | D20: =D12-1.5*D16 -> 826250 | E20: =E12-1.5*E16 -> 95.75 | F20: =F12-1.5*F16 -> 57.9125 | G20: =G12-1.5*G16 -> -100
A21: Upper fence (Q3+1.5×IQR) | B21: =B13+1.5*B16 -> 6963.75 | C21: =C13+1.5*C16 -> 106.475 | D21: =D13+1.5*D16 -> 1656250 | E21: =E13+1.5*E16 -> 119.95 | F21: =F13+1.5*F16 -> 101.6125 | G21: =G13+1.5*G16 -> 2560
A22: IQR outliers (count) | B22: =COUNTIF(Data!$I$2:$I$49,"<"&B20)+COUNTIF(Data!$I$2:$I$49,">"&B21) -> 0 | C22: =COUNTIF(Data!$J$2:$J$49,"<"&C20)+COUNTIF(Data!$J$2:$J$49,">"&C21) -> 0 | D22: =COUNTIF(Data!$K$2:$K$49,"<"&D20)+COUNTIF(Data!$K$2:$K$49,">"&D21) -> 0 | E22: =COUNTIF(Data!$L$2:$L$49,"<"&E20)+COUNTIF(Data!$L$2:$L$49,">"&E21) -> 0 | F22: =COUNTIF(Data!$M$2:$M$49,"<"&F20)+COUNTIF(Data!$M$2:$M$49,">"&F21) -> 0 | G22: =COUNTIF(Data!$N$2:$N$49,"<"&G20)+COUNTIF(Data!$N$2:$N$49,">"&G21) -> 0
A23: Mean − Median | B23: =B6-B7 -> 160 | C23: =C6-C7 -> 1.5708333 | D23: =D6-D7 -> 34166.667 | E23: =E6-E7 -> 0.17708333 | F23: =F6-F7 -> -0.19791667 | G23: =G6-G7 -> 73.125
A24: Shape interpretation | B24: =IF(ABS(B17)<0.5,"Approximately symmetric",IF(B17>0,"Moderately right-skewed","Moderately left-skewed"))&IF(B18<0,", platykurtic",", leptokurtic") -> Approximately symmetric, platykurtic | C24: =IF(ABS(C17)<0.5,"Approximately symmetric",IF(C17>0,"Moderately right-skewed","Moderately left-skewed"))&IF(C18<0,", platykurtic",", leptokurtic") -> Approximately symmetric, platykurtic | D24: =IF(ABS(D17)<0.5,"Approximately symmetric",IF(D17>0,"Moderately right-skewed","Moderately left-skewed"))&IF(D18<0,", platykurtic",", leptokurtic") -> Moderately right-skewed, platykurtic | E24: =IF(ABS(E17)<0.5,"Approximately symmetric",IF(E17>0,"Moderately right-skewed","Moderately left-skewed"))&IF(E18<0,", platykurtic",", leptokurtic") -> Approximately symmetric, platykurtic | F24: =IF(ABS(F17)<0.5,"Approximately symmetric",IF(F17>0,"Moderately right-skewed","Moderately left-skewed"))&IF(F18<0,", platykurtic",", leptokurtic") -> Moderately left-skewed, platykurtic | G24: =IF(ABS(G17)<0.5,"Approximately symmetric",IF(G17>0,"Moderately right-skewed","Moderately left-skewed"))&IF(G18<0,", platykurtic",", leptokurtic") -> Moderately right-skewed, platykurtic
A27: Normality (Shapiro-Wilk p, from notebook) | B27: 0.0842 | C27: 0.0763 | D27: 0.0437 | E27: 0.045 | F27: 0.1194 | G27: 0.0043
A29: Interpretation: all demand variables are right-skewed (mean > median) because of winter surges; no value breaches the 1.5×IQR fences, so extremes are seasonal peaks, not errors.

Sheet Frequency
A1: Unit 4 · Frequency distributions and histograms
A2: Bins are [lower, upper) — COUNTIFS formulas
A4: ER visits per month
A5: Lower | B5: Upper | C5: Bin | D5: Frequency | E5: Relative % | F5: Cumulative %
A6: 3500 | B6: =A6+250 -> 3750 | C6: =TEXT(A6,"#,##0")&"–"&TEXT(B6,"#,##0") -> 3,500–3,750 | D6: =COUNTIFS(Data!$I$2:$I$49,">="&A6,Data!$I$2:$I$49,"<"&B6) -> 3 | E6: =D6/SUM($D$6:$D$17)*100 -> 6.25 | F6: =E6 -> 6.25
A7: 3750 | B7: =A7+250 -> 4000 | C7: =TEXT(A7,"#,##0")&"–"&TEXT(B7,"#,##0") -> 3,750–4,000 | D7: =COUNTIFS(Data!$I$2:$I$49,">="&A7,Data!$I$2:$I$49,"<"&B7) -> 4 | E7: =D7/SUM($D$6:$D$17)*100 -> 8.3333333 | F7: =F6+E7 -> 14.583333
A8: 4000 | B8: =A8+250 -> 4250 | C8: =TEXT(A8,"#,##0")&"–"&TEXT(B8,"#,##0") -> 4,000–4,250 | D8: =COUNTIFS(Data!$I$2:$I$49,">="&A8,Data!$I$2:$I$49,"<"&B8) -> 8 | E8: =D8/SUM($D$6:$D$17)*100 -> 16.666667 | F8: =F7+E8 -> 31.25
A9: 4250 | B9: =A9+250 -> 4500 | C9: =TEXT(A9,"#,##0")&"–"&TEXT(B9,"#,##0") -> 4,250–4,500 | D9: =COUNTIFS(Data!$I$2:$I$49,">="&A9,Data!$I$2:$I$49,"<"&B9) -> 7 | E9: =D9/SUM($D$6:$D$17)*100 -> 14.583333 | F9: =F8+E9 -> 45.833333
A10: 4500 | B10: =A10+250 -> 4750 | C10: =TEXT(A10,"#,##0")&"–"&TEXT(B10,"#,##0") -> 4,500–4,750 | D10: =COUNTIFS(Data!$I$2:$I$49,">="&A10,Data!$I$2:$I$49,"<"&B10) -> 5 | E10: =D10/SUM($D$6:$D$17)*100 -> 10.416667 | F10: =F9+E10 -> 56.25
A11: 4750 | B11: =A11+250 -> 5000 | C11: =TEXT(A11,"#,##0")&"–"&TEXT(B11,"#,##0") -> 4,750–5,000 | D11: =COUNTIFS(Data!$I$2:$I$49,">="&A11,Data!$I$2:$I$49,"<"&B11) -> 5 | E11: =D11/SUM($D$6:$D$17)*100 -> 10.416667 | F11: =F10+E11 -> 66.666667
A12: 5000 | B12: =A12+250 -> 5250 | C12: =TEXT(A12,"#,##0")&"–"&TEXT(B12,"#,##0") -> 5,000–5,250 | D12: =COUNTIFS(Data!$I$2:$I$49,">="&A12,Data!$I$2:$I$49,"<"&B12) -> 3 | E12: =D12/SUM($D$6:$D$17)*100 -> 6.25 | F12: =F11+E12 -> 72.916667
A13: 5250 | B13: =A13+250 -> 5500 | C13: =TEXT(A13,"#,##0")&"–"&TEXT(B13,"#,##0") -> 5,250–5,500 | D13: =COUNTIFS(Data!$I$2:$I$49,">="&A13,Data!$I$2:$I$49,"<"&B13) -> 4 | E13: =D13/SUM($D$6:$D$17)*100 -> 8.3333333 | F13: =F12+E13 -> 81.25
A14: 5500 | B14: =A14+250 -> 5750 | C14: =TEXT(A14,"#,##0")&"–"&TEXT(B14,"#,##0") -> 5,500–5,750 | D14: =COUNTIFS(Data!$I$2:$I$49,">="&A14,Data!$I$2:$I$49,"<"&B14) -> 3 | E14: =D14/SUM($D$6:$D$17)*100 -> 6.25 | F14: =F13+E14 -> 87.5
A15: 5750 | B15: =A15+250 -> 6000 | C15: =TEXT(A15,"#,##0")&"–"&TEXT(B15,"#,##0") -> 5,750–6,000 | D15: =COUNTIFS(Data!$I$2:$I$49,">="&A15,Data!$I$2:$I$49,"<"&B15) -> 3 | E15: =D15/SUM($D$6:$D$17)*100 -> 6.25 | F15: =F14+E15 -> 93.75
A16: 6000 | B16: =A16+250 -> 6250 | C16: =TEXT(A16,"#,##0")&"–"&TEXT(B16,"#,##0") -> 6,000–6,250 | D16: =COUNTIFS(Data!$I$2:$I$49,">="&A16,Data!$I$2:$I$49,"<"&B16) -> 1 | E16: =D16/SUM($D$6:$D$17)*100 -> 2.0833333 | F16: =F15+E16 -> 95.833333
A17: 6250 | B17: =A17+250 -> 6500 | C17: =TEXT(A17,"#,##0")&"–"&TEXT(B17,"#,##0") -> 6,250–6,500 | D17: =COUNTIFS(Data!$I$2:$I$49,">="&A17,Data!$I$2:$I$49,"<"&B17) -> 2 | E17: =D17/SUM($D$6:$D$17)*100 -> 4.1666667 | F17: =F16+E17 -> 100
C18: Total | D18: =SUM(D6:D17) -> 48
A21: ICU utilisation %
A22: Lower | B22: Upper | C22: Bin | D22: Frequency | E22: Relative % | F22: Cumulative %
A23: 55 | B23: =A23+5 -> 60 | C23: =TEXT(A23,"0")&"–"&TEXT(B23,"0") -> 55–60 | D23: =COUNTIFS(Data!$J$2:$J$49,">="&A23,Data!$J$2:$J$49,"<"&B23) -> 1 | E23: =D23/SUM($D$23:$D$31)*100 -> 2.0833333 | F23: =E23 -> 2.0833333
A24: 60 | B24: =A24+5 -> 65 | C24: =TEXT(A24,"0")&"–"&TEXT(B24,"0") -> 60–65 | D24: =COUNTIFS(Data!$J$2:$J$49,">="&A24,Data!$J$2:$J$49,"<"&B24) -> 6 | E24: =D24/SUM($D$23:$D$31)*100 -> 12.5 | F24: =F23+E24 -> 14.583333
A25: 65 | B25: =A25+5 -> 70 | C25: =TEXT(A25,"0")&"–"&TEXT(B25,"0") -> 65–70 | D25: =COUNTIFS(Data!$J$2:$J$49,">="&A25,Data!$J$2:$J$49,"<"&B25) -> 11 | E25: =D25/SUM($D$23:$D$31)*100 -> 22.916667 | F25: =F24+E25 -> 37.5
A26: 70 | B26: =A26+5 -> 75 | C26: =TEXT(A26,"0")&"–"&TEXT(B26,"0") -> 70–75 | D26: =COUNTIFS(Data!$J$2:$J$49,">="&A26,Data!$J$2:$J$49,"<"&B26) -> 9 | E26: =D26/SUM($D$23:$D$31)*100 -> 18.75 | F26: =F25+E26 -> 56.25
A27: 75 | B27: =A27+5 -> 80 | C27: =TEXT(A27,"0")&"–"&TEXT(B27,"0") -> 75–80 | D27: =COUNTIFS(Data!$J$2:$J$49,">="&A27,Data!$J$2:$J$49,"<"&B27) -> 5 | E27: =D27/SUM($D$23:$D$31)*100 -> 10.416667 | F27: =F26+E27 -> 66.666667
A28: 80 | B28: =A28+5 -> 85 | C28: =TEXT(A28,"0")&"–"&TEXT(B28,"0") -> 80–85 | D28: =COUNTIFS(Data!$J$2:$J$49,">="&A28,Data!$J$2:$J$49,"<"&B28) -> 5 | E28: =D28/SUM($D$23:$D$31)*100 -> 10.416667 | F28: =F27+E28 -> 77.083333
A29: 85 | B29: =A29+5 -> 90 | C29: =TEXT(A29,"0")&"–"&TEXT(B29,"0") -> 85–90 | D29: =COUNTIFS(Data!$J$2:$J$49,">="&A29,Data!$J$2:$J$49,"<"&B29) -> 4 | E29: =D29/SUM($D$23:$D$31)*100 -> 8.3333333 | F29: =F28+E29 -> 85.416667
A30: 90 | B30: =A30+5 -> 95 | C30: =TEXT(A30,"0")&"–"&TEXT(B30,"0") -> 90–95 | D30: =COUNTIFS(Data!$J$2:$J$49,">="&A30,Data!$J$2:$J$49,"<"&B30) -> 5 | E30: =D30/SUM($D$23:$D$31)*100 -> 10.416667 | F30: =F29+E30 -> 95.833333
A31: 95 | B31: =A31+5 -> 100 | C31: =TEXT(A31,"0")&"–"&TEXT(B31,"0") -> 95–100 | D31: =COUNTIFS(Data!$J$2:$J$49,">="&A31,Data!$J$2:$J$49,"<"&B31) -> 2 | E31: =D31/SUM($D$23:$D$31)*100 -> 4.1666667 | F31: =F30+E31 -> 100
C32: Total | D32: =SUM(D23:D31) -> 48
A35: Flu / respiratory cases
A36: Lower | B36: Upper | C36: Bin | D36: Frequency | E36: Relative % | F36: Cumulative %
A37: 600 | B37: =A37+200 -> 800 | C37: =TEXT(A37,"#,##0")&"–"&TEXT(B37,"#,##0") -> 600–800 | D37: =COUNTIFS(Data!$N$2:$N$49,">="&A37,Data!$N$2:$N$49,"<"&B37) -> 4 | E37: =D37/SUM($D$37:$D$44)*100 -> 8.3333333 | F37: =E37 -> 8.3333333
A38: 800 | B38: =A38+200 -> 1000 | C38: =TEXT(A38,"#,##0")&"–"&TEXT(B38,"#,##0") -> 800–1,000 | D38: =COUNTIFS(Data!$N$2:$N$49,">="&A38,Data!$N$2:$N$49,"<"&B38) -> 14 | E38: =D38/SUM($D$37:$D$44)*100 -> 29.166667 | F38: =F37+E38 -> 37.5
A39: 1000 | B39: =A39+200 -> 1200 | C39: =TEXT(A39,"#,##0")&"–"&TEXT(B39,"#,##0") -> 1,000–1,200 | D39: =COUNTIFS(Data!$N$2:$N$49,">="&A39,Data!$N$2:$N$49,"<"&B39) -> 8 | E39: =D39/SUM($D$37:$D$44)*100 -> 16.666667 | F39: =F38+E39 -> 54.166667
A40: 1200 | B40: =A40+200 -> 1400 | C40: =TEXT(A40,"#,##0")&"–"&TEXT(B40,"#,##0") -> 1,200–1,400 | D40: =COUNTIFS(Data!$N$2:$N$49,">="&A40,Data!$N$2:$N$49,"<"&B40) -> 6 | E40: =D40/SUM($D$37:$D$44)*100 -> 12.5 | F40: =F39+E40 -> 66.666667
A41: 1400 | B41: =A41+200 -> 1600 | C41: =TEXT(A41,"#,##0")&"–"&TEXT(B41,"#,##0") -> 1,400–1,600 | D41: =COUNTIFS(Data!$N$2:$N$49,">="&A41,Data!$N$2:$N$49,"<"&B41) -> 5 | E41: =D41/SUM($D$37:$D$44)*100 -> 10.416667 | F41: =F40+E41 -> 77.083333
A42: 1600 | B42: =A42+200 -> 1800 | C42: =TEXT(A42,"#,##0")&"–"&TEXT(B42,"#,##0") -> 1,600–1,800 | D42: =COUNTIFS(Data!$N$2:$N$49,">="&A42,Data!$N$2:$N$49,"<"&B42) -> 3 | E42: =D42/SUM($D$37:$D$44)*100 -> 6.25 | F42: =F41+E42 -> 83.333333
A43: 1800 | B43: =A43+200 -> 2000 | C43: =TEXT(A43,"#,##0")&"–"&TEXT(B43,"#,##0") -> 1,800–2,000 | D43: =COUNTIFS(Data!$N$2:$N$49,">="&A43,Data!$N$2:$N$49,"<"&B43) -> 6 | E43: =D43/SUM($D$37:$D$44)*100 -> 12.5 | F43: =F42+E43 -> 95.833333
A44: 2000 | B44: =A44+200 -> 2200 | C44: =TEXT(A44,"#,##0")&"–"&TEXT(B44,"#,##0") -> 2,000–2,200 | D44: =COUNTIFS(Data!$N$2:$N$49,">="&A44,Data!$N$2:$N$49,"<"&B44) -> 2 | E44: =D44/SUM($D$37:$D$44)*100 -> 4.1666667 | F44: =F43+E44 -> 100
C45: Total | D45: =SUM(D37:D44) -> 48

Sheet Pivot_Tables
A1: Unit 4 · Native PivotTables (source: Data!A1:R49)
A2: Right-click any table ▸ Refresh to update. Value-display modes: Sum, % of column total, % difference from previous year, Average.
A4: PT1. Sum of ER visits — Quarter × Year | H4: PT2. ER visits as % of column (annual) total | O4: PT3. ER visits — % difference from previous year (YoY)
A5: Sum - ER_Visits | B5: Year | H5: Sum - ER_Visits | I5: Year | O5: Sum - ER_Visits | P5: Year
A6: Quarter | B6: 2021 | C6: 2022 | D6: 2023 | E6: 2024 | F6: Total Result | H6: Quarter | I6: 2021 | J6: 2022 | K6: 2023 | L6: 2024 | M6: Total Result | O6: Quarter | P6: 2021 | Q6: 2022 | R6: 2023 | S6: 2024 | T6: Total Result
A7: Q1 | B7: 13510 | C7: 15410 | D7: 16360 | E7: 17240 | F7: 62520 | H7: Q1 | I7: 0.26500588 | J7: 0.27646215 | K7: 0.27747626 | L7: 0.27770619 | M7: 0.27449947 | O7: Q1 | Q7: 0.14063657 | R7: 0.06164828 | S7: 0.053789731
A8: Q2 | B8: 11210 | C8: 12100 | D8: 12770 | E8: 13430 | F8: 49510 | H8: Q2 | I8: 0.21989015 | J8: 0.2170793 | K8: 0.21658752 | L8: 0.21633376 | M8: 0.21737794 | O8: Q2 | Q8: 0.079393399 | R8: 0.055371901 | S8: 0.051683634
A9: Q3 | B9: 11530 | C9: 12430 | D9: 13160 | E9: 13860 | F9: 50980 | H9: Q3 | I9: 0.22616712 | J9: 0.22299964 | K9: 0.22320217 | L9: 0.22326031 | M9: 0.2238321 | O9: Q3 | Q9: 0.078057242 | R9: 0.058728882 | S9: 0.053191489
A10: Q4 | B10: 14730 | C10: 15800 | D10: 16670 | E10: 17550 | F10: 64750 | H10: Q4 | I10: 0.28893684 | J10: 0.28345892 | K10: 0.28273406 | L10: 0.28269974 | M10: 0.28429048 | O10: Q4 | Q10: 0.072640869 | R10: 0.055063291 | S10: 0.052789442
A11: Total Result | B11: 50980 | C11: 55740 | D11: 58960 | E11: 62080 | F11: 227760 | H11: Total Result | I11: 1 | J11: 1 | K11: 1 | L11: 1 | M11: 1 | O11: Total Result | Q11: 0.093369949 | R11: 0.05776821 | S11: 0.052917232
A17: PT4. Average ICU utilisation % — Season × Year | H17: PT5. Annual KPI pivot (sums)
A18: Average - ICU_Util_Rate | B18: Year | H18: Year | I18: Data
A19: Season | B19: 2021 | C19: 2022 | D19: 2023 | E19: 2024 | F19: Total Result | H19: 2021 | I19: Sum - ER_Visits | J19: 50980
A20: Autumn | B20: 73.966667 | C20: 77.266667 | D20: 80.666667 | E20: 83.933333 | F20: 78.958333 | I20: Sum - Pub_Health_Exp | J20: 13760000
A21: Spring | B21: 65.166667 | C21: 69.633333 | D21: 72.8 | E21: 75.8 | F21: 70.85 | I21: Sum - Flu_Resp_Cases | J21: 12590
A22: Summer | B22: 61.066667 | C22: 64.1 | D22: 67.133333 | E22: 69.933333 | F22: 65.558333 | I22: Sum - ICU_Over_85 | J22: 1
A23: Winter | B23: 79.566667 | C23: 87.2 | D23: 91.3 | E23: 95.2 | F23: 88.316667 | H23: 2022 | I23: Sum - ER_Visits | J23: 55740
A24: Total Result | B24: 69.941667 | C24: 74.55 | D24: 77.975 | E24: 81.216667 | F24: 75.920833 | I24: Sum - Pub_Health_Exp | J24: 14690000
I25: Sum - Flu_Resp_Cases | J25: 14630
I26: Sum - ICU_Over_85 | J26: 2
H27: 2023 | I27: Sum - ER_Visits | J27: 58960
I28: Sum - Pub_Health_Exp | J28: 15390000
I29: Sum - Flu_Resp_Cases | J29: 15820
A30: PT6. Average ICU utilisation % — Month × Year | H30: PT7. Average $ per ER visit and flu cases — Season | I30: Sum - ICU_Over_85 | J30: 4
A31: Average - ICU_Util_Rate | B31: Year | H31: Season | I31: Data
A32: MonthNum | B32: 2021 | C32: 2022 | D32: 2023 | E32: 2024 | F32: Total Result | H32: Autumn | I32: Average - Exp_per_ER_Visit | J32: 259.83022
A33: 1 | B33: 78.4 | C33: 89.4 | D33: 93.2 | E33: 97.3 | F33: 89.575 | I33: Average - Flu_Resp_Cases | J33: 1387.5
A34: 2 | B34: 74.1 | C34: 82.1 | D34: 86.7 | E34: 90.4 | F34: 83.325 | I34: Average - ER_Visits | J34: 4960
A35: 3 | B35: 69.5 | C35: 74.8 | D35: 78.4 | E35: 81.7 | F35: 76.1 | H35: Spring | I35: Average - Exp_per_ER_Visit | J35: 268.62229
A36: 4 | B36: 64.2 | C36: 68.9 | D36: 71.9 | E36: 74.8 | F36: 69.95 | I36: Average - Flu_Resp_Cases | J36: 1006.6667
A37: 5 | B37: 61.8 | C37: 65.2 | D37: 68.1 | E37: 70.9 | F37: 66.5 | I37: Average - ER_Visits | J37: 4377.5
A38: 6 | B38: 59.4 | C38: 62.4 | D38: 65.4 | E38: 68.1 | F38: 63.825 | H38: Summer | I38: Average - Exp_per_ER_Visit | J38: 276.46924
A39: 7 | B39: 60.1 | C39: 63.1 | D39: 66.2 | E39: 69 | F39: 64.6 | I39: Average - Flu_Resp_Cases | J39: 851.66667
A40: 8 | B40: 63.7 | C40: 66.8 | D40: 69.8 | E40: 72.7 | F40: 68.25 | I40: Average - ER_Visits | J40: 4050.8333
A41: 9 | B41: 68.9 | C41: 71.5 | D41: 74.6 | E41: 77.6 | F41: 73.15 | H41: Winter | I41: Average - Exp_per_ER_Visit | J41: 254.12161
A42: 10 | B42: 73.2 | C42: 76.9 | D42: 80.3 | E42: 83.6 | F42: 78.5 | I42: Average - Flu_Resp_Cases | J42: 1766.6667
A43: 11 | B43: 79.8 | C43: 83.4 | D43: 87.1 | E43: 90.6 | F43: 85.225 | I43: Average - ER_Visits | J43: 5591.6667
A44: 12 | B44: 86.2 | C44: 90.1 | D44: 94 | E44: 97.9 | F44: 92.05 | H44: Total Average - Exp_per_ER_Visit | J44: 264.76084
A45: Total Result | B45: 69.941667 | C45: 74.55 | D45: 77.975 | E45: 81.216667 | F45: 75.920833 | H45: Total Average - Flu_Resp_Cases | J45: 1253.125
H46: Total Average - ER_Visits | J46: 4745

Sheet Pivot_Formulas
A1: Unit 4 · Cross-tabulations with calculated fields, % of column total and YoY growth
A2: SUMIFS / AVERAGEIFS / COUNTIFS on the Data sheet (native PivotTables are on the Pivot_Tables sheet)
A4: Table 1. ER visits — Quarter × Year (sum) | H4: Table 2. % of column (annual) total | O4: Table 3. Year-over-Year growth %
A5: Quarter | B5: 2021 | C5: 2022 | D5: 2023 | E5: 2024 | F5: Total | H5: Quarter | I5: 2021 | J5: 2022 | K5: 2023 | L5: 2024 | M5: All years | O5: Quarter | P5: 2022 vs 21 | Q5: 2023 vs 22 | R5: 2024 vs 23 | S5: CAGR 21–24
A6: Q1 | B6: =SUMIFS(Data!$I$2:$I$49,Data!$D$2:$D$49,$A6,Data!$C$2:$C$49,B$5) -> 13510 | C6: =SUMIFS(Data!$I$2:$I$49,Data!$D$2:$D$49,$A6,Data!$C$2:$C$49,C$5) -> 15410 | D6: =SUMIFS(Data!$I$2:$I$49,Data!$D$2:$D$49,$A6,Data!$C$2:$C$49,D$5) -> 16360 | E6: =SUMIFS(Data!$I$2:$I$49,Data!$D$2:$D$49,$A6,Data!$C$2:$C$49,E$5) -> 17240 | F6: =SUM(B6:E6) -> 62520 | H6: Q1 | I6: =B6/B$10 -> 0.26500588 | J6: =C6/C$10 -> 0.27646215 | K6: =D6/D$10 -> 0.27747626 | L6: =E6/E$10 -> 0.27770619 | M6: =F6/F$10 -> 0.27449947 | O6: Q1 | P6: =C6/B6-1 -> 0.14063657 | Q6: =D6/C6-1 -> 0.06164828 | R6: =E6/D6-1 -> 0.053789731 | S6: =(E6/B6)^(1/3)-1 -> 0.084660865
A7: Q2 | B7: =SUMIFS(Data!$I$2:$I$49,Data!$D$2:$D$49,$A7,Data!$C$2:$C$49,B$5) -> 11210 | C7: =SUMIFS(Data!$I$2:$I$49,Data!$D$2:$D$49,$A7,Data!$C$2:$C$49,C$5) -> 12100 | D7: =SUMIFS(Data!$I$2:$I$49,Data!$D$2:$D$49,$A7,Data!$C$2:$C$49,D$5) -> 12770 | E7: =SUMIFS(Data!$I$2:$I$49,Data!$D$2:$D$49,$A7,Data!$C$2:$C$49,E$5) -> 13430 | F7: =SUM(B7:E7) -> 49510 | H7: Q2 | I7: =B7/B$10 -> 0.21989015 | J7: =C7/C$10 -> 0.2170793 | K7: =D7/D$10 -> 0.21658752 | L7: =E7/E$10 -> 0.21633376 | M7: =F7/F$10 -> 0.21737794 | O7: Q2 | P7: =C7/B7-1 -> 0.079393399 | Q7: =D7/C7-1 -> 0.055371901 | R7: =E7/D7-1 -> 0.051683634 | S7: =(E7/B7)^(1/3)-1 -> 0.062078947
A8: Q3 | B8: =SUMIFS(Data!$I$2:$I$49,Data!$D$2:$D$49,$A8,Data!$C$2:$C$49,B$5) -> 11530 | C8: =SUMIFS(Data!$I$2:$I$49,Data!$D$2:$D$49,$A8,Data!$C$2:$C$49,C$5) -> 12430 | D8: =SUMIFS(Data!$I$2:$I$49,Data!$D$2:$D$49,$A8,Data!$C$2:$C$49,D$5) -> 13160 | E8: =SUMIFS(Data!$I$2:$I$49,Data!$D$2:$D$49,$A8,Data!$C$2:$C$49,E$5) -> 13860 | F8: =SUM(B8:E8) -> 50980 | H8: Q3 | I8: =B8/B$10 -> 0.22616712 | J8: =C8/C$10 -> 0.22299964 | K8: =D8/D$10 -> 0.22320217 | L8: =E8/E$10 -> 0.22326031 | M8: =F8/F$10 -> 0.2238321 | O8: Q3 | P8: =C8/B8-1 -> 0.078057242 | Q8: =D8/C8-1 -> 0.058728882 | R8: =E8/D8-1 -> 0.053191489 | S8: =(E8/B8)^(1/3)-1 -> 0.063272645
A9: Q4 | B9: =SUMIFS(Data!$I$2:$I$49,Data!$D$2:$D$49,$A9,Data!$C$2:$C$49,B$5) -> 14730 | C9: =SUMIFS(Data!$I$2:$I$49,Data!$D$2:$D$49,$A9,Data!$C$2:$C$49,C$5) -> 15800 | D9: =SUMIFS(Data!$I$2:$I$49,Data!$D$2:$D$49,$A9,Data!$C$2:$C$49,D$5) -> 16670 | E9: =SUMIFS(Data!$I$2:$I$49,Data!$D$2:$D$49,$A9,Data!$C$2:$C$49,E$5) -> 17550 | F9: =SUM(B9:E9) -> 64750 | H9: Q4 | I9: =B9/B$10 -> 0.28893684 | J9: =C9/C$10 -> 0.28345892 | K9: =D9/D$10 -> 0.28273406 | L9: =E9/E$10 -> 0.28269974 | M9: =F9/F$10 -> 0.28429048 | O9: Q4 | P9: =C9/B9-1 -> 0.072640869 | Q9: =D9/C9-1 -> 0.055063291 | R9: =E9/D9-1 -> 0.052789442 | S9: =(E9/B9)^(1/3)-1 -> 0.060127559
A10: Total | B10: =SUM(B6:B9) -> 50980 | C10: =SUM(C6:C9) -> 55740 | D10: =SUM(D6:D9) -> 58960 | E10: =SUM(E6:E9) -> 62080 | F10: =SUM(F6:F9) -> 227760 | O10: Total | P10: =C10/B10-1 -> 0.093369949 | Q10: =D10/C10-1 -> 0.05776821 | R10: =E10/D10-1 -> 0.052917232 | S10: =(E10/B10)^(1/3)-1 -> 0.067867311
A13: Table 4. Annual KPI pivot with calculated fields
A14: Year | B14: ER visits | C14: Flu cases | D14: Expenditure $ | E14: Mean ICU % | F14: Peak ICU % | G14: Months ICU>85% | H14: Mean vacc % | I14: Mean pop idx | J14: $ per ER visit | K14: ER visits per flu case | L14: YoY ER % | M14: YoY Exp % | N14: YoY $/visit %
A15: 2021 | B15: =SUMIFS(Data!$I$2:$I$49,Data!$C$2:$C$49,A15) -> 50980 | C15: =SUMIFS(Data!$N$2:$N$49,Data!$C$2:$C$49,A15) -> 12590 | D15: =SUMIFS(Data!$K$2:$K$49,Data!$C$2:$C$49,A15) -> 13760000 | E15: =AVERAGEIFS(Data!$J$2:$J$49,Data!$C$2:$C$49,A15) -> 69.941667 | F15: =SUMPRODUCT(MAX((Data!$C$2:$C$49=A15)*Data!$J$2:$J$49)) -> 86.2 | G15: =COUNTIFS(Data!$C$2:$C$49,A15,Data!$J$2:$J$49,">85") -> 1 | H15: =AVERAGEIFS(Data!$M$2:$M$49,Data!$C$2:$C$49,A15) -> 70.016667 | I15: =AVERAGEIFS(Data!$L$2:$L$49,Data!$C$2:$C$49,A15) -> 103.48333 | J15: =D15/B15 -> 269.90977 | K15: =B15/C15 -> 4.0492454
A16: 2022 | B16: =SUMIFS(Data!$I$2:$I$49,Data!$C$2:$C$49,A16) -> 55740 | C16: =SUMIFS(Data!$N$2:$N$49,Data!$C$2:$C$49,A16) -> 14630 | D16: =SUMIFS(Data!$K$2:$K$49,Data!$C$2:$C$49,A16) -> 14690000 | E16: =AVERAGEIFS(Data!$J$2:$J$49,Data!$C$2:$C$49,A16) -> 74.55 | F16: =SUMPRODUCT(MAX((Data!$C$2:$C$49=A16)*Data!$J$2:$J$49)) -> 90.1 | G16: =COUNTIFS(Data!$C$2:$C$49,A16,Data!$J$2:$J$49,">85") -> 2 | H16: =AVERAGEIFS(Data!$M$2:$M$49,Data!$C$2:$C$49,A16) -> 77.416667 | I16: =AVERAGEIFS(Data!$L$2:$L$49,Data!$C$2:$C$49,A16) -> 106.25 | J16: =D16/B16 -> 263.54503 | K16: =B16/C16 -> 3.8099795 | L16: =B16/B15-1 -> 0.093369949 | M16: =D16/D15-1 -> 0.067587209 | N16: =J16/J15-1 -> -0.023580984
A17: 2023 | B17: =SUMIFS(Data!$I$2:$I$49,Data!$C$2:$C$49,A17) -> 58960 | C17: =SUMIFS(Data!$N$2:$N$49,Data!$C$2:$C$49,A17) -> 15820 | D17: =SUMIFS(Data!$K$2:$K$49,Data!$C$2:$C$49,A17) -> 15390000 | E17: =AVERAGEIFS(Data!$J$2:$J$49,Data!$C$2:$C$49,A17) -> 77.975 | F17: =SUMPRODUCT(MAX((Data!$C$2:$C$49=A17)*Data!$J$2:$J$49)) -> 94 | G17: =COUNTIFS(Data!$C$2:$C$49,A17,Data!$J$2:$J$49,">85") -> 4 | H17: =AVERAGEIFS(Data!$M$2:$M$49,Data!$C$2:$C$49,A17) -> 82.966667 | I17: =AVERAGEIFS(Data!$L$2:$L$49,Data!$C$2:$C$49,A17) -> 109.34167 | J17: =D17/B17 -> 261.02442 | K17: =B17/C17 -> 3.7269279 | L17: =B17/B16-1 -> 0.05776821 | M17: =D17/D16-1 -> 0.047651464 | N17: =J17/J16-1 -> -0.0095642371
A18: 2024 | B18: =SUMIFS(Data!$I$2:$I$49,Data!$C$2:$C$49,A18) -> 62080 | C18: =SUMIFS(Data!$N$2:$N$49,Data!$C$2:$C$49,A18) -> 17110 | D18: =SUMIFS(Data!$K$2:$K$49,Data!$C$2:$C$49,A18) -> 16120000 | E18: =AVERAGEIFS(Data!$J$2:$J$49,Data!$C$2:$C$49,A18) -> 81.216667 | F18: =SUMPRODUCT(MAX((Data!$C$2:$C$49=A18)*Data!$J$2:$J$49)) -> 97.9 | G18: =COUNTIFS(Data!$C$2:$C$49,A18,Data!$J$2:$J$49,">85") -> 4 | H18: =AVERAGEIFS(Data!$M$2:$M$49,Data!$C$2:$C$49,A18) -> 88.208333 | I18: =AVERAGEIFS(Data!$L$2:$L$49,Data!$C$2:$C$49,A18) -> 112.63333 | J18: =D18/B18 -> 259.66495 | K18: =B18/C18 -> 3.6282876 | L18: =B18/B17-1 -> 0.052917232 | M18: =D18/D17-1 -> 0.047433398 | N18: =J18/J17-1 -> -0.0052082287
A21: Table 5. Mean ICU utilisation % — Season × Year | H21: Table 6. Seasonal share of annual ER visits (% of column total)
A22: Season | B22: 2021 | C22: 2022 | D22: 2023 | E22: 2024 | F22: Change 21→24 (pp) | H22: Season | I22: 2021 | J22: 2022 | K22: 2023 | L22: 2024
A23: Winter | B23: =AVERAGEIFS(Data!$J$2:$J$49,Data!$F$2:$F$49,$A23,Data!$C$2:$C$49,B$22) -> 79.566667 | C23: =AVERAGEIFS(Data!$J$2:$J$49,Data!$F$2:$F$49,$A23,Data!$C$2:$C$49,C$22) -> 87.2 | D23: =AVERAGEIFS(Data!$J$2:$J$49,Data!$F$2:$F$49,$A23,Data!$C$2:$C$49,D$22) -> 91.3 | E23: =AVERAGEIFS(Data!$J$2:$J$49,Data!$F$2:$F$49,$A23,Data!$C$2:$C$49,E$22) -> 95.2 | F23: =E23-B23 -> 15.633333 | H23: Winter | I23: =SUMIFS(Data!$I$2:$I$49,Data!$F$2:$F$49,$H23,Data!$C$2:$C$49,I$22)/SUMIFS(Data!$I$2:$I$49,Data!$C$2:$C$49,I$22) -> 0.28775991 | J23: =SUMIFS(Data!$I$2:$I$49,Data!$F$2:$F$49,$H23,Data!$C$2:$C$49,J$22)/SUMIFS(Data!$I$2:$I$49,Data!$C$2:$C$49,J$22) -> 0.29619663 | K23: =SUMIFS(Data!$I$2:$I$49,Data!$F$2:$F$49,$H23,Data!$C$2:$C$49,K$22)/SUMIFS(Data!$I$2:$I$49,Data!$C$2:$C$49,K$22) -> 0.29664179 | L23: =SUMIFS(Data!$I$2:$I$49,Data!$F$2:$F$49,$H23,Data!$C$2:$C$49,L$22)/SUMIFS(Data!$I$2:$I$49,Data!$C$2:$C$49,L$22) -> 0.296875
A24: Spring | B24: =AVERAGEIFS(Data!$J$2:$J$49,Data!$F$2:$F$49,$A24,Data!$C$2:$C$49,B$22) -> 65.166667 | C24: =AVERAGEIFS(Data!$J$2:$J$49,Data!$F$2:$F$49,$A24,Data!$C$2:$C$49,C$22) -> 69.633333 | D24: =AVERAGEIFS(Data!$J$2:$J$49,Data!$F$2:$F$49,$A24,Data!$C$2:$C$49,D$22) -> 72.8 | E24: =AVERAGEIFS(Data!$J$2:$J$49,Data!$F$2:$F$49,$A24,Data!$C$2:$C$49,E$22) -> 75.8 | F24: =E24-B24 -> 10.633333 | H24: Spring | I24: =SUMIFS(Data!$I$2:$I$49,Data!$F$2:$F$49,$H24,Data!$C$2:$C$49,I$22)/SUMIFS(Data!$I$2:$I$49,Data!$C$2:$C$49,I$22) -> 0.23165947 | J24: =SUMIFS(Data!$I$2:$I$49,Data!$F$2:$F$49,$H24,Data!$C$2:$C$49,J$22)/SUMIFS(Data!$I$2:$I$49,Data!$C$2:$C$49,J$22) -> 0.23053463 | K24: =SUMIFS(Data!$I$2:$I$49,Data!$F$2:$F$49,$H24,Data!$C$2:$C$49,K$22)/SUMIFS(Data!$I$2:$I$49,Data!$C$2:$C$49,K$22) -> 0.23032564 | L24: =SUMIFS(Data!$I$2:$I$49,Data!$F$2:$F$49,$H24,Data!$C$2:$C$49,L$22)/SUMIFS(Data!$I$2:$I$49,Data!$C$2:$C$49,L$22) -> 0.23018686
A25: Summer | B25: =AVERAGEIFS(Data!$J$2:$J$49,Data!$F$2:$F$49,$A25,Data!$C$2:$C$49,B$22) -> 61.066667 | C25: =AVERAGEIFS(Data!$J$2:$J$49,Data!$F$2:$F$49,$A25,Data!$C$2:$C$49,C$22) -> 64.1 | D25: =AVERAGEIFS(Data!$J$2:$J$49,Data!$F$2:$F$49,$A25,Data!$C$2:$C$49,D$22) -> 67.133333 | E25: =AVERAGEIFS(Data!$J$2:$J$49,Data!$F$2:$F$49,$A25,Data!$C$2:$C$49,E$22) -> 69.933333 | F25: =E25-B25 -> 8.8666667 | H25: Summer | I25: =SUMIFS(Data!$I$2:$I$49,Data!$F$2:$F$49,$H25,Data!$C$2:$C$49,I$22)/SUMIFS(Data!$I$2:$I$49,Data!$C$2:$C$49,I$22) -> 0.21557474 | J25: =SUMIFS(Data!$I$2:$I$49,Data!$F$2:$F$49,$H25,Data!$C$2:$C$49,J$22)/SUMIFS(Data!$I$2:$I$49,Data!$C$2:$C$49,J$22) -> 0.21277359 | K25: =SUMIFS(Data!$I$2:$I$49,Data!$F$2:$F$49,$H25,Data!$C$2:$C$49,K$22)/SUMIFS(Data!$I$2:$I$49,Data!$C$2:$C$49,K$22) -> 0.21285617 | L25: =SUMIFS(Data!$I$2:$I$49,Data!$F$2:$F$49,$H25,Data!$C$2:$C$49,L$22)/SUMIFS(Data!$I$2:$I$49,Data!$C$2:$C$49,L$22) -> 0.21278995
A26: Autumn | B26: =AVERAGEIFS(Data!$J$2:$J$49,Data!$F$2:$F$49,$A26,Data!$C$2:$C$49,B$22) -> 73.966667 | C26: =AVERAGEIFS(Data!$J$2:$J$49,Data!$F$2:$F$49,$A26,Data!$C$2:$C$49,C$22) -> 77.266667 | D26: =AVERAGEIFS(Data!$J$2:$J$49,Data!$F$2:$F$49,$A26,Data!$C$2:$C$49,D$22) -> 80.666667 | E26: =AVERAGEIFS(Data!$J$2:$J$49,Data!$F$2:$F$49,$A26,Data!$C$2:$C$49,E$22) -> 83.933333 | F26: =E26-B26 -> 9.9666667 | H26: Autumn | I26: =SUMIFS(Data!$I$2:$I$49,Data!$F$2:$F$49,$H26,Data!$C$2:$C$49,I$22)/SUMIFS(Data!$I$2:$I$49,Data!$C$2:$C$49,I$22) -> 0.26500588 | J26: =SUMIFS(Data!$I$2:$I$49,Data!$F$2:$F$49,$H26,Data!$C$2:$C$49,J$22)/SUMIFS(Data!$I$2:$I$49,Data!$C$2:$C$49,J$22) -> 0.26049516 | K26: =SUMIFS(Data!$I$2:$I$49,Data!$F$2:$F$49,$H26,Data!$C$2:$C$49,K$22)/SUMIFS(Data!$I$2:$I$49,Data!$C$2:$C$49,K$22) -> 0.26017639 | L26: =SUMIFS(Data!$I$2:$I$49,Data!$F$2:$F$49,$H26,Data!$C$2:$C$49,L$22)/SUMIFS(Data!$I$2:$I$49,Data!$C$2:$C$49,L$22) -> 0.2601482
A29: Table 7. ICU utilisation % — Month × Year (red = above 85% safe-occupancy threshold)
A30: Month | B30: 2021 | C30: 2022 | D30: 2023 | E30: 2024
A31: 1 | B31: =AVERAGEIFS(Data!$J$2:$J$49,Data!$E$2:$E$49,$A31,Data!$C$2:$C$49,B$30) -> 78.4 | C31: =AVERAGEIFS(Data!$J$2:$J$49,Data!$E$2:$E$49,$A31,Data!$C$2:$C$49,C$30) -> 89.4 | D31: =AVERAGEIFS(Data!$J$2:$J$49,Data!$E$2:$E$49,$A31,Data!$C$2:$C$49,D$30) -> 93.2 | E31: =AVERAGEIFS(Data!$J$2:$J$49,Data!$E$2:$E$49,$A31,Data!$C$2:$C$49,E$30) -> 97.3
A32: 2 | B32: =AVERAGEIFS(Data!$J$2:$J$49,Data!$E$2:$E$49,$A32,Data!$C$2:$C$49,B$30) -> 74.1 | C32: =AVERAGEIFS(Data!$J$2:$J$49,Data!$E$2:$E$49,$A32,Data!$C$2:$C$49,C$30) -> 82.1 | D32: =AVERAGEIFS(Data!$J$2:$J$49,Data!$E$2:$E$49,$A32,Data!$C$2:$C$49,D$30) -> 86.7 | E32: =AVERAGEIFS(Data!$J$2:$J$49,Data!$E$2:$E$49,$A32,Data!$C$2:$C$49,E$30) -> 90.4
A33: 3 | B33: =AVERAGEIFS(Data!$J$2:$J$49,Data!$E$2:$E$49,$A33,Data!$C$2:$C$49,B$30) -> 69.5 | C33: =AVERAGEIFS(Data!$J$2:$J$49,Data!$E$2:$E$49,$A33,Data!$C$2:$C$49,C$30) -> 74.8 | D33: =AVERAGEIFS(Data!$J$2:$J$49,Data!$E$2:$E$49,$A33,Data!$C$2:$C$49,D$30) -> 78.4 | E33: =AVERAGEIFS(Data!$J$2:$J$49,Data!$E$2:$E$49,$A33,Data!$C$2:$C$49,E$30) -> 81.7
A34: 4 | B34: =AVERAGEIFS(Data!$J$2:$J$49,Data!$E$2:$E$49,$A34,Data!$C$2:$C$49,B$30) -> 64.2 | C34: =AVERAGEIFS(Data!$J$2:$J$49,Data!$E$2:$E$49,$A34,Data!$C$2:$C$49,C$30) -> 68.9 | D34: =AVERAGEIFS(Data!$J$2:$J$49,Data!$E$2:$E$49,$A34,Data!$C$2:$C$49,D$30) -> 71.9 | E34: =AVERAGEIFS(Data!$J$2:$J$49,Data!$E$2:$E$49,$A34,Data!$C$2:$C$49,E$30) -> 74.8
A35: 5 | B35: =AVERAGEIFS(Data!$J$2:$J$49,Data!$E$2:$E$49,$A35,Data!$C$2:$C$49,B$30) -> 61.8 | C35: =AVERAGEIFS(Data!$J$2:$J$49,Data!$E$2:$E$49,$A35,Data!$C$2:$C$49,C$30) -> 65.2 | D35: =AVERAGEIFS(Data!$J$2:$J$49,Data!$E$2:$E$49,$A35,Data!$C$2:$C$49,D$30) -> 68.1 | E35: =AVERAGEIFS(Data!$J$2:$J$49,Data!$E$2:$E$49,$A35,Data!$C$2:$C$49,E$30) -> 70.9
A36: 6 | B36: =AVERAGEIFS(Data!$J$2:$J$49,Data!$E$2:$E$49,$A36,Data!$C$2:$C$49,B$30) -> 59.4 | C36: =AVERAGEIFS(Data!$J$2:$J$49,Data!$E$2:$E$49,$A36,Data!$C$2:$C$49,C$30) -> 62.4 | D36: =AVERAGEIFS(Data!$J$2:$J$49,Data!$E$2:$E$49,$A36,Data!$C$2:$C$49,D$30) -> 65.4 | E36: =AVERAGEIFS(Data!$J$2:$J$49,Data!$E$2:$E$49,$A36,Data!$C$2:$C$49,E$30) -> 68.1
A37: 7 | B37: =AVERAGEIFS(Data!$J$2:$J$49,Data!$E$2:$E$49,$A37,Data!$C$2:$C$49,B$30) -> 60.1 | C37: =AVERAGEIFS(Data!$J$2:$J$49,Data!$E$2:$E$49,$A37,Data!$C$2:$C$49,C$30) -> 63.1 | D37: =AVERAGEIFS(Data!$J$2:$J$49,Data!$E$2:$E$49,$A37,Data!$C$2:$C$49,D$30) -> 66.2 | E37: =AVERAGEIFS(Data!$J$2:$J$49,Data!$E$2:$E$49,$A37,Data!$C$2:$C$49,E$30) -> 69
A38: 8 | B38: =AVERAGEIFS(Data!$J$2:$J$49,Data!$E$2:$E$49,$A38,Data!$C$2:$C$49,B$30) -> 63.7 | C38: =AVERAGEIFS(Data!$J$2:$J$49,Data!$E$2:$E$49,$A38,Data!$C$2:$C$49,C$30) -> 66.8 | D38: =AVERAGEIFS(Data!$J$2:$J$49,Data!$E$2:$E$49,$A38,Data!$C$2:$C$49,D$30) -> 69.8 | E38: =AVERAGEIFS(Data!$J$2:$J$49,Data!$E$2:$E$49,$A38,Data!$C$2:$C$49,E$30) -> 72.7
A39: 9 | B39: =AVERAGEIFS(Data!$J$2:$J$49,Data!$E$2:$E$49,$A39,Data!$C$2:$C$49,B$30) -> 68.9 | C39: =AVERAGEIFS(Data!$J$2:$J$49,Data!$E$2:$E$49,$A39,Data!$C$2:$C$49,C$30) -> 71.5 | D39: =AVERAGEIFS(Data!$J$2:$J$49,Data!$E$2:$E$49,$A39,Data!$C$2:$C$49,D$30) -> 74.6 | E39: =AVERAGEIFS(Data!$J$2:$J$49,Data!$E$2:$E$49,$A39,Data!$C$2:$C$49,E$30) -> 77.6
A40: 10 | B40: =AVERAGEIFS(Data!$J$2:$J$49,Data!$E$2:$E$49,$A40,Data!$C$2:$C$49,B$30) -> 73.2 | C40: =AVERAGEIFS(Data!$J$2:$J$49,Data!$E$2:$E$49,$A40,Data!$C$2:$C$49,C$30) -> 76.9 | D40: =AVERAGEIFS(Data!$J$2:$J$49,Data!$E$2:$E$49,$A40,Data!$C$2:$C$49,D$30) -> 80.3 | E40: =AVERAGEIFS(Data!$J$2:$J$49,Data!$E$2:$E$49,$A40,Data!$C$2:$C$49,E$30) -> 83.6
A41: 11 | B41: =AVERAGEIFS(Data!$J$2:$J$49,Data!$E$2:$E$49,$A41,Data!$C$2:$C$49,B$30) -> 79.8 | C41: =AVERAGEIFS(Data!$J$2:$J$49,Data!$E$2:$E$49,$A41,Data!$C$2:$C$49,C$30) -> 83.4 | D41: =AVERAGEIFS(Data!$J$2:$J$49,Data!$E$2:$E$49,$A41,Data!$C$2:$C$49,D$30) -> 87.1 | E41: =AVERAGEIFS(Data!$J$2:$J$49,Data!$E$2:$E$49,$A41,Data!$C$2:$C$49,E$30) -> 90.6
A42: 12 | B42: =AVERAGEIFS(Data!$J$2:$J$49,Data!$E$2:$E$49,$A42,Data!$C$2:$C$49,B$30) -> 86.2 | C42: =AVERAGEIFS(Data!$J$2:$J$49,Data!$E$2:$E$49,$A42,Data!$C$2:$C$49,C$30) -> 90.1 | D42: =AVERAGEIFS(Data!$J$2:$J$49,Data!$E$2:$E$49,$A42,Data!$C$2:$C$49,D$30) -> 94 | E42: =AVERAGEIFS(Data!$J$2:$J$49,Data!$E$2:$E$49,$A42,Data!$C$2:$C$49,E$30) -> 97.9
A43: Months > 85% | B43: =COUNTIF(B31:B42,">85") -> 1 | C43: =COUNTIF(C31:C42,">85") -> 2 | D43: =COUNTIF(D31:D42,">85") -> 4 | E43: =COUNTIF(E31:E42,">85") -> 4

Sheet Correlation
A1: Unit 4 · Correlation matrix heat map (Pearson r) and significance
A2: Colour scale: red = −1, grey = 0, blue = +1
A4: r | B4: ER_Visits | C4: ICU_Util_Rate | D4: Pub_Health_Exp | E4: Pop_Density_Idx | F4: Vacc_Coverage | G4: Flu_Resp_Cases
A5: ER_Visits | B5: =CORREL(Data!$I$2:$I$49,Data!$I$2:$I$49) -> 1 | C5: =CORREL(Data!$I$2:$I$49,Data!$J$2:$J$49) -> 0.99645458 | D5: =CORREL(Data!$I$2:$I$49,Data!$K$2:$K$49) -> 0.99772628 | E5: =CORREL(Data!$I$2:$I$49,Data!$L$2:$L$49) -> 0.47286856 | F5: =CORREL(Data!$I$2:$I$49,Data!$M$2:$M$49) -> 0.42186539 | G5: =CORREL(Data!$I$2:$I$49,Data!$N$2:$N$49) -> 0.98759393
A6: ICU_Util_Rate | B6: =CORREL(Data!$J$2:$J$49,Data!$I$2:$I$49) -> 0.99645458 | C6: =CORREL(Data!$J$2:$J$49,Data!$J$2:$J$49) -> 1 | D6: =CORREL(Data!$J$2:$J$49,Data!$K$2:$K$49) -> 0.99136608 | E6: =CORREL(Data!$J$2:$J$49,Data!$L$2:$L$49) -> 0.41012692 | F6: =CORREL(Data!$J$2:$J$49,Data!$M$2:$M$49) -> 0.35805243 | G6: =CORREL(Data!$J$2:$J$49,Data!$N$2:$N$49) -> 0.99301223
A7: Pub_Health_Exp | B7: =CORREL(Data!$K$2:$K$49,Data!$I$2:$I$49) -> 0.99772628 | C7: =CORREL(Data!$K$2:$K$49,Data!$J$2:$J$49) -> 0.99136608 | D7: =CORREL(Data!$K$2:$K$49,Data!$K$2:$K$49) -> 1 | E7: =CORREL(Data!$K$2:$K$49,Data!$L$2:$L$49) -> 0.5018227 | F7: =CORREL(Data!$K$2:$K$49,Data!$M$2:$M$49) -> 0.45326942 | G7: =CORREL(Data!$K$2:$K$49,Data!$N$2:$N$49) -> 0.98298921
A8: Pop_Density_Idx | B8: =CORREL(Data!$L$2:$L$49,Data!$I$2:$I$49) -> 0.47286856 | C8: =CORREL(Data!$L$2:$L$49,Data!$J$2:$J$49) -> 0.41012692 | D8: =CORREL(Data!$L$2:$L$49,Data!$K$2:$K$49) -> 0.5018227 | E8: =CORREL(Data!$L$2:$L$49,Data!$L$2:$L$49) -> 1 | F8: =CORREL(Data!$L$2:$L$49,Data!$M$2:$M$49) -> 0.97301257 | G8: =CORREL(Data!$L$2:$L$49,Data!$N$2:$N$49) -> 0.34868759
A9: Vacc_Coverage | B9: =CORREL(Data!$M$2:$M$49,Data!$I$2:$I$49) -> 0.42186539 | C9: =CORREL(Data!$M$2:$M$49,Data!$J$2:$J$49) -> 0.35805243 | D9: =CORREL(Data!$M$2:$M$49,Data!$K$2:$K$49) -> 0.45326942 | E9: =CORREL(Data!$M$2:$M$49,Data!$L$2:$L$49) -> 0.97301257 | F9: =CORREL(Data!$M$2:$M$49,Data!$M$2:$M$49) -> 1 | G9: =CORREL(Data!$M$2:$M$49,Data!$N$2:$N$49) -> 0.30306456
A10: Flu_Resp_Cases | B10: =CORREL(Data!$N$2:$N$49,Data!$I$2:$I$49) -> 0.98759393 | C10: =CORREL(Data!$N$2:$N$49,Data!$J$2:$J$49) -> 0.99301223 | D10: =CORREL(Data!$N$2:$N$49,Data!$K$2:$K$49) -> 0.98298921 | E10: =CORREL(Data!$N$2:$N$49,Data!$L$2:$L$49) -> 0.34868759 | F10: =CORREL(Data!$N$2:$N$49,Data!$M$2:$M$49) -> 0.30306456 | G10: =CORREL(Data!$N$2:$N$49,Data!$N$2:$N$49) -> 1
A12: p-values (H0: ρ = 0), t = r·√((n−2)/(1−r²))
A13: p | B13: ER_Visits | C13: ICU_Util_Rate | D13: Pub_Health_Exp | E13: Pop_Density_Idx | F13: Vacc_Coverage | G13: Flu_Resp_Cases
A14: ER_Visits | B14: =IF(ABS(B5)>=0.999999,0,_xlfn.T.DIST.2T(ABS(B5)*SQRT(46/(1-B5^2)),46)) -> 0 | C14: =IF(ABS(C5)>=0.999999,0,_xlfn.T.DIST.2T(ABS(C5)*SQRT(46/(1-C5^2)),46)) -> 4.1496985e-51 | D14: =IF(ABS(D5)>=0.999999,0,_xlfn.T.DIST.2T(ABS(D5)*SQRT(46/(1-D5^2)),46)) -> 1.5360586e-55 | E14: =IF(ABS(E5)>=0.999999,0,_xlfn.T.DIST.2T(ABS(E5)*SQRT(46/(1-E5^2)),46)) -> 0.00068884235 | F14: =IF(ABS(F5)>=0.999999,0,_xlfn.T.DIST.2T(ABS(F5)*SQRT(46/(1-F5^2)),46)) -> 0.0028219174 | G14: =IF(ABS(G5)>=0.999999,0,_xlfn.T.DIST.2T(ABS(G5)*SQRT(46/(1-G5^2)),46)) -> 1.2260671e-38
A15: ICU_Util_Rate | B15: =IF(ABS(B6)>=0.999999,0,_xlfn.T.DIST.2T(ABS(B6)*SQRT(46/(1-B6^2)),46)) -> 4.1496985e-51 | C15: =IF(ABS(C6)>=0.999999,0,_xlfn.T.DIST.2T(ABS(C6)*SQRT(46/(1-C6^2)),46)) -> 0 | D15: =IF(ABS(D6)>=0.999999,0,_xlfn.T.DIST.2T(ABS(D6)*SQRT(46/(1-D6^2)),46)) -> 3.0553667e-42 | E15: =IF(ABS(E6)>=0.999999,0,_xlfn.T.DIST.2T(ABS(E6)*SQRT(46/(1-E6^2)),46)) -> 0.0037904492 | F15: =IF(ABS(F6)>=0.999999,0,_xlfn.T.DIST.2T(ABS(F6)*SQRT(46/(1-F6^2)),46)) -> 0.012464113 | G15: =IF(ABS(G6)>=0.999999,0,_xlfn.T.DIST.2T(ABS(G6)*SQRT(46/(1-G6^2)),46)) -> 2.3967981e-44
A16: Pub_Health_Exp | B16: =IF(ABS(B7)>=0.999999,0,_xlfn.T.DIST.2T(ABS(B7)*SQRT(46/(1-B7^2)),46)) -> 1.5360586e-55 | C16: =IF(ABS(C7)>=0.999999,0,_xlfn.T.DIST.2T(ABS(C7)*SQRT(46/(1-C7^2)),46)) -> 3.0553667e-42 | D16: =IF(ABS(D7)>=0.999999,0,_xlfn.T.DIST.2T(ABS(D7)*SQRT(46/(1-D7^2)),46)) -> 0 | E16: =IF(ABS(E7)>=0.999999,0,_xlfn.T.DIST.2T(ABS(E7)*SQRT(46/(1-E7^2)),46)) -> 0.00027924091 | F16: =IF(ABS(F7)>=0.999999,0,_xlfn.T.DIST.2T(ABS(F7)*SQRT(46/(1-F7^2)),46)) -> 0.0012152093 | G16: =IF(ABS(G7)>=0.999999,0,_xlfn.T.DIST.2T(ABS(G7)*SQRT(46/(1-G7^2)),46)) -> 1.6610028e-35
A17: Pop_Density_Idx | B17: =IF(ABS(B8)>=0.999999,0,_xlfn.T.DIST.2T(ABS(B8)*SQRT(46/(1-B8^2)),46)) -> 0.00068884235 | C17: =IF(ABS(C8)>=0.999999,0,_xlfn.T.DIST.2T(ABS(C8)*SQRT(46/(1-C8^2)),46)) -> 0.0037904492 | D17: =IF(ABS(D8)>=0.999999,0,_xlfn.T.DIST.2T(ABS(D8)*SQRT(46/(1-D8^2)),46)) -> 0.00027924091 | E17: =IF(ABS(E8)>=0.999999,0,_xlfn.T.DIST.2T(ABS(E8)*SQRT(46/(1-E8^2)),46)) -> 0 | F17: =IF(ABS(F8)>=0.999999,0,_xlfn.T.DIST.2T(ABS(F8)*SQRT(46/(1-F8^2)),46)) -> 6.0852124e-31 | G17: =IF(ABS(G8)>=0.999999,0,_xlfn.T.DIST.2T(ABS(G8)*SQRT(46/(1-G8^2)),46)) -> 0.015146059
A18: Vacc_Coverage | B18: =IF(ABS(B9)>=0.999999,0,_xlfn.T.DIST.2T(ABS(B9)*SQRT(46/(1-B9^2)),46)) -> 0.0028219174 | C18: =IF(ABS(C9)>=0.999999,0,_xlfn.T.DIST.2T(ABS(C9)*SQRT(46/(1-C9^2)),46)) -> 0.012464113 | D18: =IF(ABS(D9)>=0.999999,0,_xlfn.T.DIST.2T(ABS(D9)*SQRT(46/(1-D9^2)),46)) -> 0.0012152093 | E18: =IF(ABS(E9)>=0.999999,0,_xlfn.T.DIST.2T(ABS(E9)*SQRT(46/(1-E9^2)),46)) -> 6.0852124e-31 | F18: =IF(ABS(F9)>=0.999999,0,_xlfn.T.DIST.2T(ABS(F9)*SQRT(46/(1-F9^2)),46)) -> 0 | G18: =IF(ABS(G9)>=0.999999,0,_xlfn.T.DIST.2T(ABS(G9)*SQRT(46/(1-G9^2)),46)) -> 0.036271653
A19: Flu_Resp_Cases | B19: =IF(ABS(B10)>=0.999999,0,_xlfn.T.DIST.2T(ABS(B10)*SQRT(46/(1-B10^2)),46)) -> 1.2260671e-38 | C19: =IF(ABS(C10)>=0.999999,0,_xlfn.T.DIST.2T(ABS(C10)*SQRT(46/(1-C10^2)),46)) -> 2.3967981e-44 | D19: =IF(ABS(D10)>=0.999999,0,_xlfn.T.DIST.2T(ABS(D10)*SQRT(46/(1-D10^2)),46)) -> 1.6610028e-35 | E19: =IF(ABS(E10)>=0.999999,0,_xlfn.T.DIST.2T(ABS(E10)*SQRT(46/(1-E10^2)),46)) -> 0.015146059 | F19: =IF(ABS(F10)>=0.999999,0,_xlfn.T.DIST.2T(ABS(F10)*SQRT(46/(1-F10^2)),46)) -> 0.036271653 | G19: =IF(ABS(G10)>=0.999999,0,_xlfn.T.DIST.2T(ABS(G10)*SQRT(46/(1-G10^2)),46)) -> 0
A21: Two clusters: seasonal demand (ER, ICU, expenditure, flu; r ≥ 0.98) and structural trend (population density, vaccination; r = 0.97). Expenditure and ICU are outcomes of demand and are not used as regression predictors.

Sheet Decomposition
A1: Unit 6 · Classical decomposition of ER visits (period = 12)
A2: Trend = 2×12 centred moving average; seasonal index = average ratio-to-MA by month, normalised to mean 1 (multiplicative) or 0 (additive)
A4: Date | B4: t | C4: Month | D4: ER visits (Y) | E4: Trend: 2×12 CMA | F4: Ratio Y/CMA | G4: Y − CMA | H4: Seasonal index (mult) | I4: Deseasonalised Y/S | J4: Irregular (mult) | K4: Seasonal (add) | L4: Irregular (add) | M4: Irregular % | N4: Irregular z | O4: Mult irregular (visits) | Q4: Seasonal indices
A5: =Data!B2 -> 44197 | B5: 1 | C5: =MONTH(A5) -> 1 | D5: =Data!I2 -> 4820 | F5: =IF(E5="","",D5/E5) | G5: =IF(E5="","",D5-E5) | H5: =INDEX($S$6:$S$17,C5) -> 1.2492676 | I5: =D5/H5 -> 3858.2605 | J5: =IF(E5="","",D5/(E5*H5)) | K5: =INDEX($U$6:$U$17,C5) -> 1191.088 | L5: =IF(E5="","",D5-E5-K5) | M5: =IF(E5="","",(J5-1)*100) | N5: =IF(E5="","",(M5-AVERAGE($M$5:$M$52))/_xlfn.STDEV.S($M$5:$M$52)) | O5: =IF(E5="","",(J5-1)*E5) | Q5: Month | R5: Raw mult | S5: Normalised mult | T5: Raw add | U5: Normalised add
A6: =Data!B3 -> 44228 | B6: 2 | C6: =MONTH(A6) -> 2 | D6: =Data!I3 -> 4510 | F6: =IF(E6="","",D6/E6) | G6: =IF(E6="","",D6-E6) | H6: =INDEX($S$6:$S$17,C6) -> 1.1425117 | I6: =D6/H6 -> 3947.4432 | J6: =IF(E6="","",D6/(E6*H6)) | K6: =INDEX($U$6:$U$17,C6) -> 683.44907 | L6: =IF(E6="","",D6-E6-K6) | M6: =IF(E6="","",(J6-1)*100) | N6: =IF(E6="","",(M6-AVERAGE($M$5:$M$52))/_xlfn.STDEV.S($M$5:$M$52)) | O6: =IF(E6="","",(J6-1)*E6) | Q6: 1 | R6: =AVERAGEIF($C$5:$C$52,Q6,$F$5:$F$52) -> 1.2495665 | S6: =R6/AVERAGE($R$6:$R$17) -> 1.2492676 | T6: =AVERAGEIF($C$5:$C$52,Q6,$G$5:$G$52) -> 1192.2222 | U6: =T6-AVERAGE($T$6:$T$17) -> 1191.088
A7: =Data!B4 -> 44256 | B7: 3 | C7: =MONTH(A7) -> 3 | D7: =Data!I4 -> 4180 | F7: =IF(E7="","",D7/E7) | G7: =IF(E7="","",D7-E7) | H7: =INDEX($S$6:$S$17,C7) -> 1.0127776 | I7: =D7/H7 -> 4127.2635 | J7: =IF(E7="","",D7/(E7*H7)) | K7: =INDEX($U$6:$U$17,C7) -> 61.365741 | L7: =IF(E7="","",D7-E7-K7) | M7: =IF(E7="","",(J7-1)*100) | N7: =IF(E7="","",(M7-AVERAGE($M$5:$M$52))/_xlfn.STDEV.S($M$5:$M$52)) | O7: =IF(E7="","",(J7-1)*E7) | Q7: 2 | R7: =AVERAGEIF($C$5:$C$52,Q7,$F$5:$F$52) -> 1.142785 | S7: =R7/AVERAGE($R$6:$R$17) -> 1.1425117 | T7: =AVERAGEIF($C$5:$C$52,Q7,$G$5:$G$52) -> 684.58333 | U7: =T7-AVERAGE($T$6:$T$17) -> 683.44907
A8: =Data!B5 -> 44287 | B8: 4 | C8: =MONTH(A8) -> 4 | D8: =Data!I5 -> 3920 | F8: =IF(E8="","",D8/E8) | G8: =IF(E8="","",D8-E8) | H8: =INDEX($S$6:$S$17,C8) -> 0.92057255 | I8: =D8/H8 -> 4258.2195 | J8: =IF(E8="","",D8/(E8*H8)) | K8: =INDEX($U$6:$U$17,C8) -> -385.5787 | L8: =IF(E8="","",D8-E8-K8) | M8: =IF(E8="","",(J8-1)*100) | N8: =IF(E8="","",(M8-AVERAGE($M$5:$M$52))/_xlfn.STDEV.S($M$5:$M$52)) | O8: =IF(E8="","",(J8-1)*E8) | Q8: 3 | R8: =AVERAGEIF($C$5:$C$52,Q8,$F$5:$F$52) -> 1.0130199 | S8: =R8/AVERAGE($R$6:$R$17) -> 1.0127776 | T8: =AVERAGEIF($C$5:$C$52,Q8,$G$5:$G$52) -> 62.5 | U8: =T8-AVERAGE($T$6:$T$17) -> 61.365741
A9: =Data!B6 -> 44317 | B9: 5 | C9: =MONTH(A9) -> 5 | D9: =Data!I6 -> 3710 | F9: =IF(E9="","",D9/E9) | G9: =IF(E9="","",D9-E9) | H9: =INDEX($S$6:$S$17,C9) -> 0.86852134 | I9: =D9/H9 -> 4271.6279 | J9: =IF(E9="","",D9/(E9*H9)) | K9: =INDEX($U$6:$U$17,C9) -> -640.85648 | L9: =IF(E9="","",D9-E9-K9) | M9: =IF(E9="","",(J9-1)*100) | N9: =IF(E9="","",(M9-AVERAGE($M$5:$M$52))/_xlfn.STDEV.S($M$5:$M$52)) | O9: =IF(E9="","",(J9-1)*E9) | Q9: 4 | R9: =AVERAGEIF($C$5:$C$52,Q9,$F$5:$F$52) -> 0.92079277 | S9: =R9/AVERAGE($R$6:$R$17) -> 0.92057255 | T9: =AVERAGEIF($C$5:$C$52,Q9,$G$5:$G$52) -> -384.44444 | U9: =T9-AVERAGE($T$6:$T$17) -> -385.5787
A10: =Data!B7 -> 44348 | B10: 6 | C10: =MONTH(A10) -> 6 | D10: =Data!I7 -> 3580 | F10: =IF(E10="","",D10/E10) | G10: =IF(E10="","",D10-E10) | H10: =INDEX($S$6:$S$17,C10) -> 0.83238286 | I10: =D10/H10 -> 4300.9055 | J10: =IF(E10="","",D10/(E10*H10)) | K10: =INDEX($U$6:$U$17,C10) -> -821.13426 | L10: =IF(E10="","",D10-E10-K10) | M10: =IF(E10="","",(J10-1)*100) | N10: =IF(E10="","",(M10-AVERAGE($M$5:$M$52))/_xlfn.STDEV.S($M$5:$M$52)) | O10: =IF(E10="","",(J10-1)*E10) | Q10: 5 | R10: =AVERAGEIF($C$5:$C$52,Q10,$F$5:$F$52) -> 0.8687291 | S10: =R10/AVERAGE($R$6:$R$17) -> 0.86852134 | T10: =AVERAGEIF($C$5:$C$52,Q10,$G$5:$G$52) -> -639.72222 | U10: =T10-AVERAGE($T$6:$T$17) -> -640.85648
A11: =Data!B8 -> 44378 | B11: 7 | C11: =MONTH(A11) -> 7 | D11: =Data!I8 -> 3620 | E11: =(SUM(D5:D16)+SUM(D6:D17))/24 -> 4281.6667 | F11: =IF(E11="","",D11/E11) -> 0.84546516 | G11: =IF(E11="","",D11-E11) -> -661.66667 | H11: =INDEX($S$6:$S$17,C11) -> 0.84139027 | I11: =D11/H11 -> 4302.403 | J11: =IF(E11="","",D11/(E11*H11)) -> 1.004843 | K11: =INDEX($U$6:$U$17,C11) -> -734.05093 | L11: =IF(E11="","",D11-E11-K11) -> 72.384259 | M11: =IF(E11="","",(J11-1)*100) -> 0.48430405 | N11: =IF(E11="","",(M11-AVERAGE($M$5:$M$52))/_xlfn.STDEV.S($M$5:$M$52)) -> 2.1454417 | O11: =IF(E11="","",(J11-1)*E11) -> 20.736285 | Q11: 6 | R11: =AVERAGEIF($C$5:$C$52,Q11,$F$5:$F$52) -> 0.83258198 | S11: =R11/AVERAGE($R$6:$R$17) -> 0.83238286 | T11: =AVERAGEIF($C$5:$C$52,Q11,$G$5:$G$52) -> -820 | U11: =T11-AVERAGE($T$6:$T$17) -> -821.13426
A12: =Data!B9 -> 44409 | B12: 8 | C12: =MONTH(A12) -> 8 | D12: =Data!I9 -> 3790 | E12: =(SUM(D6:D17)+SUM(D7:D18))/24 -> 4342.9167 | F12: =IF(E12="","",D12/E12) -> 0.87268541 | G12: =IF(E12="","",D12-E12) -> -552.91667 | H12: =INDEX($S$6:$S$17,C12) -> 0.8729157 | I12: =D12/H12 -> 4341.7709 | J12: =IF(E12="","",D12/(E12*H12)) -> 0.99973618 | K12: =INDEX($U$6:$U$17,C12) -> -592.38426 | L12: =IF(E12="","",D12-E12-K12) -> 39.467593 | M12: =IF(E12="","",(J12-1)*100) -> -0.026381508 | N12: =IF(E12="","",(M12-AVERAGE($M$5:$M$52))/_xlfn.STDEV.S($M$5:$M$52)) -> -0.23442109 | O12: =IF(E12="","",(J12-1)*E12) -> -1.1457269 | Q12: 7 | R12: =AVERAGEIF($C$5:$C$52,Q12,$F$5:$F$52) -> 0.84159155 | S12: =R12/AVERAGE($R$6:$R$17) -> 0.84139027 | T12: =AVERAGEIF($C$5:$C$52,Q12,$G$5:$G$52) -> -732.91667 | U12: =T12-AVERAGE($T$6:$T$17) -> -734.05093
A13: =Data!B10 -> 44440 | B13: 9 | C13: =MONTH(A13) -> 9 | D13: =Data!I10 -> 4120 | E13: =(SUM(D7:D18)+SUM(D8:D19))/24 -> 4388.75 | F13: =IF(E13="","",D13/E13) -> 0.93876388 | G13: =IF(E13="","",D13-E13) -> -268.75 | H13: =INDEX($S$6:$S$17,C13) -> 0.94023262 | I13: =D13/H13 -> 4381.8944 | J13: =IF(E13="","",D13/(E13*H13)) -> 0.9984379 | K13: =INDEX($U$6:$U$17,C13) -> -280.16204 | L13: =IF(E13="","",D13-E13-K13) -> 11.412037 | M13: =IF(E13="","",(J13-1)*100) -> -0.15620953 | N13: =IF(E13="","",(M13-AVERAGE($M$5:$M$52))/_xlfn.STDEV.S($M$5:$M$52)) -> -0.83943698 | O13: =IF(E13="","",(J13-1)*E13) -> -6.8556457 | Q13: 8 | R13: =AVERAGEIF($C$5:$C$52,Q13,$F$5:$F$52) -> 0.87312451 | S13: =R13/AVERAGE($R$6:$R$17) -> 0.8729157 | T13: =AVERAGEIF($C$5:$C$52,Q13,$G$5:$G$52) -> -591.25 | U13: =T13-AVERAGE($T$6:$T$17) -> -592.38426
A14: =Data!B11 -> 44470 | B14: 10 | C14: =MONTH(A14) -> 10 | D14: =Data!I11 -> 4480 | E14: =(SUM(D8:D19)+SUM(D9:D20))/24 -> 4419.5833 | F14: =IF(E14="","",D14/E14) -> 1.0136702 | G14: =IF(E14="","",D14-E14) -> 60.416667 | H14: =INDEX($S$6:$S$17,C14) -> 1.0166416 | I14: =D14/H14 -> 4406.6659 | J14: =IF(E14="","",D14/(E14*H14)) -> 0.99707722 | K14: =INDEX($U$6:$U$17,C14) -> 79.00463 | L14: =IF(E14="","",D14-E14-K14) -> -18.587963 | M14: =IF(E14="","",(J14-1)*100) -> -0.29227806 | N14: =IF(E14="","",(M14-AVERAGE($M$5:$M$52))/_xlfn.STDEV.S($M$5:$M$52)) -> -1.4735345 | O14: =IF(E14="","",(J14-1)*E14) -> -12.917472 | Q14: 9 | R14: =AVERAGEIF($C$5:$C$52,Q14,$F$5:$F$52) -> 0.94045754 | S14: =R14/AVERAGE($R$6:$R$17) -> 0.94023262 | T14: =AVERAGEIF($C$5:$C$52,Q14,$G$5:$G$52) -> -279.02778 | U14: =T14-AVERAGE($T$6:$T$17) -> -280.16204
A15: =Data!B12 -> 44501 | B15: 11 | C15: =MONTH(A15) -> 11 | D15: =Data!I12 -> 4910 | E15: =(SUM(D9:D20)+SUM(D10:D21))/24 -> 4445 | F15: =IF(E15="","",D15/E15) -> 1.1046119 | G15: =IF(E15="","",D15-E15) -> 465 | H15: =INDEX($S$6:$S$17,C15) -> 1.1071271 | I15: =D15/H15 -> 4434.9017 | J15: =IF(E15="","",D15/(E15*H15)) -> 0.99772816 | K15: =INDEX($U$6:$U$17,C15) -> 508.03241 | L15: =IF(E15="","",D15-E15-K15) -> -43.032407 | M15: =IF(E15="","",(J15-1)*100) -> -0.22718402 | N15: =IF(E15="","",(M15-AVERAGE($M$5:$M$52))/_xlfn.STDEV.S($M$5:$M$52)) -> -1.1701876 | O15: =IF(E15="","",(J15-1)*E15) -> -10.09833 | Q15: 10 | R15: =AVERAGEIF($C$5:$C$52,Q15,$F$5:$F$52) -> 1.0168848 | S15: =R15/AVERAGE($R$6:$R$17) -> 1.0166416 | T15: =AVERAGEIF($C$5:$C$52,Q15,$G$5:$G$52) -> 80.138889 | U15: =T15-AVERAGE($T$6:$T$17) -> 79.00463
A16: =Data!B13 -> 44531 | B16: 12 | C16: =MONTH(A16) -> 12 | D16: =Data!I13 -> 5340 | E16: =(SUM(D10:D21)+SUM(D11:D22))/24 -> 4469.1667 | F16: =IF(E16="","",D16/E16) -> 1.1948536 | G16: =IF(E16="","",D16-E16) -> 870.83333 | H16: =INDEX($S$6:$S$17,C16) -> 1.195659 | I16: =D16/H16 -> 4466.1564 | J16: =IF(E16="","",D16/(E16*H16)) -> 0.99932643 | K16: =INDEX($U$6:$U$17,C16) -> 931.22685 | L16: =IF(E16="","",D16-E16-K16) -> -60.393519 | M16: =IF(E16="","",(J16-1)*100) -> -0.067356775 | N16: =IF(E16="","",(M16-AVERAGE($M$5:$M$52))/_xlfn.STDEV.S($M$5:$M$52)) -> -0.4253713 | O16: =IF(E16="","",(J16-1)*E16) -> -3.0102865 | Q16: 11 | R16: =AVERAGEIF($C$5:$C$52,Q16,$F$5:$F$52) -> 1.107392 | S16: =R16/AVERAGE($R$6:$R$17) -> 1.1071271 | T16: =AVERAGEIF($C$5:$C$52,Q16,$G$5:$G$52) -> 509.16667 | U16: =T16-AVERAGE($T$6:$T$17) -> 508.03241
A17: =Data!B14 -> 44562 | B17: 13 | C17: =MONTH(A17) -> 1 | D17: =Data!I14 -> 5620 | E17: =(SUM(D11:D22)+SUM(D12:D23))/24 -> 4492.9167 | F17: =IF(E17="","",D17/E17) -> 1.2508578 | G17: =IF(E17="","",D17-E17) -> 1127.0833 | H17: =INDEX($S$6:$S$17,C17) -> 1.2492676 | I17: =D17/H17 -> 4498.6357 | J17: =IF(E17="","",D17/(E17*H17)) -> 1.0012729 | K17: =INDEX($U$6:$U$17,C17) -> 1191.088 | L17: =IF(E17="","",D17-E17-K17) -> -64.00463 | M17: =IF(E17="","",(J17-1)*100) -> 0.12728986 | N17: =IF(E17="","",(M17-AVERAGE($M$5:$M$52))/_xlfn.STDEV.S($M$5:$M$52)) -> 0.48170796 | O17: =IF(E17="","",(J17-1)*E17) -> 5.7190271 | Q17: 12 | R17: =AVERAGEIF($C$5:$C$52,Q17,$F$5:$F$52) -> 1.195945 | S17: =R17/AVERAGE($R$6:$R$17) -> 1.195659 | T17: =AVERAGEIF($C$5:$C$52,Q17,$G$5:$G$52) -> 932.36111 | U17: =T17-AVERAGE($T$6:$T$17) -> 931.22685
A18: =Data!B15 -> 44593 | B18: 14 | C18: =MONTH(A18) -> 2 | D18: =Data!I15 -> 5180 | E18: =(SUM(D12:D23)+SUM(D13:D24))/24 -> 4517.5 | F18: =IF(E18="","",D18/E18) -> 1.1466519 | G18: =IF(E18="","",D18-E18) -> 662.5 | H18: =INDEX($S$6:$S$17,C18) -> 1.1425117 | I18: =D18/H18 -> 4533.8705 | J18: =IF(E18="","",D18/(E18*H18)) -> 1.0036238 | K18: =INDEX($U$6:$U$17,C18) -> 683.44907 | L18: =IF(E18="","",D18-E18-K18) -> -20.949074 | M18: =IF(E18="","",(J18-1)*100) -> 0.36237961 | N18: =IF(E18="","",(M18-AVERAGE($M$5:$M$52))/_xlfn.STDEV.S($M$5:$M$52)) -> 1.5772576 | O18: =IF(E18="","",(J18-1)*E18) -> 16.370499
A19: =Data!B16 -> 44621 | B19: 15 | C19: =MONTH(A19) -> 3 | D19: =Data!I16 -> 4610 | E19: =(SUM(D13:D24)+SUM(D14:D25))/24 -> 4542.9167 | F19: =IF(E19="","",D19/E19) -> 1.0147666 | G19: =IF(E19="","",D19-E19) -> 67.083333 | H19: =INDEX($S$6:$S$17,C19) -> 1.0127776 | I19: =D19/H19 -> 4551.8385 | J19: =IF(E19="","",D19/(E19*H19)) -> 1.0019639 | K19: =INDEX($U$6:$U$17,C19) -> 61.365741 | L19: =IF(E19="","",D19-E19-K19) -> 5.7175926 | M19: =IF(E19="","",(J19-1)*100) -> 0.19638978 | N19: =IF(E19="","",(M19-AVERAGE($M$5:$M$52))/_xlfn.STDEV.S($M$5:$M$52)) -> 0.80372283 | O19: =IF(E19="","",(J19-1)*E19) -> 8.9218242 | Q19: Additive vs multiplicative diagnosis
A20: =Data!B17 -> 44652 | B20: 16 | C20: =MONTH(A20) -> 4 | D20: =Data!I17 -> 4230 | E20: =(SUM(D14:D25)+SUM(D15:D26))/24 -> 4570 | F20: =IF(E20="","",D20/E20) -> 0.92560175 | G20: =IF(E20="","",D20-E20) -> -340 | H20: =INDEX($S$6:$S$17,C20) -> 0.92057255 | I20: =D20/H20 -> 4594.9665 | J20: =IF(E20="","",D20/(E20*H20)) -> 1.0054631 | K20: =INDEX($U$6:$U$17,C20) -> -385.5787 | L20: =IF(E20="","",D20-E20-K20) -> 45.578704 | M20: =IF(E20="","",(J20-1)*100) -> 0.5463126 | N20: =IF(E20="","",(M20-AVERAGE($M$5:$M$52))/_xlfn.STDEV.S($M$5:$M$52)) -> 2.4344098 | O20: =IF(E20="","",(J20-1)*E20) -> 24.966486 | Q20: Measure | R20: Additive | S20: Multiplicative
A21: =Data!B18 -> 44682 | B21: 17 | C21: =MONTH(A21) -> 5 | D21: =Data!I18 -> 4010 | E21: =(SUM(D15:D26)+SUM(D16:D27))/24 -> 4599.1667 | F21: =IF(E21="","",D21/E21) -> 0.87189708 | G21: =IF(E21="","",D21-E21) -> -589.16667 | H21: =INDEX($S$6:$S$17,C21) -> 0.86852134 | I21: =D21/H21 -> 4617.0426 | J21: =IF(E21="","",D21/(E21*H21)) -> 1.0038868 | K21: =INDEX($U$6:$U$17,C21) -> -640.85648 | L21: =IF(E21="","",D21-E21-K21) -> 51.689815 | M21: =IF(E21="","",(J21-1)*100) -> 0.38867746 | N21: =IF(E21="","",(M21-AVERAGE($M$5:$M$52))/_xlfn.STDEV.S($M$5:$M$52)) -> 1.699809 | O21: =IF(E21="","",(J21-1)*E21) -> 17.875924 | Q21: Residual SD (visits) | R21: =_xlfn.STDEV.S(L5:L52) -> 35.731167 | S21: =_xlfn.STDEV.S(O5:O52) -> 9.9927157
A22: =Data!B19 -> 44713 | B22: 18 | C22: =MONTH(A22) -> 6 | D22: =Data!I19 -> 3860 | E22: =(SUM(D16:D27)+SUM(D17:D28))/24 -> 4629.5833 | F22: =IF(E22="","",D22/E22) -> 0.83376834 | G22: =IF(E22="","",D22-E22) -> -769.58333 | H22: =INDEX($S$6:$S$17,C22) -> 0.83238286 | I22: =D22/H22 -> 4637.2891 | J22: =IF(E22="","",D22/(E22*H22)) -> 1.0016645 | K22: =INDEX($U$6:$U$17,C22) -> -821.13426 | L22: =IF(E22="","",D22-E22-K22) -> 51.550926 | M22: =IF(E22="","",(J22-1)*100) -> 0.16644709 | N22: =IF(E22="","",(M22-AVERAGE($M$5:$M$52))/_xlfn.STDEV.S($M$5:$M$52)) -> 0.6641859 | O22: =IF(E22="","",(J22-1)*E22) -> 7.7058068 | Q22: Verdict | R22: =IF(S21<R21,"Multiplicative fits better","Additive fits better") -> Multiplicative fits better
A23: =Data!B20 -> 44743 | B23: 19 | C23: =MONTH(A23) -> 7 | D23: =Data!I20 -> 3910 | E23: =(SUM(D17:D28)+SUM(D18:D29))/24 -> 4660 | F23: =IF(E23="","",D23/E23) -> 0.83905579 | G23: =IF(E23="","",D23-E23) -> -750 | H23: =INDEX($S$6:$S$17,C23) -> 0.84139027 | I23: =D23/H23 -> 4647.0706 | J23: =IF(E23="","",D23/(E23*H23)) -> 0.99722545 | K23: =INDEX($U$6:$U$17,C23) -> -734.05093 | L23: =IF(E23="","",D23-E23-K23) -> -15.949074 | M23: =IF(E23="","",(J23-1)*100) -> -0.27745511 | N23: =IF(E23="","",(M23-AVERAGE($M$5:$M$52))/_xlfn.STDEV.S($M$5:$M$52)) -> -1.4044576 | O23: =IF(E23="","",(J23-1)*E23) -> -12.929408
A24: =Data!B21 -> 44774 | B24: 20 | C24: =MONTH(A24) -> 8 | D24: =Data!I21 -> 4090 | E24: =(SUM(D18:D29)+SUM(D19:D30))/24 -> 4687.9167 | F24: =IF(E24="","",D24/E24) -> 0.87245578 | G24: =IF(E24="","",D24-E24) -> -597.91667 | H24: =INDEX($S$6:$S$17,C24) -> 0.8729157 | I24: =D24/H24 -> 4685.4467 | J24: =IF(E24="","",D24/(E24*H24)) -> 0.99947313 | K24: =INDEX($U$6:$U$17,C24) -> -592.38426 | L24: =IF(E24="","",D24-E24-K24) -> -5.5324074 | M24: =IF(E24="","",(J24-1)*100) -> -0.052687091 | N24: =IF(E24="","",(M24-AVERAGE($M$5:$M$52))/_xlfn.STDEV.S($M$5:$M$52)) -> -0.35700861 | O24: =IF(E24="","",(J24-1)*E24) -> -2.4699269 | Q24: Seasonal amplitude by year
A25: =Data!B22 -> 44805 | B25: 21 | C25: =MONTH(A25) -> 9 | D25: =Data!I22 -> 4430 | E25: =(SUM(D19:D30)+SUM(D20:D31))/24 -> 4712.5 | F25: =IF(E25="","",D25/E25) -> 0.94005305 | G25: =IF(E25="","",D25-E25) -> -282.5 | H25: =INDEX($S$6:$S$17,C25) -> 0.94023262 | I25: =D25/H25 -> 4711.6 | J25: =IF(E25="","",D25/(E25*H25)) -> 0.99980902 | K25: =INDEX($U$6:$U$17,C25) -> -280.16204 | L25: =IF(E25="","",D25-E25-K25) -> -2.337963 | M25: =IF(E25="","",(J25-1)*100) -> -0.019098196 | N25: =IF(E25="","",(M25-AVERAGE($M$5:$M$52))/_xlfn.STDEV.S($M$5:$M$52)) -> -0.20047988 | O25: =IF(E25="","",(J25-1)*E25) -> -0.9000025 | Q25: Year | R25: Peak | S25: Trough | T25: Range | U25: Peak/Trough | V25: Annual mean | W25: Range % of mean
A26: =Data!B23 -> 44835 | B26: 22 | C26: =MONTH(A26) -> 10 | D26: =Data!I23 -> 4820 | E26: =(SUM(D20:D31)+SUM(D21:D32))/24 -> 4733.75 | F26: =IF(E26="","",D26/E26) -> 1.0182202 | G26: =IF(E26="","",D26-E26) -> 86.25 | H26: =INDEX($S$6:$S$17,C26) -> 1.0166416 | I26: =D26/H26 -> 4741.1003 | J26: =IF(E26="","",D26/(E26*H26)) -> 1.0015527 | K26: =INDEX($U$6:$U$17,C26) -> 79.00463 | L26: =IF(E26="","",D26-E26-K26) -> 7.2453704 | M26: =IF(E26="","",(J26-1)*100) -> 0.15527486 | N26: =IF(E26="","",(M26-AVERAGE($M$5:$M$52))/_xlfn.STDEV.S($M$5:$M$52)) -> 0.61212181 | O26: =IF(E26="","",(J26-1)*E26) -> 7.3503236 | Q26: 2021 | R26: =MAX(D5:D16) -> 5340 | S26: =MIN(D5:D16) -> 3580 | T26: =R26-S26 -> 1760 | U26: =R26/S26 -> 1.4916201 | V26: =AVERAGE(D5:D16) -> 4248.3333 | W26: =T26/V26 -> 0.41428011
A27: =Data!B24 -> 44866 | B27: 23 | C27: =MONTH(A27) -> 11 | D27: =Data!I24 -> 5270 | E27: =(SUM(D21:D32)+SUM(D22:D33))/24 -> 4752.5 | F27: =IF(E27="","",D27/E27) -> 1.1088901 | G27: =IF(E27="","",D27-E27) -> 517.5 | H27: =INDEX($S$6:$S$17,C27) -> 1.1071271 | I27: =D27/H27 -> 4760.0676 | J27: =IF(E27="","",D27/(E27*H27)) -> 1.0015923 | K27: =INDEX($U$6:$U$17,C27) -> 508.03241 | L27: =IF(E27="","",D27-E27-K27) -> 9.4675926 | M27: =IF(E27="","",(J27-1)*100) -> 0.1592336 | N27: =IF(E27="","",(M27-AVERAGE($M$5:$M$52))/_xlfn.STDEV.S($M$5:$M$52)) -> 0.63057007 | O27: =IF(E27="","",(J27-1)*E27) -> 7.5675769 | Q27: 2022 | R27: =MAX(D17:D28) -> 5710 | S27: =MIN(D17:D28) -> 3860 | T27: =R27-S27 -> 1850 | U27: =R27/S27 -> 1.4792746 | V27: =AVERAGE(D17:D28) -> 4645 | W27: =T27/V27 -> 0.39827772
A28: =Data!B25 -> 44896 | B28: 24 | C28: =MONTH(A28) -> 12 | D28: =Data!I25 -> 5710 | E28: =(SUM(D22:D33)+SUM(D23:D34))/24 -> 4770.8333 | F28: =IF(E28="","",D28/E28) -> 1.1968559 | G28: =IF(E28="","",D28-E28) -> 939.16667 | H28: =INDEX($S$6:$S$17,C28) -> 1.195659 | I28: =D28/H28 -> 4775.6092 | J28: =IF(E28="","",D28/(E28*H28)) -> 1.001001 | K28: =INDEX($U$6:$U$17,C28) -> 931.22685 | L28: =IF(E28="","",D28-E28-K28) -> 7.9398148 | M28: =IF(E28="","",(J28-1)*100) -> 0.10010473 | N28: =IF(E28="","",(M28-AVERAGE($M$5:$M$52))/_xlfn.STDEV.S($M$5:$M$52)) -> 0.35502164 | O28: =IF(E28="","",(J28-1)*E28) -> 4.7758297 | Q28: 2023 | R28: =MAX(D29:D40) -> 6020 | S28: =MIN(D29:D40) -> 4080 | T28: =R28-S28 -> 1940 | U28: =R28/S28 -> 1.4754902 | V28: =AVERAGE(D29:D40) -> 4913.3333 | W28: =T28/V28 -> 0.39484396
A29: =Data!B26 -> 44927 | B29: 25 | C29: =MONTH(A29) -> 1 | D29: =Data!I26 -> 5980 | E29: =(SUM(D23:D34)+SUM(D24:D35))/24 -> 4789.5833 | F29: =IF(E29="","",D29/E29) -> 1.2485428 | G29: =IF(E29="","",D29-E29) -> 1190.4167 | H29: =INDEX($S$6:$S$17,C29) -> 1.2492676 | I29: =D29/H29 -> 4786.8045 | J29: =IF(E29="","",D29/(E29*H29)) -> 0.99941982 | K29: =INDEX($U$6:$U$17,C29) -> 1191.088 | L29: =IF(E29="","",D29-E29-K29) -> -0.6712963 | M29: =IF(E29="","",(J29-1)*100) -> -0.058017678 | N29: =IF(E29="","",(M29-AVERAGE($M$5:$M$52))/_xlfn.STDEV.S($M$5:$M$52)) -> -0.38184986 | O29: =IF(E29="","",(J29-1)*E29) -> -2.778805 | Q29: 2024 | R29: =MAX(D41:D52) -> 6340 | S29: =MIN(D41:D52) -> 4290 | T29: =R29-S29 -> 2050 | U29: =R29/S29 -> 1.4778555 | V29: =AVERAGE(D41:D52) -> 5173.3333 | W29: =T29/V29 -> 0.39626289
A30: =Data!B27 -> 44958 | B30: 26 | C30: =MONTH(A30) -> 2 | D30: =Data!I27 -> 5490 | E30: =(SUM(D24:D35)+SUM(D25:D36))/24 -> 4809.1667 | F30: =IF(E30="","",D30/E30) -> 1.1415699 | G30: =IF(E30="","",D30-E30) -> 680.83333 | H30: =INDEX($S$6:$S$17,C30) -> 1.1425117 | I30: =D30/H30 -> 4805.2025 | J30: =IF(E30="","",D30/(E30*H30)) -> 0.99917571 | K30: =INDEX($U$6:$U$17,C30) -> 683.44907 | L30: =IF(E30="","",D30-E30-K30) -> -2.6157407 | M30: =IF(E30="","",(J30-1)*100) -> -0.082429033 | N30: =IF(E30="","",(M30-AVERAGE($M$5:$M$52))/_xlfn.STDEV.S($M$5:$M$52)) -> -0.49561003 | O30: =IF(E30="","",(J30-1)*E30) -> -3.9641496
A31: =Data!B28 -> 44986 | B31: 27 | C31: =MONTH(A31) -> 3 | D31: =Data!I28 -> 4890 | E31: =(SUM(D25:D36)+SUM(D26:D37))/24 -> 4830 | F31: =IF(E31="","",D31/E31) -> 1.0124224 | G31: =IF(E31="","",D31-E31) -> 60 | H31: =INDEX($S$6:$S$17,C31) -> 1.0127776 | I31: =D31/H31 -> 4828.3059 | J31: =IF(E31="","",D31/(E31*H31)) -> 0.99964926 | K31: =INDEX($U$6:$U$17,C31) -> 61.365741 | L31: =IF(E31="","",D31-E31-K31) -> -1.3657407 | M31: =IF(E31="","",(J31-1)*100) -> -0.035074439 | N31: =IF(E31="","",(M31-AVERAGE($M$5:$M$52))/_xlfn.STDEV.S($M$5:$M$52)) -> -0.27493131 | O31: =IF(E31="","",(J31-1)*E31) -> -1.6940954 | Q31: Range grows with the level while Peak/Trough stays ≈1.48 → seasonality is multiplicative.
A32: =Data!B29 -> 45017 | B32: 28 | C32: =MONTH(A32) -> 4 | D32: =Data!I29 -> 4460 | E32: =(SUM(D26:D37)+SUM(D27:D38))/24 -> 4852.0833 | F32: =IF(E32="","",D32/E32) -> 0.91919279 | G32: =IF(E32="","",D32-E32) -> -392.08333 | H32: =INDEX($S$6:$S$17,C32) -> 0.92057255 | I32: =D32/H32 -> 4844.811 | J32: =IF(E32="","",D32/(E32*H32)) -> 0.99850119 | K32: =INDEX($U$6:$U$17,C32) -> -385.5787 | L32: =IF(E32="","",D32-E32-K32) -> -6.5046296 | M32: =IF(E32="","",(J32-1)*100) -> -0.14988065 | N32: =IF(E32="","",(M32-AVERAGE($M$5:$M$52))/_xlfn.STDEV.S($M$5:$M$52)) -> -0.80994356 | O32: =IF(E32="","",(J32-1)*E32) -> -7.2723341
A33: =Data!B30 -> 45047 | B33: 29 | C33: =MONTH(A33) -> 5 | D33: =Data!I30 -> 4230 | E33: =(SUM(D27:D38)+SUM(D28:D39))/24 -> 4875.4167 | F33: =IF(E33="","",D33/E33) -> 0.86761815 | G33: =IF(E33="","",D33-E33) -> -645.41667 | H33: =INDEX($S$6:$S$17,C33) -> 0.86852134 | I33: =D33/H33 -> 4870.3467 | J33: =IF(E33="","",D33/(E33*H33)) -> 0.99896009 | K33: =INDEX($U$6:$U$17,C33) -> -640.85648 | L33: =IF(E33="","",D33-E33-K33) -> -4.5601852 | M33: =IF(E33="","",(J33-1)*100) -> -0.10399098 | N33: =IF(E33="","",(M33-AVERAGE($M$5:$M$52))/_xlfn.STDEV.S($M$5:$M$52)) -> -0.59609159 | O33: =IF(E33="","",(J33-1)*E33) -> -5.0699937 | Q33: Linear trend of deseasonalised series (HW initial values)
A34: =Data!B31 -> 45078 | B34: 30 | C34: =MONTH(A34) -> 6 | D34: =Data!I31 -> 4080 | E34: =(SUM(D28:D39)+SUM(D29:D40))/24 -> 4900.4167 | F34: =IF(E34="","",D34/E34) -> 0.83258226 | G34: =IF(E34="","",D34-E34) -> -820.41667 | H34: =INDEX($S$6:$S$17,C34) -> 0.83238286 | I34: =D34/H34 -> 4901.5906 | J34: =IF(E34="","",D34/(E34*H34)) -> 1.0002396 | K34: =INDEX($U$6:$U$17,C34) -> -821.13426 | L34: =IF(E34="","",D34-E34-K34) -> 0.71759259 | M34: =IF(E34="","",(J34-1)*100) -> 0.023955658 | N34: =IF(E34="","",(M34-AVERAGE($M$5:$M$52))/_xlfn.STDEV.S($M$5:$M$52)) -> 0.00015681626 | O34: =IF(E34="","",(J34-1)*E34) -> 1.173927 | Q34: Intercept L0 (t = 0) | R34: =INTERCEPT(I5:I52,B5:B52) -> 4123.89
A35: =Data!B32 -> 45108 | B35: 31 | C35: =MONTH(A35) -> 7 | D35: =Data!I32 -> 4140 | E35: =(SUM(D29:D40)+SUM(D30:D41))/24 -> 4927.0833 | F35: =IF(E35="","",D35/E35) -> 0.8402537 | G35: =IF(E35="","",D35-E35) -> -787.08333 | H35: =INDEX($S$6:$S$17,C35) -> 0.84139027 | I35: =D35/H35 -> 4920.4277 | J35: =IF(E35="","",D35/(E35*H35)) -> 0.99864917 | K35: =INDEX($U$6:$U$17,C35) -> -734.05093 | L35: =IF(E35="","",D35-E35-K35) -> -53.032407 | M35: =IF(E35="","",(J35-1)*100) -> -0.13508292 | N35: =IF(E35="","",(M35-AVERAGE($M$5:$M$52))/_xlfn.STDEV.S($M$5:$M$52)) -> -0.74098416 | O35: =IF(E35="","",(J35-1)*E35) -> -6.655648 | Q35: Slope T0 (visits/month) | R35: =SLOPE(I5:I52,B5:B52) -> 25.476711
A36: =Data!B33 -> 45139 | B36: 32 | C36: =MONTH(A36) -> 8 | D36: =Data!I33 -> 4330 | E36: =(SUM(D30:D41)+SUM(D31:D42))/24 -> 4952.9167 | F36: =IF(E36="","",D36/E36) -> 0.87423235 | G36: =IF(E36="","",D36-E36) -> -622.91667 | H36: =INDEX($S$6:$S$17,C36) -> 0.8729157 | I36: =D36/H36 -> 4960.3874 | J36: =IF(E36="","",D36/(E36*H36)) -> 1.0015083 | K36: =INDEX($U$6:$U$17,C36) -> -592.38426 | L36: =IF(E36="","",D36-E36-K36) -> -30.532407 | M36: =IF(E36="","",(J36-1)*100) -> 0.15083462 | N36: =IF(E36="","",(M36-AVERAGE($M$5:$M$52))/_xlfn.STDEV.S($M$5:$M$52)) -> 0.5914297 | O36: =IF(E36="","",(J36-1)*E36) -> 7.4707131
A37: =Data!B34 -> 45170 | B37: 33 | C37: =MONTH(A37) -> 9 | D37: =Data!I34 -> 4690 | E37: =(SUM(D31:D42)+SUM(D32:D43))/24 -> 4975.8333 | F37: =IF(E37="","",D37/E37) -> 0.94255569 | G37: =IF(E37="","",D37-E37) -> -285.83333 | H37: =INDEX($S$6:$S$17,C37) -> 0.94023262 | I37: =D37/H37 -> 4988.1273 | J37: =IF(E37="","",D37/(E37*H37)) -> 1.0024707 | K37: =INDEX($U$6:$U$17,C37) -> -280.16204 | L37: =IF(E37="","",D37-E37-K37) -> -5.6712963 | M37: =IF(E37="","",(J37-1)*100) -> 0.24707375 | N37: =IF(E37="","",(M37-AVERAGE($M$5:$M$52))/_xlfn.STDEV.S($M$5:$M$52)) -> 1.0399169 | O37: =IF(E37="","",(J37-1)*E37) -> 12.293978
A38: =Data!B35 -> 45200 | B38: 34 | C38: =MONTH(A38) -> 10 | D38: =Data!I35 -> 5090 | E38: =(SUM(D32:D43)+SUM(D33:D44))/24 -> 4996.25 | F38: =IF(E38="","",D38/E38) -> 1.0187641 | G38: =IF(E38="","",D38-E38) -> 93.75 | H38: =INDEX($S$6:$S$17,C38) -> 1.0166416 | I38: =D38/H38 -> 5006.6806 | J38: =IF(E38="","",D38/(E38*H38)) -> 1.0020877 | K38: =INDEX($U$6:$U$17,C38) -> 79.00463 | L38: =IF(E38="","",D38-E38-K38) -> 14.74537 | M38: =IF(E38="","",(J38-1)*100) -> 0.20876922 | N38: =IF(E38="","",(M38-AVERAGE($M$5:$M$52))/_xlfn.STDEV.S($M$5:$M$52)) -> 0.86141267 | O38: =IF(E38="","",(J38-1)*E38) -> 10.430632
A39: =Data!B36 -> 45231 | B39: 35 | C39: =MONTH(A39) -> 11 | D39: =Data!I36 -> 5560 | E39: =(SUM(D33:D44)+SUM(D34:D45))/24 -> 5015 | F39: =IF(E39="","",D39/E39) -> 1.108674 | G39: =IF(E39="","",D39-E39) -> 545 | H39: =INDEX($S$6:$S$17,C39) -> 1.1071271 | I39: =D39/H39 -> 5022.0068 | J39: =IF(E39="","",D39/(E39*H39)) -> 1.0013972 | K39: =INDEX($U$6:$U$17,C39) -> 508.03241 | L39: =IF(E39="","",D39-E39-K39) -> 36.967593 | M39: =IF(E39="","",(J39-1)*100) -> 0.13971644 | N39: =IF(E39="","",(M39-AVERAGE($M$5:$M$52))/_xlfn.STDEV.S($M$5:$M$52)) -> 0.5396175 | O39: =IF(E39="","",(J39-1)*E39) -> 7.0067794
A40: =Data!B37 -> 45261 | B40: 36 | C40: =MONTH(A40) -> 12 | D40: =Data!I37 -> 6020 | E40: =(SUM(D34:D45)+SUM(D35:D46))/24 -> 5032.9167 | F40: =IF(E40="","",D40/E40) -> 1.1961255 | G40: =IF(E40="","",D40-E40) -> 987.08333 | H40: =INDEX($S$6:$S$17,C40) -> 1.195659 | I40: =D40/H40 -> 5034.8804 | J40: =IF(E40="","",D40/(E40*H40)) -> 1.0003902 | K40: =INDEX($U$6:$U$17,C40) -> 931.22685 | L40: =IF(E40="","",D40-E40-K40) -> 55.856481 | M40: =IF(E40="","",(J40-1)*100) -> 0.039018069 | N40: =IF(E40="","",(M40-AVERAGE($M$5:$M$52))/_xlfn.STDEV.S($M$5:$M$52)) -> 0.070349661 | O40: =IF(E40="","",(J40-1)*E40) -> 1.9637469
A41: =Data!B38 -> 45292 | B41: 37 | C41: =MONTH(A41) -> 1 | D41: =Data!I38 -> 6310 | E41: =(SUM(D35:D46)+SUM(D36:D47))/24 -> 5050.8333 | F41: =IF(E41="","",D41/E41) -> 1.2492988 | G41: =IF(E41="","",D41-E41) -> 1259.1667 | H41: =INDEX($S$6:$S$17,C41) -> 1.2492676 | I41: =D41/H41 -> 5050.9593 | J41: =IF(E41="","",D41/(E41*H41)) -> 1.0000249 | K41: =INDEX($U$6:$U$17,C41) -> 1191.088 | L41: =IF(E41="","",D41-E41-K41) -> 68.078704 | M41: =IF(E41="","",(J41-1)*100) -> 0.0024938438 | N41: =IF(E41="","",(M41-AVERAGE($M$5:$M$52))/_xlfn.STDEV.S($M$5:$M$52)) -> -0.099858099 | O41: =IF(E41="","",(J41-1)*E41) -> 0.12595989
A42: =Data!B39 -> 45323 | B42: 38 | C42: =MONTH(A42) -> 2 | D42: =Data!I39 -> 5780 | E42: =(SUM(D36:D47)+SUM(D37:D48))/24 -> 5069.5833 | F42: =IF(E42="","",D42/E42) -> 1.1401331 | G42: =IF(E42="","",D42-E42) -> 710.41667 | H42: =INDEX($S$6:$S$17,C42) -> 1.1425117 | I42: =D42/H42 -> 5059.0292 | J42: =IF(E42="","",D42/(E42*H42)) -> 0.99791815 | K42: =INDEX($U$6:$U$17,C42) -> 683.44907 | L42: =IF(E42="","",D42-E42-K42) -> 26.967593 | M42: =IF(E42="","",(J42-1)*100) -> -0.20818455 | N42: =IF(E42="","",(M42-AVERAGE($M$5:$M$52))/_xlfn.STDEV.S($M$5:$M$52)) -> -1.0816475 | O42: =IF(E42="","",(J42-1)*E42) -> -10.554089
A43: =Data!B40 -> 45352 | B43: 39 | C43: =MONTH(A43) -> 3 | D43: =Data!I40 -> 5150 | E43: =(SUM(D37:D48)+SUM(D38:D49))/24 -> 5089.5833 | F43: =IF(E43="","",D43/E43) -> 1.0118707 | G43: =IF(E43="","",D43-E43) -> 60.416667 | H43: =INDEX($S$6:$S$17,C43) -> 1.0127776 | I43: =D43/H43 -> 5085.0256 | J43: =IF(E43="","",D43/(E43*H43)) -> 0.99910451 | K43: =INDEX($U$6:$U$17,C43) -> 61.365741 | L43: =IF(E43="","",D43-E43-K43) -> -0.94907407 | M43: =IF(E43="","",(J43-1)*100) -> -0.089549322 | N43: =IF(E43="","",(M43-AVERAGE($M$5:$M$52))/_xlfn.STDEV.S($M$5:$M$52)) -> -0.52879153 | O43: =IF(E43="","",(J43-1)*E43) -> -4.5576874
A44: =Data!B41 -> 45383 | B44: 40 | C44: =MONTH(A44) -> 4 | D44: =Data!I41 -> 4690 | E44: =(SUM(D38:D49)+SUM(D39:D50))/24 -> 5111.25 | F44: =IF(E44="","",D44/E44) -> 0.91758376 | G44: =IF(E44="","",D44-E44) -> -421.25 | H44: =INDEX($S$6:$S$17,C44) -> 0.92057255 | I44: =D44/H44 -> 5094.6555 | J44: =IF(E44="","",D44/(E44*H44)) -> 0.99675334 | K44: =INDEX($U$6:$U$17,C44) -> -385.5787 | L44: =IF(E44="","",D44-E44-K44) -> -35.671296 | M44: =IF(E44="","",(J44-1)*100) -> -0.32466593 | N44: =IF(E44="","",(M44-AVERAGE($M$5:$M$52))/_xlfn.STDEV.S($M$5:$M$52)) -> -1.6244663 | O44: =IF(E44="","",(J44-1)*E44) -> -16.594487
A45: =Data!B42 -> 45413 | B45: 41 | C45: =MONTH(A45) -> 5 | D45: =Data!I42 -> 4450 | E45: =(SUM(D39:D50)+SUM(D40:D51))/24 -> 5134.5833 | F45: =IF(E45="","",D45/E45) -> 0.86667208 | G45: =IF(E45="","",D45-E45) -> -684.58333 | H45: =INDEX($S$6:$S$17,C45) -> 0.86852134 | I45: =D45/H45 -> 5123.6508 | J45: =IF(E45="","",D45/(E45*H45)) -> 0.9978708 | K45: =INDEX($U$6:$U$17,C45) -> -640.85648 | L45: =IF(E45="","",D45-E45-K45) -> -43.726852 | M45: =IF(E45="","",(J45-1)*100) -> -0.21292045 | N45: =IF(E45="","",(M45-AVERAGE($M$5:$M$52))/_xlfn.STDEV.S($M$5:$M$52)) -> -1.1037174 | O45: =IF(E45="","",(J45-1)*E45) -> -10.932578
A46: =Data!B43 -> 45444 | B46: 42 | C46: =MONTH(A46) -> 6 | D46: =Data!I43 -> 4290 | E46: =(SUM(D40:D51)+SUM(D41:D52))/24 -> 5160 | F46: =IF(E46="","",D46/E46) -> 0.83139535 | G46: =IF(E46="","",D46-E46) -> -870 | H46: =INDEX($S$6:$S$17,C46) -> 0.83238286 | I46: =D46/H46 -> 5153.8783 | J46: =IF(E46="","",D46/(E46*H46)) -> 0.99881363 | K46: =INDEX($U$6:$U$17,C46) -> -821.13426 | L46: =IF(E46="","",D46-E46-K46) -> -48.865741 | M46: =IF(E46="","",(J46-1)*100) -> -0.11863673 | N46: =IF(E46="","",(M46-AVERAGE($M$5:$M$52))/_xlfn.STDEV.S($M$5:$M$52)) -> -0.66434271 | O46: =IF(E46="","",(J46-1)*E46) -> -6.1216551
A47: =Data!B44 -> 45474 | B47: 43 | C47: =MONTH(A47) -> 7 | D47: =Data!I44 -> 4360 | F47: =IF(E47="","",D47/E47) | G47: =IF(E47="","",D47-E47) | H47: =INDEX($S$6:$S$17,C47) -> 0.84139027 | I47: =D47/H47 -> 5181.8997 | J47: =IF(E47="","",D47/(E47*H47)) | K47: =INDEX($U$6:$U$17,C47) -> -734.05093 | L47: =IF(E47="","",D47-E47-K47) | M47: =IF(E47="","",(J47-1)*100) | N47: =IF(E47="","",(M47-AVERAGE($M$5:$M$52))/_xlfn.STDEV.S($M$5:$M$52)) | O47: =IF(E47="","",(J47-1)*E47)
A48: =Data!B45 -> 45505 | B48: 44 | C48: =MONTH(A48) -> 8 | D48: =Data!I45 -> 4560 | F48: =IF(E48="","",D48/E48) | G48: =IF(E48="","",D48-E48) | H48: =INDEX($S$6:$S$17,C48) -> 0.8729157 | I48: =D48/H48 -> 5223.8722 | J48: =IF(E48="","",D48/(E48*H48)) | K48: =INDEX($U$6:$U$17,C48) -> -592.38426 | L48: =IF(E48="","",D48-E48-K48) | M48: =IF(E48="","",(J48-1)*100) | N48: =IF(E48="","",(M48-AVERAGE($M$5:$M$52))/_xlfn.STDEV.S($M$5:$M$52)) | O48: =IF(E48="","",(J48-1)*E48)
A49: =Data!B46 -> 45536 | B49: 45 | C49: =MONTH(A49) -> 9 | D49: =Data!I46 -> 4940 | F49: =IF(E49="","",D49/E49) | G49: =IF(E49="","",D49-E49) | H49: =INDEX($S$6:$S$17,C49) -> 0.94023262 | I49: =D49/H49 -> 5254.019 | J49: =IF(E49="","",D49/(E49*H49)) | K49: =INDEX($U$6:$U$17,C49) -> -280.16204 | L49: =IF(E49="","",D49-E49-K49) | M49: =IF(E49="","",(J49-1)*100) | N49: =IF(E49="","",(M49-AVERAGE($M$5:$M$52))/_xlfn.STDEV.S($M$5:$M$52)) | O49: =IF(E49="","",(J49-1)*E49)
A50: =Data!B47 -> 45566 | B50: 46 | C50: =MONTH(A50) -> 10 | D50: =Data!I47 -> 5360 | F50: =IF(E50="","",D50/E50) | G50: =IF(E50="","",D50-E50) | H50: =INDEX($S$6:$S$17,C50) -> 1.0166416 | I50: =D50/H50 -> 5272.2609 | J50: =IF(E50="","",D50/(E50*H50)) | K50: =INDEX($U$6:$U$17,C50) -> 79.00463 | L50: =IF(E50="","",D50-E50-K50) | M50: =IF(E50="","",(J50-1)*100) | N50: =IF(E50="","",(M50-AVERAGE($M$5:$M$52))/_xlfn.STDEV.S($M$5:$M$52)) | O50: =IF(E50="","",(J50-1)*E50)
A51: =Data!B48 -> 45597 | B51: 47 | C51: =MONTH(A51) -> 11 | D51: =Data!I48 -> 5850 | F51: =IF(E51="","",D51/E51) | G51: =IF(E51="","",D51-E51) | H51: =INDEX($S$6:$S$17,C51) -> 1.1071271 | I51: =D51/H51 -> 5283.946 | J51: =IF(E51="","",D51/(E51*H51)) | K51: =INDEX($U$6:$U$17,C51) -> 508.03241 | L51: =IF(E51="","",D51-E51-K51) | M51: =IF(E51="","",(J51-1)*100) | N51: =IF(E51="","",(M51-AVERAGE($M$5:$M$52))/_xlfn.STDEV.S($M$5:$M$52)) | O51: =IF(E51="","",(J51-1)*E51)
A52: =Data!B49 -> 45627 | B52: 48 | C52: =MONTH(A52) -> 12 | D52: =Data!I49 -> 6340 | F52: =IF(E52="","",D52/E52) | G52: =IF(E52="","",D52-E52) | H52: =INDEX($S$6:$S$17,C52) -> 1.195659 | I52: =D52/H52 -> 5302.5153 | J52: =IF(E52="","",D52/(E52*H52)) | K52: =INDEX($U$6:$U$17,C52) -> 931.22685 | L52: =IF(E52="","",D52-E52-K52) | M52: =IF(E52="","",(J52-1)*100) | N52: =IF(E52="","",(M52-AVERAGE($M$5:$M$52))/_xlfn.STDEV.S($M$5:$M$52)) | O52: =IF(E52="","",(J52-1)*E52)

Sheet Anomalies
A1: Unit 4 · Pattern recognition and anomaly detection
A2: z = (x − mean)/SD; irregular = Y / (Trend × Season) from the Decomposition sheet
A4: Date | B4: ER visits | C4: ER z-score | D4: MoM ER % | E4: ICU % | F4: ICU > 85% | G4: ICU > 90% | H4: Vacc change (pp) | I4: Irregular % | J4: Irregular z | K4: Anomaly flag | M4: Summary
A5: =Data!B2 -> 44197 | B5: =Data!I2 -> 4820 | C5: =STANDARDIZE(B5,Descriptive_Stats!$B$6,Descriptive_Stats!$B$8) -> 0.10143652 | E5: =Data!J2 -> 78.4 | F5: =IF(E5>85,1,0) -> 0 | G5: =IF(E5>90,1,0) -> 0 | I5: =Decomposition!M5 | J5: =Decomposition!N5 | K5: =IF(E5>95,"Critical ICU (>95%)",IF(E5>90,"ICU capacity stress (>90%)",IF(E5>85,"Above safe occupancy (>85%)","")))&IF(AND(J5<>"",ABS(N(J5))>2)," | Statistical irregular |z|>2","")&IF(N(H5)>2," | Vaccination surge","") | M5: Max |ER z| | N5: =MAX(MAX(C5:C52),-MIN(C5:C52)) -> 2.1572166
A6: =Data!B3 -> 44228 | B6: =Data!I3 -> 4510 | C6: =STANDARDIZE(B6,Descriptive_Stats!$B$6,Descriptive_Stats!$B$8) -> -0.31783442 | D6: =B6/B5-1 -> -0.064315353 | E6: =Data!J3 -> 74.1 | F6: =IF(E6>85,1,0) -> 0 | G6: =IF(E6>90,1,0) -> 0 | H6: =Data!R3 -> 2.6 | I6: =Decomposition!M6 | J6: =Decomposition!N6 | K6: =IF(E6>95,"Critical ICU (>95%)",IF(E6>90,"ICU capacity stress (>90%)",IF(E6>85,"Above safe occupancy (>85%)","")))&IF(AND(J6<>"",ABS(N(J6))>2)," | Statistical irregular |z|>2","")&IF(N(H6)>2," | Vaccination surge","") -> | Vaccination surge | M6: Max |irregular| % | N6: =MAX(MAX(I5:I52),-MIN(I5:I52)) -> 0.5463126
A7: =Data!B4 -> 44256 | B7: =Data!I4 -> 4180 | C7: =STANDARDIZE(B7,Descriptive_Stats!$B$6,Descriptive_Stats!$B$8) -> -0.7641551 | D7: =B7/B6-1 -> -0.073170732 | E7: =Data!J4 -> 69.5 | F7: =IF(E7>85,1,0) -> 0 | G7: =IF(E7>90,1,0) -> 0 | H7: =Data!R4 -> 2.3 | I7: =Decomposition!M7 | J7: =Decomposition!N7 | K7: =IF(E7>95,"Critical ICU (>95%)",IF(E7>90,"ICU capacity stress (>90%)",IF(E7>85,"Above safe occupancy (>85%)","")))&IF(AND(J7<>"",ABS(N(J7))>2)," | Statistical irregular |z|>2","")&IF(N(H7)>2," | Vaccination surge","") -> | Vaccination surge | M7: Months |irregular z| > 2 | N7: =COUNTIF(J5:J52,">2")+COUNTIF(J5:J52,"<-2") -> 2
A8: =Data!B5 -> 44287 | B8: =Data!I5 -> 3920 | C8: =STANDARDIZE(B8,Descriptive_Stats!$B$6,Descriptive_Stats!$B$8) -> -1.1158017 | D8: =B8/B7-1 -> -0.062200957 | E8: =Data!J5 -> 64.2 | F8: =IF(E8>85,1,0) -> 0 | G8: =IF(E8>90,1,0) -> 0 | H8: =Data!R5 -> 2.3 | I8: =Decomposition!M8 | J8: =Decomposition!N8 | K8: =IF(E8>95,"Critical ICU (>95%)",IF(E8>90,"ICU capacity stress (>90%)",IF(E8>85,"Above safe occupancy (>85%)","")))&IF(AND(J8<>"",ABS(N(J8))>2)," | Statistical irregular |z|>2","")&IF(N(H8)>2," | Vaccination surge","") -> | Vaccination surge | M8: Months ICU > 85% | N8: =SUM(F5:F52) -> 11
A9: =Data!B6 -> 44317 | B9: =Data!I6 -> 3710 | C9: =STANDARDIZE(B9,Descriptive_Stats!$B$6,Descriptive_Stats!$B$8) -> -1.3998239 | D9: =B9/B8-1 -> -0.053571429 | E9: =Data!J6 -> 61.8 | F9: =IF(E9>85,1,0) -> 0 | G9: =IF(E9>90,1,0) -> 0 | H9: =Data!R6 -> 1.8 | I9: =Decomposition!M9 | J9: =Decomposition!N9 | K9: =IF(E9>95,"Critical ICU (>95%)",IF(E9>90,"ICU capacity stress (>90%)",IF(E9>85,"Above safe occupancy (>85%)","")))&IF(AND(J9<>"",ABS(N(J9))>2)," | Statistical irregular |z|>2","")&IF(N(H9)>2," | Vaccination surge","") | M9: Months ICU > 90% | N9: =SUM(G5:G52) -> 7
A10: =Data!B7 -> 44348 | B10: =Data!I7 -> 3580 | C10: =STANDARDIZE(B10,Descriptive_Stats!$B$6,Descriptive_Stats!$B$8) -> -1.5756472 | D10: =B10/B9-1 -> -0.035040431 | E10: =Data!J7 -> 59.4 | F10: =IF(E10>85,1,0) -> 0 | G10: =IF(E10>90,1,0) -> 0 | H10: =Data!R7 -> 1.3 | I10: =Decomposition!M10 | J10: =Decomposition!N10 | K10: =IF(E10>95,"Critical ICU (>95%)",IF(E10>90,"ICU capacity stress (>90%)",IF(E10>85,"Above safe occupancy (>85%)","")))&IF(AND(J10<>"",ABS(N(J10))>2)," | Statistical irregular |z|>2","")&IF(N(H10)>2," | Vaccination surge","") | M10: Peak ICU % | N10: =MAX(E5:E52) -> 97.9
A11: =Data!B8 -> 44378 | B11: =Data!I8 -> 3620 | C11: =STANDARDIZE(B11,Descriptive_Stats!$B$6,Descriptive_Stats!$B$8) -> -1.5215478 | D11: =B11/B10-1 -> 0.011173184 | E11: =Data!J8 -> 60.1 | F11: =IF(E11>85,1,0) -> 0 | G11: =IF(E11>90,1,0) -> 0 | H11: =Data!R8 -> 0.5 | I11: =Decomposition!M11 -> 0.48430405 | J11: =Decomposition!N11 -> 2.1454417 | K11: =IF(E11>95,"Critical ICU (>95%)",IF(E11>90,"ICU capacity stress (>90%)",IF(E11>85,"Above safe occupancy (>85%)","")))&IF(AND(J11<>"",ABS(N(J11))>2)," | Statistical irregular |z|>2","")&IF(N(H11)>2," | Vaccination surge","") -> | Statistical irregular |z|>2 | M11: Avg vacc change 2021 (pp/mo) | N11: =AVERAGE(H6:H16) -> 1.1636364
A12: =Data!B9 -> 44409 | B12: =Data!I9 -> 3790 | C12: =STANDARDIZE(B12,Descriptive_Stats!$B$6,Descriptive_Stats!$B$8) -> -1.291625 | D12: =B12/B11-1 -> 0.046961326 | E12: =Data!J9 -> 63.7 | F12: =IF(E12>85,1,0) -> 0 | G12: =IF(E12>90,1,0) -> 0 | H12: =Data!R9 -> 0.6 | I12: =Decomposition!M12 -> -0.026381508 | J12: =Decomposition!N12 -> -0.23442109 | K12: =IF(E12>95,"Critical ICU (>95%)",IF(E12>90,"ICU capacity stress (>90%)",IF(E12>85,"Above safe occupancy (>85%)","")))&IF(AND(J12<>"",ABS(N(J12))>2)," | Statistical irregular |z|>2","")&IF(N(H12)>2," | Vaccination surge","") | M12: Avg vacc change 2022–24 (pp/mo) | N12: =AVERAGE(H17:H52) -> 0.45
A13: =Data!B10 -> 44440 | B13: =Data!I10 -> 4120 | C13: =STANDARDIZE(B13,Descriptive_Stats!$B$6,Descriptive_Stats!$B$8) -> -0.84530432 | D13: =B13/B12-1 -> 0.08707124 | E13: =Data!J10 -> 68.9 | F13: =IF(E13>85,1,0) -> 0 | G13: =IF(E13>90,1,0) -> 0 | H13: =Data!R10 -> 0.5 | I13: =Decomposition!M13 -> -0.15620953 | J13: =Decomposition!N13 -> -0.83943698 | K13: =IF(E13>95,"Critical ICU (>95%)",IF(E13>90,"ICU capacity stress (>90%)",IF(E13>85,"Above safe occupancy (>85%)","")))&IF(AND(J13<>"",ABS(N(J13))>2)," | Statistical irregular |z|>2","")&IF(N(H13)>2," | Vaccination surge","") | M13: IQR outliers (all variables) | N13: =SUM(Descriptive_Stats!B22:G22) -> 0
A14: =Data!B11 -> 44470 | B14: =Data!I11 -> 4480 | C14: =STANDARDIZE(B14,Descriptive_Stats!$B$6,Descriptive_Stats!$B$8) -> -0.35840903 | D14: =B14/B13-1 -> 0.087378641 | E14: =Data!J11 -> 73.2 | F14: =IF(E14>85,1,0) -> 0 | G14: =IF(E14>90,1,0) -> 0 | H14: =Data!R11 -> 0.4 | I14: =Decomposition!M14 -> -0.29227806 | J14: =Decomposition!N14 -> -1.4735345 | K14: =IF(E14>95,"Critical ICU (>95%)",IF(E14>90,"ICU capacity stress (>90%)",IF(E14>85,"Above safe occupancy (>85%)","")))&IF(AND(J14<>"",ABS(N(J14))>2)," | Statistical irregular |z|>2","")&IF(N(H14)>2," | Vaccination surge","")
A15: =Data!B12 -> 44501 | B15: =Data!I12 -> 4910 | C15: =STANDARDIZE(B15,Descriptive_Stats!$B$6,Descriptive_Stats!$B$8) -> 0.22316034 | D15: =B15/B14-1 -> 0.095982143 | E15: =Data!J12 -> 79.8 | F15: =IF(E15>85,1,0) -> 0 | G15: =IF(E15>90,1,0) -> 0 | H15: =Data!R12 -> 0.3 | I15: =Decomposition!M15 -> -0.22718402 | J15: =Decomposition!N15 -> -1.1701876 | K15: =IF(E15>95,"Critical ICU (>95%)",IF(E15>90,"ICU capacity stress (>90%)",IF(E15>85,"Above safe occupancy (>85%)","")))&IF(AND(J15<>"",ABS(N(J15))>2)," | Statistical irregular |z|>2","")&IF(N(H15)>2," | Vaccination surge","")
A16: =Data!B13 -> 44531 | B16: =Data!I13 -> 5340 | C16: =STANDARDIZE(B16,Descriptive_Stats!$B$6,Descriptive_Stats!$B$8) -> 0.80472971 | D16: =B16/B15-1 -> 0.087576375 | E16: =Data!J13 -> 86.2 | F16: =IF(E16>85,1,0) -> 1 | G16: =IF(E16>90,1,0) -> 0 | H16: =Data!R13 -> 0.2 | I16: =Decomposition!M16 -> -0.067356775 | J16: =Decomposition!N16 -> -0.4253713 | K16: =IF(E16>95,"Critical ICU (>95%)",IF(E16>90,"ICU capacity stress (>90%)",IF(E16>85,"Above safe occupancy (>85%)","")))&IF(AND(J16<>"",ABS(N(J16))>2)," | Statistical irregular |z|>2","")&IF(N(H16)>2," | Vaccination surge","") -> Above safe occupancy (>85%)
A17: =Data!B14 -> 44562 | B17: =Data!I14 -> 5620 | C17: =STANDARDIZE(B17,Descriptive_Stats!$B$6,Descriptive_Stats!$B$8) -> 1.183426 | D17: =B17/B16-1 -> 0.052434457 | E17: =Data!J14 -> 89.4 | F17: =IF(E17>85,1,0) -> 1 | G17: =IF(E17>90,1,0) -> 0 | H17: =Data!R14 -> 0.4 | I17: =Decomposition!M17 -> 0.12728986 | J17: =Decomposition!N17 -> 0.48170796 | K17: =IF(E17>95,"Critical ICU (>95%)",IF(E17>90,"ICU capacity stress (>90%)",IF(E17>85,"Above safe occupancy (>85%)","")))&IF(AND(J17<>"",ABS(N(J17))>2)," | Statistical irregular |z|>2","")&IF(N(H17)>2," | Vaccination surge","") -> Above safe occupancy (>85%)
A18: =Data!B15 -> 44593 | B18: =Data!I15 -> 5180 | C18: =STANDARDIZE(B18,Descriptive_Stats!$B$6,Descriptive_Stats!$B$8) -> 0.5883318 | D18: =B18/B17-1 -> -0.078291815 | E18: =Data!J15 -> 82.1 | F18: =IF(E18>85,1,0) -> 0 | G18: =IF(E18>90,1,0) -> 0 | H18: =Data!R15 -> 0.7 | I18: =Decomposition!M18 -> 0.36237961 | J18: =Decomposition!N18 -> 1.5772576 | K18: =IF(E18>95,"Critical ICU (>95%)",IF(E18>90,"ICU capacity stress (>90%)",IF(E18>85,"Above safe occupancy (>85%)","")))&IF(AND(J18<>"",ABS(N(J18))>2)," | Statistical irregular |z|>2","")&IF(N(H18)>2," | Vaccination surge","")
A19: =Data!B16 -> 44621 | B19: =Data!I16 -> 4610 | C19: =STANDARDIZE(B19,Descriptive_Stats!$B$6,Descriptive_Stats!$B$8) -> -0.18258573 | D19: =B19/B18-1 -> -0.11003861 | E19: =Data!J16 -> 74.8 | F19: =IF(E19>85,1,0) -> 0 | G19: =IF(E19>90,1,0) -> 0 | H19: =Data!R16 -> 0.7 | I19: =Decomposition!M19 -> 0.19638978 | J19: =Decomposition!N19 -> 0.80372283 | K19: =IF(E19>95,"Critical ICU (>95%)",IF(E19>90,"ICU capacity stress (>90%)",IF(E19>85,"Above safe occupancy (>85%)","")))&IF(AND(J19<>"",ABS(N(J19))>2)," | Statistical irregular |z|>2","")&IF(N(H19)>2," | Vaccination surge","")
A20: =Data!B17 -> 44652 | B20: =Data!I17 -> 4230 | C20: =STANDARDIZE(B20,Descriptive_Stats!$B$6,Descriptive_Stats!$B$8) -> -0.69653076 | D20: =B20/B19-1 -> -0.082429501 | E20: =Data!J17 -> 68.9 | F20: =IF(E20>85,1,0) -> 0 | G20: =IF(E20>90,1,0) -> 0 | H20: =Data!R17 -> 0.6 | I20: =Decomposition!M20 -> 0.5463126 | J20: =Decomposition!N20 -> 2.4344098 | K20: =IF(E20>95,"Critical ICU (>95%)",IF(E20>90,"ICU capacity stress (>90%)",IF(E20>85,"Above safe occupancy (>85%)","")))&IF(AND(J20<>"",ABS(N(J20))>2)," | Statistical irregular |z|>2","")&IF(N(H20)>2," | Vaccination surge","") -> | Statistical irregular |z|>2
A21: =Data!B18 -> 44682 | B21: =Data!I18 -> 4010 | C21: =STANDARDIZE(B21,Descriptive_Stats!$B$6,Descriptive_Stats!$B$8) -> -0.99407788 | D21: =B21/B20-1 -> -0.052009456 | E21: =Data!J18 -> 65.2 | F21: =IF(E21>85,1,0) -> 0 | G21: =IF(E21>90,1,0) -> 0 | H21: =Data!R18 -> 0.6 | I21: =Decomposition!M21 -> 0.38867746 | J21: =Decomposition!N21 -> 1.699809 | K21: =IF(E21>95,"Critical ICU (>95%)",IF(E21>90,"ICU capacity stress (>90%)",IF(E21>85,"Above safe occupancy (>85%)","")))&IF(AND(J21<>"",ABS(N(J21))>2)," | Statistical irregular |z|>2","")&IF(N(H21)>2," | Vaccination surge","")
A22: =Data!B19 -> 44713 | B22: =Data!I19 -> 3860 | C22: =STANDARDIZE(B22,Descriptive_Stats!$B$6,Descriptive_Stats!$B$8) -> -1.1969509 | D22: =B22/B21-1 -> -0.037406484 | E22: =Data!J19 -> 62.4 | F22: =IF(E22>85,1,0) -> 0 | G22: =IF(E22>90,1,0) -> 0 | H22: =Data!R19 -> 0.5 | I22: =Decomposition!M22 -> 0.16644709 | J22: =Decomposition!N22 -> 0.6641859 | K22: =IF(E22>95,"Critical ICU (>95%)",IF(E22>90,"ICU capacity stress (>90%)",IF(E22>85,"Above safe occupancy (>85%)","")))&IF(AND(J22<>"",ABS(N(J22))>2)," | Statistical irregular |z|>2","")&IF(N(H22)>2," | Vaccination surge","")
A23: =Data!B20 -> 44743 | B23: =Data!I20 -> 3910 | C23: =STANDARDIZE(B23,Descriptive_Stats!$B$6,Descriptive_Stats!$B$8) -> -1.1293266 | D23: =B23/B22-1 -> 0.012953368 | E23: =Data!J20 -> 63.1 | F23: =IF(E23>85,1,0) -> 0 | G23: =IF(E23>90,1,0) -> 0 | H23: =Data!R20 -> 0.4 | I23: =Decomposition!M23 -> -0.27745511 | J23: =Decomposition!N23 -> -1.4044576 | K23: =IF(E23>95,"Critical ICU (>95%)",IF(E23>90,"ICU capacity stress (>90%)",IF(E23>85,"Above safe occupancy (>85%)","")))&IF(AND(J23<>"",ABS(N(J23))>2)," | Statistical irregular |z|>2","")&IF(N(H23)>2," | Vaccination surge","")
A24: =Data!B21 -> 44774 | B24: =Data!I21 -> 4090 | C24: =STANDARDIZE(B24,Descriptive_Stats!$B$6,Descriptive_Stats!$B$8) -> -0.88587892 | D24: =B24/B23-1 -> 0.046035806 | E24: =Data!J21 -> 66.8 | F24: =IF(E24>85,1,0) -> 0 | G24: =IF(E24>90,1,0) -> 0 | H24: =Data!R21 -> 0.4 | I24: =Decomposition!M24 -> -0.052687091 | J24: =Decomposition!N24 -> -0.35700861 | K24: =IF(E24>95,"Critical ICU (>95%)",IF(E24>90,"ICU capacity stress (>90%)",IF(E24>85,"Above safe occupancy (>85%)","")))&IF(AND(J24<>"",ABS(N(J24))>2)," | Statistical irregular |z|>2","")&IF(N(H24)>2," | Vaccination surge","")
A25: =Data!B22 -> 44805 | B25: =Data!I22 -> 4430 | C25: =STANDARDIZE(B25,Descriptive_Stats!$B$6,Descriptive_Stats!$B$8) -> -0.42603338 | D25: =B25/B24-1 -> 0.083129584 | E25: =Data!J22 -> 71.5 | F25: =IF(E25>85,1,0) -> 0 | G25: =IF(E25>90,1,0) -> 0 | H25: =Data!R22 -> 0.4 | I25: =Decomposition!M25 -> -0.019098196 | J25: =Decomposition!N25 -> -0.20047988 | K25: =IF(E25>95,"Critical ICU (>95%)",IF(E25>90,"ICU capacity stress (>90%)",IF(E25>85,"Above safe occupancy (>85%)","")))&IF(AND(J25<>"",ABS(N(J25))>2)," | Statistical irregular |z|>2","")&IF(N(H25)>2," | Vaccination surge","")
... A52: =Data!B49 -> 45627 | B52: =Data!I49 -> 6340 | C52: =STANDARDIZE(B52,Descriptive_Stats!$B$6,Descriptive_Stats!$B$8) -> 2.1572166 | D52: =B52/B51-1 -> 0.083760684 | E52: =Data!J49 -> 97.9 | F52: =IF(E52>85,1,0) -> 1 | G52: =IF(E52>90,1,0) -> 1 | H52: =Data!R49 -> 0.3 | I52: =Decomposition!M52 | J52: =Decomposition!N52 | K52: =IF(E52>95,"Critical ICU (>95%)",IF(E52>90,"ICU capacity stress (>90%)",IF(E52>85,"Above safe occupancy (>85%)","")))&IF(AND(J52<>"",ABS(N(J52))>2)," | Statistical irregular |z|>2","")&IF(N(H52)>2," | Vaccination surge","") -> Critical ICU (>95%)

Sheet SLR
A1: Unit 5 · Simple linear regression: ER_Visits = β0 + β1 · Flu_Resp_Cases
A2: Predictor chosen as the exogenous variable most correlated with ER visits (r = 0.988). Analysis ToolPak layout, live LINEST formulas.
A4: SUMMARY OUTPUT
A6: Regression Statistics
A7: Multiple R | B7: =SQRT(B8) -> 0.98759393
A8: R Square | B8: =INDEX(LINEST(Data!$I$2:$I$49,Data!$N$2:$N$49,TRUE(),TRUE()),3,1) -> 0.97534178
A9: Adjusted R Square | B9: =1-(1-B8)*(B11-1)/(B11-1-1) -> 0.97480573
A10: Standard Error | B10: =INDEX(LINEST(Data!$I$2:$I$49,Data!$N$2:$N$49,TRUE(),TRUE()),3,2) -> 117.35938
A11: Observations | B11: =COUNT(Data!$I$2:$I$49) -> 48
A14: ANOVA
B15: df | C15: SS | D15: MS | E15: F | F15: Significance F
A16: Regression | B16: 1 | C16: =INDEX(LINEST(Data!$I$2:$I$49,Data!$N$2:$N$49,TRUE(),TRUE()),5,1) -> 25060432 | D16: =C16/B16 -> 25060432 | E16: =INDEX(LINEST(Data!$I$2:$I$49,Data!$N$2:$N$49,TRUE(),TRUE()),4,1) -> 1819.5036 | F16: =_xlfn.F.DIST.RT(E16,B16,B17) -> 1.2260671e-38
A17: Residual | B17: =INDEX(LINEST(Data!$I$2:$I$49,Data!$N$2:$N$49,TRUE(),TRUE()),4,2) -> 46 | C17: =INDEX(LINEST(Data!$I$2:$I$49,Data!$N$2:$N$49,TRUE(),TRUE()),5,2) -> 633568.33 | D17: =C17/B17 -> 13773.225
A18: Total | B18: =B16+B17 -> 47 | C18: =C16+C17 -> 25694000
B20: Coefficients | C20: Standard Error | D20: t Stat | E20: P-value | F20: Lower 95% | G20: Upper 95% | H20: Significant at α=0.05?
A21: Intercept | B21: =INDEX(LINEST(Data!$I$2:$I$49,Data!$N$2:$N$49,TRUE(),TRUE()),1,2) -> 2552.7054 | C21: =INDEX(LINEST(Data!$I$2:$I$49,Data!$N$2:$N$49,TRUE(),TRUE()),2,2) -> 54.114763 | D21: =B21/C21 -> 47.172069 | E21: =_xlfn.T.DIST.2T(ABS(D21),$B$17) -> 1.3243281e-40 | F21: =B21-_xlfn.T.INV.2T(0.05,$B$17)*C21 -> 2443.778 | G21: =B21+_xlfn.T.INV.2T(0.05,$B$17)*C21 -> 2661.6327 | H21: =IF(E21<0.05,"Yes (reject H0)","No (fail to reject H0)") -> Yes (reject H0)
A22: Flu_Resp_Cases | B22: =INDEX(LINEST(Data!$I$2:$I$49,Data!$N$2:$N$49,TRUE(),TRUE()),1,1) -> 1.7494621 | C22: =INDEX(LINEST(Data!$I$2:$I$49,Data!$N$2:$N$49,TRUE(),TRUE()),2,1) -> 0.041013617 | D22: =B22/C22 -> 42.65564 | E22: =_xlfn.T.DIST.2T(ABS(D22),$B$17) -> 1.2260671e-38 | F22: =B22-_xlfn.T.INV.2T(0.05,$B$17)*C22 -> 1.6669059 | G22: =B22+_xlfn.T.INV.2T(0.05,$B$17)*C22 -> 1.8320182 | H22: =IF(E22<0.05,"Yes (reject H0)","No (fail to reject H0)") -> Yes (reject H0)
A24: Fitted equation | B24: ="Ŷ = "&TEXT($B$21,"#,##0.00")&" + "&TEXT($B$22,"0.0000")&" × Flu_Resp_Cases" -> Ŷ = 2,552.71 + 1.7495 × Flu_Resp_Cases
A26: Cross-checks
A27: SLOPE() | B27: =SLOPE(Data!$I$2:$I$49,Data!$N$2:$N$49) -> 1.7494621
A28: INTERCEPT() | B28: =INTERCEPT(Data!$I$2:$I$49,Data!$N$2:$N$49) -> 2552.7054
A29: RSQ() | B29: =RSQ(Data!$I$2:$I$49,Data!$N$2:$N$49) -> 0.97534178
A30: CORREL() | B30: =CORREL(Data!$I$2:$I$49,Data!$N$2:$N$49) -> 0.98759393
A32: Interpretation
A33: =" Each additional flu/respiratory case is associated with "&TEXT($B$22,"0.00")&" more ER visits per month; flu cases alone explain "&TEXT(B7,"0.0%")&" of the variance in ER visits." -> Each additional flu/respiratory case is associated with 1.75 more ER visits per month; flu cases alone explain 98.8% of the variance in ER visits.

Sheet MLR_Full
A1: Unit 5 · Multiple linear regression: ER_Visits ~ Flu_Resp_Cases + Pop_Density_Idx + Vacc_Coverage + Winter
A2: 3 continuous predictors + 1 categorical baseline dummy (Winter = Dec–Feb; baseline = other months). Expenditure and ICU excluded (outcomes, not drivers).
M3: Date | N3: ER_Visits | O3: Flu_Resp_Cases | P3: Pop_Density_Idx | Q3: Vacc_Coverage | R3: Winter | S3: Predicted | T3: Residual | U3: Std residual | V3: Residual² | W3: (e_t − e_t−1)²
A4: SUMMARY OUTPUT | M4: =Data!B2 -> 44197 | N4: =Data!I2 -> 4820 | O4: =Data!N2 -> 1340 | P4: =Data!L2 -> 102.3 | Q4: =Data!M2 -> 61.2 | R4: =Data!G2 -> 1 | S4: =$B$21+$B$22*O4+$B$23*P4+$B$24*Q4+$B$25*R4 -> 4779.5462 | T4: =N4-S4 -> 40.4538 | U4: =T4/$B$7 -> 40.565289 | V4: =T4^2 -> 1636.51
M5: =Data!B3 -> 44228 | N5: =Data!I3 -> 4510 | O5: =Data!N3 -> 1180 | P5: =Data!L3 -> 102.5 | Q5: =Data!M3 -> 63.8 | R5: =Data!G3 -> 1 | S5: =$B$21+$B$22*O5+$B$23*P5+$B$24*Q5+$B$25*R5 -> 4504.3982 | T5: =N5-S5 -> 5.6018282 | U5: =T5/$B$7 -> 5.6172666 | V5: =T5^2 -> 31.380479 | W5: =(T5-T4)^2 -> 1214.66
A6: Regression Statistics | M6: =Data!B4 -> 44256 | N6: =Data!I4 -> 4180 | O6: =Data!N4 -> 980 | P6: =Data!L4 -> 102.8 | Q6: =Data!M4 -> 66.1 | R6: =Data!G4 -> 0 | S6: =$B$21+$B$22*O6+$B$23*P6+$B$24*Q6+$B$25*R6 -> 4162.4824 | T6: =N6-S6 -> 17.517632 | U6: =T6/$B$7 -> 17.56591 | V6: =T6^2 -> 306.86744 | W6: =(T6-T5)^2 -> 141.98639
A7: Multiple R | B7: =SQRT(B8) -> 0.99725162 | M7: =Data!B5 -> 44287 | N7: =Data!I5 -> 3920 | O7: =Data!N5 -> 820 | P7: =Data!L5 -> 103 | Q7: =Data!M5 -> 68.4 | R7: =Data!G5 -> 0 | S7: =$B$21+$B$22*O7+$B$23*P7+$B$24*Q7+$B$25*R7 -> 3889.7779 | T7: =N7-S7 -> 30.222101 | U7: =T7/$B$7 -> 30.305392 | V7: =T7^2 -> 913.37539 | W7: =(T7-T6)^2 -> 161.40353
A8: R Square | B8: =INDEX(LINEST($N$4:$N$51,$O$4:$R$51,TRUE(),TRUE()),3,1) -> 0.99451079 | M8: =Data!B6 -> 44317 | N8: =Data!I6 -> 3710 | O8: =Data!N6 -> 740 | P8: =Data!L6 -> 103.2 | Q8: =Data!M6 -> 70.2 | R8: =Data!G6 -> 0 | S8: =$B$21+$B$22*O8+$B$23*P8+$B$24*Q8+$B$25*R8 -> 3752.8373 | T8: =N8-S8 -> -42.837312 | U8: =T8/$B$7 -> -42.95537 | V8: =T8^2 -> 1835.0353 | W8: =(T8-T7)^2 -> 5337.6778
A9: Adjusted R Square | B9: =1-(1-B8)*(B11-1)/(B11-4-1) -> 0.99400016 | M9: =Data!B7 -> 44348 | N9: =Data!I7 -> 3580 | O9: =Data!N7 -> 690 | P9: =Data!L7 -> 103.4 | Q9: =Data!M7 -> 71.5 | R9: =Data!G7 -> 0 | S9: =$B$21+$B$22*O9+$B$23*P9+$B$24*Q9+$B$25*R9 -> 3669.3536 | T9: =N9-S9 -> -89.353554 | U9: =T9/$B$7 -> -89.599808 | V9: =T9^2 -> 7984.0576 | W9: =(T9-T8)^2 -> 2163.7608
A10: Standard Error | B10: =INDEX(LINEST($N$4:$N$51,$O$4:$R$51,TRUE(),TRUE()),3,2) -> 57.271258 | M10: =Data!B8 -> 44378 | N10: =Data!I8 -> 3620 | O10: =Data!N8 -> 720 | P10: =Data!L8 -> 103.6 | Q10: =Data!M8 -> 72 | R10: =Data!G8 -> 0 | S10: =$B$21+$B$22*O10+$B$23*P10+$B$24*Q10+$B$25*R10 -> 3724.0772 | T10: =N10-S10 -> -104.07724 | U10: =T10/$B$7 -> -104.36407 | V10: =T10^2 -> 10832.071 | W10: =(T10-T9)^2 -> 216.78683
A11: Observations | B11: =COUNT($N$4:$N$51) -> 48 | M11: =Data!B9 -> 44409 | N11: =Data!I9 -> 3790 | O11: =Data!N9 -> 810 | P11: =Data!L9 -> 103.8 | Q11: =Data!M9 -> 72.6 | R11: =Data!G9 -> 0 | S11: =$B$21+$B$22*O11+$B$23*P11+$B$24*Q11+$B$25*R11 -> 3876.7549 | T11: =N11-S11 -> -86.754862 | U11: =T11/$B$7 -> -86.993955 | V11: =T11^2 -> 7526.4061 | W11: =(T11-T10)^2 -> 300.06465
M12: =Data!B10 -> 44440 | N12: =Data!I10 -> 4120 | O12: =Data!N10 -> 1020 | P12: =Data!L10 -> 104 | Q12: =Data!M10 -> 73.1 | R12: =Data!G10 -> 0 | S12: =$B$21+$B$22*O12+$B$23*P12+$B$24*Q12+$B$25*R12 -> 4227.7839 | T12: =N12-S12 -> -107.78393 | U12: =T12/$B$7 -> -108.08098 | V12: =T12^2 -> 11617.376 | W12: =(T12-T11)^2 -> 442.22181
M13: =Data!B11 -> 44470 | N13: =Data!I11 -> 4480 | O13: =Data!N11 -> 1190 | P13: =Data!L11 -> 104.2 | Q13: =Data!M11 -> 73.5 | R13: =Data!G11 -> 0 | S13: =$B$21+$B$22*O13+$B$23*P13+$B$24*Q13+$B$25*R13 -> 4513.7819 | T13: =N13-S13 -> -33.781881 | U13: =T13/$B$7 -> -33.874982 | V13: =T13^2 -> 1141.2155 | W13: =(T13-T12)^2 -> 5476.3036
A14: ANOVA | M14: =Data!B12 -> 44501 | N14: =Data!I12 -> 4910 | O14: =Data!N12 -> 1420 | P14: =Data!L12 -> 104.4 | Q14: =Data!M12 -> 73.8 | R14: =Data!G12 -> 0 | S14: =$B$21+$B$22*O14+$B$23*P14+$B$24*Q14+$B$25*R14 -> 4899.3628 | T14: =N14-S14 -> 10.637188 | U14: =T14/$B$7 -> 10.666504 | V14: =T14^2 -> 113.14977 | W14: =(T14-T13)^2 -> 1973.0537
B15: df | C15: SS | D15: MS | E15: F | F15: Significance F | M15: =Data!B13 -> 44531 | N15: =Data!I13 -> 5340 | O15: =Data!N13 -> 1680 | P15: =Data!L13 -> 104.6 | Q15: =Data!M13 -> 74 | R15: =Data!G13 -> 1 | S15: =$B$21+$B$22*O15+$B$23*P15+$B$24*Q15+$B$25*R15 -> 5343.2142 | T15: =N15-S15 -> -3.2142114 | U15: =T15/$B$7 -> -3.2230696 | V15: =T15^2 -> 10.331155 | W15: =(T15-T14)^2 -> 191.86127
A16: Regression | B16: 4 | C16: =INDEX(LINEST($N$4:$N$51,$O$4:$R$51,TRUE(),TRUE()),5,1) -> 25552960 | D16: =C16/B16 -> 6388240 | E16: =INDEX(LINEST($N$4:$N$51,$O$4:$R$51,TRUE(),TRUE()),4,1) -> 1947.6359 | F16: =_xlfn.F.DIST.RT(E16,B16,B17) -> 5.6152295e-48 | M16: =Data!B14 -> 44562 | N16: =Data!I14 -> 5620 | O16: =Data!N14 -> 1820 | P16: =Data!L14 -> 104.9 | Q16: =Data!M14 -> 74.4 | R16: =Data!G14 -> 1 | S16: =$B$21+$B$22*O16+$B$23*P16+$B$24*Q16+$B$25*R16 -> 5584.534 | T16: =N16-S16 -> 35.466047 | U16: =T16/$B$7 -> 35.56379 | V16: =T16^2 -> 1257.8405 | W16: =(T16-T15)^2 -> 1496.1624
A17: Residual | B17: =INDEX(LINEST($N$4:$N$51,$O$4:$R$51,TRUE(),TRUE()),4,2) -> 43 | C17: =INDEX(LINEST($N$4:$N$51,$O$4:$R$51,TRUE(),TRUE()),5,2) -> 141039.87 | D17: =C17/B17 -> 3279.997 | M17: =Data!B15 -> 44593 | N17: =Data!I15 -> 5180 | O17: =Data!N15 -> 1560 | P17: =Data!L15 -> 105.1 | Q17: =Data!M15 -> 75.1 | R17: =Data!G15 -> 1 | S17: =$B$21+$B$22*O17+$B$23*P17+$B$24*Q17+$B$25*R17 -> 5160.2477 | T17: =N17-S17 -> 19.752306 | U17: =T17/$B$7 -> 19.806743 | V17: =T17^2 -> 390.1536 | W17: =(T17-T16)^2 -> 246.92164
A18: Total | B18: =B16+B17 -> 47 | C18: =C16+C17 -> 25694000 | M18: =Data!B16 -> 44621 | N18: =Data!I16 -> 4610 | O18: =Data!N16 -> 1180 | P18: =Data!L16 -> 105.4 | Q18: =Data!M16 -> 75.8 | R18: =Data!G16 -> 0 | S18: =$B$21+$B$22*O18+$B$23*P18+$B$24*Q18+$B$25*R18 -> 4535.0588 | T18: =N18-S18 -> 74.941184 | U18: =T18/$B$7 -> 75.147719 | V18: =T18^2 -> 5616.1811 | W18: =(T18-T17)^2 -> 3045.8123
M19: =Data!B17 -> 44652 | N19: =Data!I17 -> 4230 | O19: =Data!N17 -> 940 | P19: =Data!L17 -> 105.6 | Q19: =Data!M17 -> 76.4 | R19: =Data!G17 -> 0 | S19: =$B$21+$B$22*O19+$B$23*P19+$B$24*Q19+$B$25*R19 -> 4144.5099 | T19: =N19-S19 -> 85.490103 | U19: =T19/$B$7 -> 85.72571 | V19: =T19^2 -> 7308.5578 | W19: =(T19-T18)^2 -> 111.27969
B20: Coefficients | C20: Standard Error | D20: t Stat | E20: P-value | F20: Lower 95% | G20: Upper 95% | H20: Significant at α=0.05? | M20: =Data!B18 -> 44682 | N20: =Data!I18 -> 4010 | O20: =Data!N18 -> 830 | P20: =Data!L18 -> 105.9 | Q20: =Data!M18 -> 77 | R20: =Data!G18 -> 0 | S20: =$B$21+$B$22*O20+$B$23*P20+$B$24*Q20+$B$25*R20 -> 3972.6653 | T20: =N20-S20 -> 37.334662 | U20: =T20/$B$7 -> 37.437555 | V20: =T20^2 -> 1393.877 | W20: =(T20-T19)^2 -> 2318.9465
A21: Intercept | B21: =INDEX(LINEST($N$4:$N$51,$O$4:$R$51,TRUE(),TRUE()),1,5) -> -1750.1318 | C21: =INDEX(LINEST($N$4:$N$51,$O$4:$R$51,TRUE(),TRUE()),2,5) -> 742.66263 | D21: =B21/C21 -> -2.3565637 | E21: =_xlfn.T.DIST.2T(ABS(D21),$B$17) -> 0.023070494 | F21: =B21-_xlfn.T.INV.2T(0.05,$B$17)*C21 -> -3247.8537 | G21: =B21+_xlfn.T.INV.2T(0.05,$B$17)*C21 -> -252.40984 | H21: =IF(E21<0.05,"Yes (reject H0)","No (fail to reject H0)") -> Yes (reject H0) | M21: =Data!B19 -> 44713 | N21: =Data!I19 -> 3860 | O21: =Data!N19 -> 770 | P21: =Data!L19 -> 106.1 | Q21: =Data!M19 -> 77.5 | R21: =Data!G19 -> 0 | S21: =$B$21+$B$22*O21+$B$23*P21+$B$24*Q21+$B$25*R21 -> 3879.2363 | T21: =N21-S21 -> -19.236327 | U21: =T21/$B$7 -> -19.289341 | V21: =T21^2 -> 370.03627 | W21: =(T21-T20)^2 -> 3200.2768
A22: Flu_Resp_Cases | B22: =INDEX(LINEST($N$4:$N$51,$O$4:$R$51,TRUE(),TRUE()),1,4) -> 1.646141 | C22: =INDEX(LINEST($N$4:$N$51,$O$4:$R$51,TRUE(),TRUE()),2,4) -> 0.035206317 | D22: =B22/C22 -> 46.756979 | E22: =_xlfn.T.DIST.2T(ABS(D22),$B$17) -> 1.6635093e-38 | F22: =B22-_xlfn.T.INV.2T(0.05,$B$17)*C22 -> 1.5751407 | G22: =B22+_xlfn.T.INV.2T(0.05,$B$17)*C22 -> 1.7171413 | H22: =IF(E22<0.05,"Yes (reject H0)","No (fail to reject H0)") -> Yes (reject H0) | M22: =Data!B20 -> 44743 | N22: =Data!I20 -> 3910 | O22: =Data!N20 -> 800 | P22: =Data!L20 -> 106.4 | Q22: =Data!M20 -> 77.9 | R22: =Data!G20 -> 0 | S22: =$B$21+$B$22*O22+$B$23*P22+$B$24*Q22+$B$25*R22 -> 3939.4806 | T22: =N22-S22 -> -29.480554 | U22: =T22/$B$7 -> -29.561801 | V22: =T22^2 -> 869.10305 | W22: =(T22-T21)^2 -> 104.94418
A23: Pop_Density_Idx | B23: =INDEX(LINEST($N$4:$N$51,$O$4:$R$51,TRUE(),TRUE()),1,3) -> 47.060247 | C23: =INDEX(LINEST($N$4:$N$51,$O$4:$R$51,TRUE(),TRUE()),2,3) -> 10.607909 | D23: =B23/C23 -> 4.4363359 | E23: =_xlfn.T.DIST.2T(ABS(D23),$B$17) -> 6.255974e-05 | F23: =B23-_xlfn.T.INV.2T(0.05,$B$17)*C23 -> 25.66736 | G23: =B23+_xlfn.T.INV.2T(0.05,$B$17)*C23 -> 68.453134 | H23: =IF(E23<0.05,"Yes (reject H0)","No (fail to reject H0)") -> Yes (reject H0) | M23: =Data!B21 -> 44774 | N23: =Data!I21 -> 4090 | O23: =Data!N21 -> 890 | P23: =Data!L21 -> 106.6 | Q23: =Data!M21 -> 78.3 | R23: =Data!G21 -> 0 | S23: =$B$21+$B$22*O23+$B$23*P23+$B$24*Q23+$B$25*R23 -> 4093.7872 | T23: =N23-S23 -> -3.7872186 | U23: =T23/$B$7 -> -3.797656 | V23: =T23^2 -> 14.343025 | W23: =(T23-T22)^2 -> 660.14747
A24: Vacc_Coverage | B24: =INDEX(LINEST($N$4:$N$51,$O$4:$R$51,TRUE(),TRUE()),1,2) -> -8.1451962 | C24: =INDEX(LINEST($N$4:$N$51,$O$4:$R$51,TRUE(),TRUE()),2,2) -> 5.2958035 | D24: =B24/C24 -> -1.5380473 | E24: =_xlfn.T.DIST.2T(ABS(D24),$B$17) -> 0.13136394 | F24: =B24-_xlfn.T.INV.2T(0.05,$B$17)*C24 -> -18.825202 | G24: =B24+_xlfn.T.INV.2T(0.05,$B$17)*C24 -> 2.5348094 | H24: =IF(E24<0.05,"Yes (reject H0)","No (fail to reject H0)") -> No (fail to reject H0) | M24: =Data!B22 -> 44805 | N24: =Data!I22 -> 4430 | O24: =Data!N22 -> 1120 | P24: =Data!L22 -> 106.9 | Q24: =Data!M22 -> 78.7 | R24: =Data!G22 -> 0 | S24: =$B$21+$B$22*O24+$B$23*P24+$B$24*Q24+$B$25*R24 -> 4483.2597 | T24: =N24-S24 -> -53.259654 | U24: =T24/$B$7 -> -53.406436 | V24: =T24^2 -> 2836.5908 | W24: =(T24-T23)^2 -> 2447.5219
A25: Winter | B25: =INDEX(LINEST($N$4:$N$51,$O$4:$R$51,TRUE(),TRUE()),1,1) -> 8.0717181 | C25: =INDEX(LINEST($N$4:$N$51,$O$4:$R$51,TRUE(),TRUE()),2,1) -> 32.679337 | D25: =B25/C25 -> 0.24699761 | E25: =_xlfn.T.DIST.2T(ABS(D25),$B$17) -> 0.80608556 | F25: =B25-_xlfn.T.INV.2T(0.05,$B$17)*C25 -> -57.832445 | G25: =B25+_xlfn.T.INV.2T(0.05,$B$17)*C25 -> 73.975881 | H25: =IF(E25<0.05,"Yes (reject H0)","No (fail to reject H0)") -> No (fail to reject H0) | M25: =Data!B23 -> 44835 | N25: =Data!I23 -> 4820 | O25: =Data!N23 -> 1310 | P25: =Data!L23 -> 107.1 | Q25: =Data!M23 -> 79 | R25: =Data!G23 -> 0 | S25: =$B$21+$B$22*O25+$B$23*P25+$B$24*Q25+$B$25*R25 -> 4802.9949 | T25: =N25-S25 -> 17.005057 | U25: =T25/$B$7 -> 17.051922 | V25: =T25^2 -> 289.17196 | W25: =(T25-T24)^2 -> 4937.1296
M26: =Data!B24 -> 44866 | N26: =Data!I24 -> 5270 | O26: =Data!N24 -> 1570 | P26: =Data!L24 -> 107.4 | Q26: =Data!M24 -> 79.3 | R26: =Data!G24 -> 0 | S26: =$B$21+$B$22*O26+$B$23*P26+$B$24*Q26+$B$25*R26 -> 5242.6661 | T26: =N26-S26 -> 27.33387 | U26: =T26/$B$7 -> 27.409201 | V26: =T26^2 -> 747.14045 | W26: =(T26-T25)^2 -> 106.68438
A27: Assumption tests | M27: =Data!B25 -> 44896 | N27: =Data!I25 -> 5710 | O27: =Data!N25 -> 1840 | P27: =Data!L25 -> 107.6 | Q27: =Data!M25 -> 79.6 | R27: =Data!G25 -> 1 | S27: =$B$21+$B$22*O27+$B$23*P27+$B$24*Q27+$B$25*R27 -> 5702.1644 | T27: =N27-S27 -> 7.8355796 | U27: =T27/$B$7 -> 7.8571741 | V27: =T27^2 -> 61.396307 | W27: =(T27-T26)^2 -> 380.18333
A28: Test | B28: Statistic | C28: p-value | D28: Conclusion | M28: =Data!B26 -> 44927 | N28: =Data!I26 -> 5980 | O28: =Data!N26 -> 1980 | P28: =Data!L26 -> 107.9 | Q28: =Data!M26 -> 80.1 | R28: =Data!G26 -> 1 | S28: =$B$21+$B$22*O28+$B$23*P28+$B$24*Q28+$B$25*R28 -> 5942.6696 | T28: =N28-S28 -> 37.330357 | U28: =T28/$B$7 -> 37.433238 | V28: =T28^2 -> 1393.5556 | W28: =(T28-T27)^2 -> 869.94192
A29: Residual skewness (population) | B29: =(SUMPRODUCT(T4:T51^3)/48)/(SUMPRODUCT(T4:T51^2)/48)^1.5 -> -0.066418509 | M29: =Data!B27 -> 44958 | N29: =Data!I27 -> 5490 | O29: =Data!N27 -> 1690 | P29: =Data!L27 -> 108.1 | Q29: =Data!M27 -> 80.8 | R29: =Data!G27 -> 1 | S29: =$B$21+$B$22*O29+$B$23*P29+$B$24*Q29+$B$25*R29 -> 5468.9992 | T29: =N29-S29 -> 21.000848 | U29: =T29/$B$7 -> 21.058726 | V29: =T29^2 -> 441.03562 | W29: =(T29-T28)^2 -> 266.65287
A30: Residual excess kurtosis (population) | B30: =(SUMPRODUCT(T4:T51^4)/48)/(SUMPRODUCT(T4:T51^2)/48)^2-3 -> -0.30489238 | M30: =Data!B28 -> 44986 | N30: =Data!I28 -> 4890 | O30: =Data!N28 -> 1270 | P30: =Data!L28 -> 108.4 | Q30: =Data!M28 -> 81.4 | R30: =Data!G28 -> 0 | S30: =$B$21+$B$22*O30+$B$23*P30+$B$24*Q30+$B$25*R30 -> 4778.7792 | T30: =N30-S30 -> 111.22085 | U30: =T30/$B$7 -> 111.52737 | V30: =T30^2 -> 12370.077 | W30: =(T30-T29)^2 -> 8139.6484
A31: Jarque-Bera normality | B31: =48/6*(B29^2+B30^2/4) -> 0.22121007 | C31: =_xlfn.CHISQ.DIST.RT(B31,2) -> 0.89529229 | D31: =IF(C31>0.05,"Residuals normal (fail to reject H0)","Non-normal residuals") -> Residuals normal (fail to reject H0) | M31: =Data!B29 -> 45017 | N31: =Data!I29 -> 4460 | O31: =Data!N29 -> 1010 | P31: =Data!L29 -> 108.7 | Q31: =Data!M29 -> 82 | R31: =Data!G29 -> 0 | S31: =$B$21+$B$22*O31+$B$23*P31+$B$24*Q31+$B$25*R31 -> 4360.0134 | T31: =N31-S31 -> 99.986564 | U31: =T31/$B$7 -> 100.26212 | V31: =T31^2 -> 9997.3129 | W31: =(T31-T30)^2 -> 126.20916
A32: Breusch-Pagan (LM = n·R² of e² on X) | B32: =48*INDEX(LINEST(V4:V51,$O$4:$R$51,TRUE(),TRUE()),3,1) -> 2.0191768 | C32: =_xlfn.CHISQ.DIST.RT(B32,4) -> 0.73223157 | D32: =IF(C32>0.05,"Homoscedastic (fail to reject H0)","Heteroscedastic") -> Homoscedastic (fail to reject H0) | M32: =Data!B30 -> 45047 | N32: =Data!I30 -> 4230 | O32: =Data!N30 -> 890 | P32: =Data!L30 -> 108.9 | Q32: =Data!M30 -> 82.5 | R32: =Data!G30 -> 0 | S32: =$B$21+$B$22*O32+$B$23*P32+$B$24*Q32+$B$25*R32 -> 4167.816 | T32: =N32-S32 -> 62.184038 | U32: =T32/$B$7 -> 62.355414 | V32: =T32^2 -> 3866.8545 | W32: =(T32-T31)^2 -> 1429.031
A33: Durbin-Watson | B33: =SUM(W5:W51)/SUMSQ(T4:T51) -> 0.64075998 | D33: =IF(B33<1.5,"Positive autocorrelation — use HAC SEs (see notebook)",IF(B33>2.5,"Negative autocorrelation","No autocorrelation")) -> Positive autocorrelation — use HAC SEs (see notebook) | M33: =Data!B31 -> 45078 | N33: =Data!I31 -> 4080 | O33: =Data!N31 -> 830 | P33: =Data!L31 -> 109.2 | Q33: =Data!M31 -> 83 | R33: =Data!G31 -> 0 | S33: =$B$21+$B$22*O33+$B$23*P33+$B$24*Q33+$B$25*R33 -> 4079.093 | T33: =N33-S33 -> 0.90702429 | U33: =T33/$B$7 -> 0.90952401 | V33: =T33^2 -> 0.82269306 | W33: =(T33-T32)^2 -> 3754.8724
A34: Shapiro-Wilk (notebook) | C34: 0.5802 | D34: Residuals normal | M34: =Data!B32 -> 45108 | N34: =Data!I32 -> 4140 | O34: =Data!N32 -> 870 | P34: =Data!L32 -> 109.5 | Q34: =Data!M32 -> 83.4 | R34: =Data!G32 -> 0 | S34: =$B$21+$B$22*O34+$B$23*P34+$B$24*Q34+$B$25*R34 -> 4155.7986 | T34: =N34-S34 -> -15.798613 | U34: =T34/$B$7 -> -15.842153 | V34: =T34^2 -> 249.59617 | W34: =(T34-T33)^2 -> 279.07832
M35: =Data!B33 -> 45139 | N35: =Data!I33 -> 4330 | O35: =Data!N33 -> 960 | P35: =Data!L33 -> 109.7 | Q35: =Data!M33 -> 83.8 | R35: =Data!G33 -> 0 | S35: =$B$21+$B$22*O35+$B$23*P35+$B$24*Q35+$B$25*R35 -> 4310.1053 | T35: =N35-S35 -> 19.894722 | U35: =T35/$B$7 -> 19.949551 | V35: =T35^2 -> 395.79997 | W35: =(T35-T34)^2 -> 1274.0142
A36: Multicollinearity — VIF = diagonal of the inverse correlation matrix of predictors | M36: =Data!B34 -> 45170 | N36: =Data!I34 -> 4690 | O36: =Data!N34 -> 1210 | P36: =Data!L34 -> 110 | Q36: =Data!M34 -> 84.2 | R36: =Data!G34 -> 0 | S36: =$B$21+$B$22*O36+$B$23*P36+$B$24*Q36+$B$25*R36 -> 4732.5005 | T36: =N36-S36 -> -42.500535 | U36: =T36/$B$7 -> -42.617664 | V36: =T36^2 -> 1806.2954 | W36: =(T36-T35)^2 -> 3893.168
A37: r | B37: Flu_Resp_Cases | C37: Pop_Density_Idx | D37: Vacc_Coverage | E37: Winter | M37: =Data!B35 -> 45200 | N37: =Data!I35 -> 5090 | O37: =Data!N35 -> 1420 | P37: =Data!L35 -> 110.3 | Q37: =Data!M35 -> 84.5 | R37: =Data!G35 -> 0 | S37: =$B$21+$B$22*O37+$B$23*P37+$B$24*Q37+$B$25*R37 -> 5089.8647 | T37: =N37-S37 -> 0.13533098 | U37: =T37/$B$7 -> 0.13570395 | V37: =T37^2 -> 0.018314474 | W37: =(T37-T36)^2 -> 1817.817
A38: Flu_Resp_Cases | B38: =CORREL(O4:O51,O4:O51) -> 1 | C38: =CORREL(O4:O51,P4:P51) -> 0.34868759 | D38: =CORREL(O4:O51,Q4:Q51) -> 0.30306456 | E38: =CORREL(O4:O51,R4:R51) -> 0.71787021 | M38: =Data!B36 -> 45231 | N38: =Data!I36 -> 5560 | O38: =Data!N36 -> 1700 | P38: =Data!L36 -> 110.6 | Q38: =Data!M36 -> 84.8 | R38: =Data!G36 -> 0 | S38: =$B$21+$B$22*O38+$B$23*P38+$B$24*Q38+$B$25*R38 -> 5562.4587 | T38: =N38-S38 -> -2.4586766 | U38: =T38/$B$7 -> -2.4654526 | V38: =T38^2 -> 6.0450905 | W38: =(T38-T37)^2 -> 6.7288752
A39: Pop_Density_Idx | B39: =CORREL(P4:P51,O4:O51) -> 0.34868759 | C39: =CORREL(P4:P51,P4:P51) -> 1 | D39: =CORREL(P4:P51,Q4:Q51) -> 0.97301257 | E39: =CORREL(P4:P51,R4:R51) -> -0.063098605 | M39: =Data!B37 -> 45261 | N39: =Data!I37 -> 6020 | O39: =Data!N37 -> 1990 | P39: =Data!L37 -> 110.8 | Q39: =Data!M37 -> 85.1 | R39: =Data!G37 -> 1 | S39: =$B$21+$B$22*O39+$B$23*P39+$B$24*Q39+$B$25*R39 -> 6054.8798 | T39: =N39-S39 -> -34.879788 | U39: =T39/$B$7 -> -34.975915 | V39: =T39^2 -> 1216.5996 | W39: =(T39-T38)^2 -> 1051.1285
A40: Vacc_Coverage | B40: =CORREL(Q4:Q51,O4:O51) -> 0.30306456 | C40: =CORREL(Q4:Q51,P4:P51) -> 0.97301257 | D40: =CORREL(Q4:Q51,Q4:Q51) -> 1 | E40: =CORREL(Q4:Q51,R4:R51) -> -0.13232511 | M40: =Data!B38 -> 45292 | N40: =Data!I38 -> 6310 | O40: =Data!N38 -> 2140 | P40: =Data!L38 -> 111.1 | Q40: =Data!M38 -> 85.6 | R40: =Data!G38 -> 1 | S40: =$B$21+$B$22*O40+$B$23*P40+$B$24*Q40+$B$25*R40 -> 6311.8464 | T40: =N40-S40 -> -1.8464206 | U40: =T40/$B$7 -> -1.8515092 | V40: =T40^2 -> 3.4092689 | W40: =(T40-T39)^2 -> 1091.2034
A41: Winter | B41: =CORREL(R4:R51,O4:O51) -> 0.71787021 | C41: =CORREL(R4:R51,P4:P51) -> -0.063098605 | D41: =CORREL(R4:R51,Q4:Q51) -> -0.13232511 | E41: =CORREL(R4:R51,R4:R51) -> 1 | M41: =Data!B39 -> 45323 | N41: =Data!I39 -> 5780 | O41: =Data!N39 -> 1820 | P41: =Data!L39 -> 111.4 | Q41: =Data!M39 -> 86.2 | R41: =Data!G39 -> 1 | S41: =$B$21+$B$22*O41+$B$23*P41+$B$24*Q41+$B$25*R41 -> 5794.3122 | T41: =N41-S41 -> -14.312243 | U41: =T41/$B$7 -> -14.351687 | V41: =T41^2 -> 204.84029 | W41: =(T41-T40)^2 -> 155.39672
M42: =Data!B40 -> 45352 | N42: =Data!I40 -> 5150 | O42: =Data!N40 -> 1370 | P42: =Data!L40 -> 111.7 | Q42: =Data!M40 -> 86.8 | R42: =Data!G40 -> 0 | S42: =$B$21+$B$22*O42+$B$23*P42+$B$24*Q42+$B$25*R42 -> 5054.708 | T42: =N42-S42 -> 95.291989 | U42: =T42/$B$7 -> 95.55461 | V42: =T42^2 -> 9080.5631 | W42: =(T42-T41)^2 -> 12013.088
A43: Predictor | B43: VIF | C43: Tolerance (1/VIF) | D43: Assessment | M43: =Data!B41 -> 45383 | N43: =Data!I41 -> 4690 | O43: =Data!N41 -> 1090 | P43: =Data!L41 -> 111.9 | Q43: =Data!M41 -> 87.3 | R43: =Data!G41 -> 0 | S43: =$B$21+$B$22*O43+$B$23*P43+$B$24*Q43+$B$25*R43 -> 4599.128 | T43: =N43-S43 -> 90.87203 | U43: =T43/$B$7 -> 91.122469 | V43: =T43^2 -> 8257.7258 | W43: =(T43-T42)^2 -> 19.536037
A44: Flu_Resp_Cases | B44: =INDEX(MINVERSE($B$38:$E$41),1,1) -> 3.0941918 | C44: =1/B44 -> 0.32318617 | D44: =IF(B44>10,"Severe multicollinearity (VIF>10)",IF(B44>5,"Moderate (5–10)","Acceptable (<5)")) -> Acceptable (<5) | M44: =Data!B42 -> 45413 | N44: =Data!I42 -> 4450 | O44: =Data!N42 -> 960 | P44: =Data!L42 -> 112.2 | Q44: =Data!M42 -> 87.8 | R44: =Data!G42 -> 0 | S44: =$B$21+$B$22*O44+$B$23*P44+$B$24*Q44+$B$25*R44 -> 4395.1751 | T44: =N44-S44 -> 54.82489 | U44: =T44/$B$7 -> 54.975985 | V44: =T44^2 -> 3005.7685 | W44: =(T44-T43)^2 -> 1299.3963
A45: Pop_Density_Idx | B45: =INDEX(MINVERSE($B$38:$E$41),2,2) -> 20.479887 | C45: =1/B45 -> 0.048828395 | D45: =IF(B45>10,"Severe multicollinearity (VIF>10)",IF(B45>5,"Moderate (5–10)","Acceptable (<5)")) -> Severe multicollinearity (VIF>10) | M45: =Data!B43 -> 45444 | N45: =Data!I43 -> 4290 | O45: =Data!N43 -> 900 | P45: =Data!L43 -> 112.5 | Q45: =Data!M43 -> 88.2 | R45: =Data!G43 -> 0 | S45: =$B$21+$B$22*O45+$B$23*P45+$B$24*Q45+$B$25*R45 -> 4307.2666 | T45: =N45-S45 -> -17.266643 | U45: =T45/$B$7 -> -17.314229 | V45: =T45^2 -> 298.13697 | W45: =(T45-T44)^2 -> 5197.1891
A46: Vacc_Coverage | B46: =INDEX(MINVERSE($B$38:$E$41),3,3) -> 21.110438 | C46: =1/B46 -> 0.047369931 | D46: =IF(B46>10,"Severe multicollinearity (VIF>10)",IF(B46>5,"Moderate (5–10)","Acceptable (<5)")) -> Severe multicollinearity (VIF>10) | M46: =Data!B44 -> 45474 | N46: =Data!I44 -> 4360 | O46: =Data!N44 -> 940 | P46: =Data!L44 -> 112.8 | Q46: =Data!M44 -> 88.6 | R46: =Data!G44 -> 0 | S46: =$B$21+$B$22*O46+$B$23*P46+$B$24*Q46+$B$25*R46 -> 4383.9723 | T46: =N46-S46 -> -23.972281 | U46: =T46/$B$7 -> -24.038347 | V46: =T46^2 -> 574.67024 | W46: =(T46-T45)^2 -> 44.965572
A47: Winter | B47: =INDEX(MINVERSE($B$38:$E$41),4,4) -> 2.9303232 | C47: =1/B47 -> 0.34125929 | D47: =IF(B47>10,"Severe multicollinearity (VIF>10)",IF(B47>5,"Moderate (5–10)","Acceptable (<5)")) -> Acceptable (<5) | M47: =Data!B45 -> 45505 | N47: =Data!I45 -> 4560 | O47: =Data!N45 -> 1040 | P47: =Data!L45 -> 113 | Q47: =Data!M45 -> 89 | R47: =Data!G45 -> 0 | S47: =$B$21+$B$22*O47+$B$23*P47+$B$24*Q47+$B$25*R47 -> 4554.7404 | T47: =N47-S47 -> 5.2596441 | U47: =T47/$B$7 -> 5.2741394 | V47: =T47^2 -> 27.663856 | W47: =(T47-T46)^2 -> 854.50542
M48: =Data!B46 -> 45536 | N48: =Data!I46 -> 4940 | O48: =Data!N46 -> 1310 | P48: =Data!L46 -> 113.3 | Q48: =Data!M46 -> 89.3 | R48: =Data!G46 -> 0 | S48: =$B$21+$B$22*O48+$B$23*P48+$B$24*Q48+$B$25*R48 -> 5010.873 | T48: =N48-S48 -> -70.872953 | U48: =T48/$B$7 -> -71.068276 | V48: =T48^2 -> 5022.9755 | W48: =(T48-T47)^2 -> 5796.1723
M49: =Data!B47 -> 45566 | N49: =Data!I47 -> 5360 | O49: =Data!N47 -> 1540 | P49: =Data!L47 -> 113.6 | Q49: =Data!M47 -> 89.6 | R49: =Data!G47 -> 0 | S49: =$B$21+$B$22*O49+$B$23*P49+$B$24*Q49+$B$25*R49 -> 5401.1599 | T49: =N49-S49 -> -41.159908 | U49: =T49/$B$7 -> -41.273343 | V49: =T49^2 -> 1694.1381 | W49: =(T49-T48)^2 -> 882.86502
M50: =Data!B48 -> 45597 | N50: =Data!I48 -> 5850 | O50: =Data!N48 -> 1840 | P50: =Data!L48 -> 113.9 | Q50: =Data!M48 -> 89.9 | R50: =Data!G48 -> 0 | S50: =$B$21+$B$22*O50+$B$23*P50+$B$24*Q50+$B$25*R50 -> 5906.6767 | T50: =N50-S50 -> -56.676737 | U50: =T50/$B$7 -> -56.832936 | V50: =T50^2 -> 3212.2525 | W50: =(T50-T49)^2 -> 240.77196
M51: =Data!B49 -> 45627 | N51: =Data!I49 -> 6340 | O51: =Data!N49 -> 2160 | P51: =Data!L49 -> 114.2 | Q51: =Data!M49 -> 90.2 | R51: =Data!G49 -> 1 | S51: =$B$21+$B$22*O51+$B$23*P51+$B$24*Q51+$B$25*R51 -> 6453.1881 | T51: =N51-S51 -> -113.1881 | U51: =T51/$B$7 -> -113.50005 | V51: =T51^2 -> 12811.547 | W51: =(T51-T50)^2 -> 3193.5346

Sheet MLR_Refined
A1: Unit 5 · Multiple linear regression: ER_Visits ~ Flu_Resp_Cases + Pop_Density_Idx + Winter
A2: Vaccination coverage removed after VIF > 10 (collinear with population density, r = 0.97). Used for interpretation and the 2025 stress test.
M3: Date | N3: ER_Visits | O3: Flu_Resp_Cases | P3: Pop_Density_Idx | Q3: Winter | R3: Predicted | S3: Residual | T3: Std residual | U3: Residual² | V3: (e_t − e_t−1)²
A4: SUMMARY OUTPUT | M4: =Data!B2 -> 44197 | N4: =Data!I2 -> 4820 | O4: =Data!N2 -> 1340 | P4: =Data!L2 -> 102.3 | Q4: =Data!G2 -> 1 | R4: =$B$21+$B$22*O4+$B$23*P4+$B$24*Q4 -> 4728.0353 | S4: =N4-R4 -> 91.964748 | T4: =S4/$B$7 -> 92.232203 | U4: =S4^2 -> 8457.5148
M5: =Data!B3 -> 44228 | N5: =Data!I3 -> 4510 | O5: =Data!N3 -> 1180 | P5: =Data!L3 -> 102.5 | Q5: =Data!G3 -> 1 | R5: =$B$21+$B$22*O5+$B$23*P5+$B$24*Q5 -> 4472.0556 | S5: =N5-R5 -> 37.944368 | T5: =S5/$B$7 -> 38.054719 | U5: =S5^2 -> 1439.7751 | V5: =(S5-S4)^2 -> 2918.2014
A6: Regression Statistics | M6: =Data!B4 -> 44256 | N6: =Data!I4 -> 4180 | O6: =Data!N4 -> 980 | P6: =Data!L4 -> 102.8 | Q6: =Data!G4 -> 0 | R6: =$B$21+$B$22*O6+$B$23*P6+$B$24*Q6 -> 4130.9484 | S6: =N6-R6 -> 49.051649 | T6: =S6/$B$7 -> 49.194303 | U6: =S6^2 -> 2406.0643 | V6: =(S6-S5)^2 -> 123.3717
A7: Multiple R | B7: =SQRT(B8) -> 0.9971002 | M7: =Data!B5 -> 44287 | N7: =Data!I5 -> 3920 | O7: =Data!N5 -> 820 | P7: =Data!L5 -> 103 | Q7: =Data!G5 -> 0 | R7: =$B$21+$B$22*O7+$B$23*P7+$B$24*Q7 -> 3874.9687 | S7: =N7-R7 -> 45.03127 | T7: =S7/$B$7 -> 45.162232 | U7: =S7^2 -> 2027.8153 | V7: =(S7-S6)^2 -> 16.163451
A8: R Square | B8: =INDEX(LINEST($N$4:$N$51,$O$4:$Q$51,TRUE(),TRUE()),3,1) -> 0.9942088 | M8: =Data!B6 -> 44317 | N8: =Data!I6 -> 3710 | O8: =Data!N6 -> 740 | P8: =Data!L6 -> 103.2 | Q8: =Data!G6 -> 0 | R8: =$B$21+$B$22*O8+$B$23*P8+$B$24*Q8 -> 3750.1134 | S8: =N8-R8 -> -40.113449 | T8: =S8/$B$7 -> -40.230109 | U8: =S8^2 -> 1609.0888 | V8: =(S8-S7)^2 -> 7249.6233
A9: Adjusted R Square | B9: =1-(1-B8)*(B11-1)/(B11-3-1) -> 0.99381395 | M9: =Data!B7 -> 44348 | N9: =Data!I7 -> 3580 | O9: =Data!N7 -> 690 | P9: =Data!L7 -> 103.4 | Q9: =Data!G7 -> 0 | R9: =$B$21+$B$22*O9+$B$23*P9+$B$24*Q9 -> 3674.4298 | S9: =N9-R9 -> -94.429796 | T9: =S9/$B$7 -> -94.704421 | U9: =S9^2 -> 8916.9865 | V9: =(S9-S8)^2 -> 2950.2655
A10: Standard Error | B10: =INDEX(LINEST($N$4:$N$51,$O$4:$Q$51,TRUE(),TRUE()),3,2) -> 58.153206 | M10: =Data!B8 -> 44378 | N10: =Data!I8 -> 3620 | O10: =Data!N8 -> 720 | P10: =Data!L8 -> 103.6 | Q10: =Data!G8 -> 0 | R10: =$B$21+$B$22*O10+$B$23*P10+$B$24*Q10 -> 3729.8705 | S10: =N10-R10 -> -109.87048 | T10: =S10/$B$7 -> -110.19001 | U10: =S10^2 -> 12071.523 | V10: =(S10-S9)^2 -> 238.41482
A11: Observations | B11: =COUNT($N$4:$N$51) -> 48 | M11: =Data!B9 -> 44409 | N11: =Data!I9 -> 3790 | O11: =Data!N9 -> 810 | P11: =Data!L9 -> 103.8 | Q11: =Data!G9 -> 0 | R11: =$B$21+$B$22*O11+$B$23*P11+$B$24*Q11 -> 3883.6544 | S11: =N11-R11 -> -93.654425 | T11: =S11/$B$7 -> -93.926795 | U11: =S11^2 -> 8771.1514 | V11: =(S11-S10)^2 -> 262.96054
M12: =Data!B10 -> 44440 | N12: =Data!I10 -> 4120 | O12: =Data!N10 -> 1020 | P12: =Data!L10 -> 104 | Q12: =Data!G10 -> 0 | R12: =$B$21+$B$22*O12+$B$23*P12+$B$24*Q12 -> 4234.1249 | S12: =N12-R12 -> -114.12488 | T12: =S12/$B$7 -> -114.45678 | U12: =S12^2 -> 13024.488 | V12: =(S12-S11)^2 -> 419.03941
M13: =Data!B11 -> 44470 | N13: =Data!I11 -> 4480 | O13: =Data!N11 -> 1190 | P13: =Data!L11 -> 104.2 | Q13: =Data!G11 -> 0 | R13: =$B$21+$B$22*O13+$B$23*P13+$B$24*Q13 -> 4519.0332 | S13: =N13-R13 -> -39.03316 | T13: =S13/$B$7 -> -39.146677 | U13: =S13^2 -> 1523.5875 | V13: =(S13-S12)^2 -> 5638.7661
A14: ANOVA | M14: =Data!B12 -> 44501 | N14: =Data!I12 -> 4910 | O14: =Data!N12 -> 1420 | P14: =Data!L12 -> 104.4 | Q14: =Data!G12 -> 0 | R14: =$B$21+$B$22*O14+$B$23*P14+$B$24*Q14 -> 4902.2847 | S14: =N14-R14 -> 7.7153034 | T14: =S14/$B$7 -> 7.7377413 | U14: =S14^2 -> 59.525906 | V14: =(S14-S13)^2 -> 2185.4188
B15: df | C15: SS | D15: MS | E15: F | F15: Significance F | M15: =Data!B13 -> 44531 | N15: =Data!I13 -> 5340 | O15: =Data!N13 -> 1680 | P15: =Data!L13 -> 104.6 | Q15: =Data!G13 -> 1 | R15: =$B$21+$B$22*O15+$B$23*P15+$B$24*Q15 -> 5357.4079 | S15: =N15-R15 -> -17.407882 | T15: =S15/$B$7 -> -17.458508 | U15: =S15^2 -> 303.03434 | V15: =(S15-S14)^2 -> 631.17442
A16: Regression | B16: 3 | C16: =INDEX(LINEST($N$4:$N$51,$O$4:$Q$51,TRUE(),TRUE()),5,1) -> 25545201 | D16: =C16/B16 -> 8515067 | E16: =INDEX(LINEST($N$4:$N$51,$O$4:$Q$51,TRUE(),TRUE()),4,1) -> 2517.9131 | F16: =_xlfn.F.DIST.RT(E16,B16,B17) -> 3.2408205e-49 | M16: =Data!B14 -> 44562 | N16: =Data!I14 -> 5620 | O16: =Data!N14 -> 1820 | P16: =Data!L14 -> 104.9 | Q16: =Data!G14 -> 1 | R16: =$B$21+$B$22*O16+$B$23*P16+$B$24*Q16 -> 5596.2791 | S16: =N16-R16 -> 23.720934 | T16: =S16/$B$7 -> 23.78992 | U16: =S16^2 -> 562.68272 | V16: =(S16-S15)^2 -> 1691.5795
A17: Residual | B17: =INDEX(LINEST($N$4:$N$51,$O$4:$Q$51,TRUE(),TRUE()),4,2) -> 44 | C17: =INDEX(LINEST($N$4:$N$51,$O$4:$Q$51,TRUE(),TRUE()),5,2) -> 148799 | D17: =C17/B17 -> 3381.7954 | M17: =Data!B15 -> 44593 | N17: =Data!I15 -> 5180 | O17: =Data!N15 -> 1560 | P17: =Data!L15 -> 105.1 | Q17: =Data!G15 -> 1 | R17: =$B$21+$B$22*O17+$B$23*P17+$B$24*Q17 -> 5176.394 | S17: =N17-R17 -> 3.6059797 | T17: =S17/$B$7 -> 3.6164668 | U17: =S17^2 -> 13.00309 | V17: =(S17-S16)^2 -> 404.61139
A18: Total | B18: =B16+B17 -> 47 | C18: =C16+C17 -> 25694000 | M18: =Data!B16 -> 44621 | N18: =Data!I16 -> 4610 | O18: =Data!N16 -> 1180 | P18: =Data!L16 -> 105.4 | Q18: =Data!G16 -> 0 | R18: =$B$21+$B$22*O18+$B$23*P18+$B$24*Q18 -> 4540.257 | S18: =N18-R18 -> 69.743026 | T18: =S18/$B$7 -> 69.945855 | U18: =S18^2 -> 4864.0897 | V18: =(S18-S17)^2 -> 4374.1089
M19: =Data!B17 -> 44652 | N19: =Data!I17 -> 4230 | O19: =Data!N17 -> 940 | P19: =Data!L17 -> 105.6 | Q19: =Data!G17 -> 0 | R19: =$B$21+$B$22*O19+$B$23*P19+$B$24*Q19 -> 4153.153 | S19: =N19-R19 -> 76.846987 | T19: =S19/$B$7 -> 77.070476 | U19: =S19^2 -> 5905.4593 | V19: =(S19-S18)^2 -> 50.466256
B20: Coefficients | C20: Standard Error | D20: t Stat | E20: P-value | F20: Lower 95% | G20: Upper 95% | H20: Significant at α=0.05? | M20: =Data!B18 -> 44682 | N20: =Data!I18 -> 4010 | O20: =Data!N18 -> 830 | P20: =Data!L18 -> 105.9 | Q20: =Data!G18 -> 0 | R20: =$B$21+$B$22*O20+$B$23*P20+$B$24*Q20 -> 3982.2606 | S20: =N20-R20 -> 27.739365 | T20: =S20/$B$7 -> 27.820037 | U20: =S20^2 -> 769.47236 | V20: =(S20-S19)^2 -> 2411.5585
A21: Intercept | B21: =INDEX(LINEST($N$4:$N$51,$O$4:$Q$51,TRUE(),TRUE()),1,4) -> -697.62139 | C21: =INDEX(LINEST($N$4:$N$51,$O$4:$Q$51,TRUE(),TRUE()),2,4) -> 292.99051 | D21: =B21/C21 -> -2.3810375 | E21: =_xlfn.T.DIST.2T(ABS(D21),$B$17) -> 0.02165764 | F21: =B21-_xlfn.T.INV.2T(0.05,$B$17)*C21 -> -1288.105 | G21: =B21+_xlfn.T.INV.2T(0.05,$B$17)*C21 -> -107.13782 | H21: =IF(E21<0.05,"Yes (reject H0)","No (fail to reject H0)") -> Yes (reject H0) | M21: =Data!B19 -> 44713 | N21: =Data!I19 -> 3860 | O21: =Data!N19 -> 770 | P21: =Data!L19 -> 106.1 | Q21: =Data!G19 -> 0 | R21: =$B$21+$B$22*O21+$B$23*P21+$B$24*Q21 -> 3890.1864 | S21: =N21-R21 -> -30.18644 | T21: =S21/$B$7 -> -30.274229 | U21: =S21^2 -> 911.22114 | V21: =(S21-S20)^2 -> 3355.3988
A22: Flu_Resp_Cases | B22: =INDEX(LINEST($N$4:$N$51,$O$4:$Q$51,TRUE(),TRUE()),1,3) -> 1.6390543 | C22: =INDEX(LINEST($N$4:$N$51,$O$4:$Q$51,TRUE(),TRUE()),2,3) -> 0.035440995 | D22: =B22/C22 -> 46.24741 | E22: =_xlfn.T.DIST.2T(ABS(D22),$B$17) -> 6.0190208e-39 | F22: =B22-_xlfn.T.INV.2T(0.05,$B$17)*C22 -> 1.5676276 | G22: =B22+_xlfn.T.INV.2T(0.05,$B$17)*C22 -> 1.7104809 | H22: =IF(E22<0.05,"Yes (reject H0)","No (fail to reject H0)") -> Yes (reject H0) | M22: =Data!B20 -> 44743 | N22: =Data!I20 -> 3910 | O22: =Data!N20 -> 800 | P22: =Data!L20 -> 106.4 | Q22: =Data!G20 -> 0 | R22: =$B$21+$B$22*O22+$B$23*P22+$B$24*Q22 -> 3948.7617 | S22: =N22-R22 -> -38.761656 | T22: =S22/$B$7 -> -38.874384 | U22: =S22^2 -> 1502.466 | V22: =(S22-S21)^2 -> 73.534342
A23: Pop_Density_Idx | B23: =INDEX(LINEST($N$4:$N$51,$O$4:$Q$51,TRUE(),TRUE()),1,2) -> 31.345297 | C23: =INDEX(LINEST($N$4:$N$51,$O$4:$Q$51,TRUE(),TRUE()),2,2) -> 2.8954153 | D23: =B23/C23 -> 10.825838 | E23: =_xlfn.T.DIST.2T(ABS(D23),$B$17) -> 5.4637188e-14 | F23: =B23-_xlfn.T.INV.2T(0.05,$B$17)*C23 -> 25.509971 | G23: =B23+_xlfn.T.INV.2T(0.05,$B$17)*C23 -> 37.180624 | H23: =IF(E23<0.05,"Yes (reject H0)","No (fail to reject H0)") -> Yes (reject H0) | M23: =Data!B21 -> 44774 | N23: =Data!I21 -> 4090 | O23: =Data!N21 -> 890 | P23: =Data!L21 -> 106.6 | Q23: =Data!G21 -> 0 | R23: =$B$21+$B$22*O23+$B$23*P23+$B$24*Q23 -> 4102.5456 | S23: =N23-R23 -> -12.545598 | T23: =S23/$B$7 -> -12.582084 | U23: =S23^2 -> 157.39204 | V23: =(S23-S22)^2 -> 687.2817
A24: Winter | B24: =INDEX(LINEST($N$4:$N$51,$O$4:$Q$51,TRUE(),TRUE()),1,1) -> 22.70002 | C24: =INDEX(LINEST($N$4:$N$51,$O$4:$Q$51,TRUE(),TRUE()),2,1) -> 31.746148 | D24: =B24/C24 -> 0.71504801 | E24: =_xlfn.T.DIST.2T(ABS(D24),$B$17) -> 0.47835648 | F24: =B24-_xlfn.T.INV.2T(0.05,$B$17)*C24 -> -41.280138 | G24: =B24+_xlfn.T.INV.2T(0.05,$B$17)*C24 -> 86.680179 | H24: =IF(E24<0.05,"Yes (reject H0)","No (fail to reject H0)") -> No (fail to reject H0) | M24: =Data!B22 -> 44805 | N24: =Data!I22 -> 4430 | O24: =Data!N22 -> 1120 | P24: =Data!L22 -> 106.9 | Q24: =Data!G22 -> 0 | R24: =$B$21+$B$22*O24+$B$23*P24+$B$24*Q24 -> 4488.9317 | S24: =N24-R24 -> -58.931665 | T24: =S24/$B$7 -> -59.103052 | U24: =S24^2 -> 3472.9412 | V24: =(S24-S23)^2 -> 2151.6672
M25: =Data!B23 -> 44835 | N25: =Data!I23 -> 4820 | O25: =Data!N23 -> 1310 | P25: =Data!L23 -> 107.1 | Q25: =Data!G23 -> 0 | R25: =$B$21+$B$22*O25+$B$23*P25+$B$24*Q25 -> 4806.621 | S25: =N25-R25 -> 13.378968 | T25: =S25/$B$7 -> 13.417877 | U25: =S25^2 -> 178.99678 | V25: =(S25-S24)^2 -> 5228.8276
A26: Assumption tests | M26: =Data!B24 -> 44866 | N26: =Data!I24 -> 5270 | O26: =Data!N24 -> 1570 | P26: =Data!L24 -> 107.4 | Q26: =Data!G24 -> 0 | R26: =$B$21+$B$22*O26+$B$23*P26+$B$24*Q26 -> 5242.1787 | S26: =N26-R26 -> 27.821273 | T26: =S26/$B$7 -> 27.902184 | U26: =S26^2 -> 774.02325 | V26: =(S26-S25)^2 -> 208.58019
A27: Test | B27: Statistic | C27: p-value | D27: Conclusion | M27: =Data!B25 -> 44896 | N27: =Data!I25 -> 5710 | O27: =Data!N25 -> 1840 | P27: =Data!L25 -> 107.6 | Q27: =Data!G25 -> 1 | R27: =$B$21+$B$22*O27+$B$23*P27+$B$24*Q27 -> 5713.6925 | S27: =N27-R27 -> -3.692454 | T27: =S27/$B$7 -> -3.7031926 | U27: =S27^2 -> 13.634217 | V27: =(S27-S26)^2 -> 993.11502
A28: Residual skewness (population) | B28: =(SUMPRODUCT(S4:S51^3)/48)/(SUMPRODUCT(S4:S51^2)/48)^1.5 -> -0.035266074 | M28: =Data!B26 -> 44927 | N28: =Data!I26 -> 5980 | O28: =Data!N26 -> 1980 | P28: =Data!L26 -> 107.9 | Q28: =Data!G26 -> 1 | R28: =$B$21+$B$22*O28+$B$23*P28+$B$24*Q28 -> 5952.5636 | S28: =N28-R28 -> 27.436362 | T28: =S28/$B$7 -> 27.516153 | U28: =S28^2 -> 752.75394 | V28: =(S28-S27)^2 -> 969.00317
A29: Residual excess kurtosis (population) | B29: =(SUMPRODUCT(S4:S51^4)/48)/(SUMPRODUCT(S4:S51^2)/48)^2-3 -> -0.3994827 | M29: =Data!B27 -> 44958 | N29: =Data!I27 -> 5490 | O29: =Data!N27 -> 1690 | P29: =Data!L27 -> 108.1 | Q29: =Data!G27 -> 1 | R29: =$B$21+$B$22*O29+$B$23*P29+$B$24*Q29 -> 5483.507 | S29: =N29-R29 -> 6.4930348 | T29: =S29/$B$7 -> 6.511918 | U29: =S29^2 -> 42.1595 | V29: =(S29-S28)^2 -> 438.62294
A30: Jarque-Bera normality | B30: =48/6*(B28^2+B29^2/4) -> 0.32912243 | C30: =_xlfn.CHISQ.DIST.RT(B30,2) -> 0.84826583 | D30: =IF(C30>0.05,"Residuals normal (fail to reject H0)","Non-normal residuals") -> Residuals normal (fail to reject H0) | M30: =Data!B28 -> 44986 | N30: =Data!I28 -> 4890 | O30: =Data!N28 -> 1270 | P30: =Data!L28 -> 108.4 | Q30: =Data!G28 -> 0 | R30: =$B$21+$B$22*O30+$B$23*P30+$B$24*Q30 -> 4781.8077 | S30: =N30-R30 -> 108.19225 | T30: =S30/$B$7 -> 108.5069 | U30: =S30^2 -> 11705.563 | V30: =(S30-S29)^2 -> 10342.731
A31: Breusch-Pagan (LM = n·R² of e² on X) | B31: =48*INDEX(LINEST(U4:U51,$O$4:$Q$51,TRUE(),TRUE()),3,1) -> 2.2744349 | C31: =_xlfn.CHISQ.DIST.RT(B31,3) -> 0.51743618 | D31: =IF(C31>0.05,"Homoscedastic (fail to reject H0)","Heteroscedastic") -> Homoscedastic (fail to reject H0) | M31: =Data!B29 -> 45017 | N31: =Data!I29 -> 4460 | O31: =Data!N29 -> 1010 | P31: =Data!L29 -> 108.7 | Q31: =Data!G29 -> 0 | R31: =$B$21+$B$22*O31+$B$23*P31+$B$24*Q31 -> 4365.0572 | S31: =N31-R31 -> 94.942767 | T31: =S31/$B$7 -> 95.218883 | U31: =S31^2 -> 9014.129 | V31: =(S31-S30)^2 -> 175.54883
A32: Durbin-Watson | B32: =SUM(V5:V51)/SUMSQ(S4:S51) -> 0.70484666 | D32: =IF(B32<1.5,"Positive autocorrelation — use HAC SEs (see notebook)",IF(B32>2.5,"Negative autocorrelation","No autocorrelation")) -> Positive autocorrelation — use HAC SEs (see notebook) | M32: =Data!B30 -> 45047 | N32: =Data!I30 -> 4230 | O32: =Data!N30 -> 890 | P32: =Data!L30 -> 108.9 | Q32: =Data!G30 -> 0 | R32: =$B$21+$B$22*O32+$B$23*P32+$B$24*Q32 -> 4174.6398 | S32: =N32-R32 -> 55.360217 | T32: =S32/$B$7 -> 55.521218 | U32: =S32^2 -> 3064.7537 | V32: =(S32-S31)^2 -> 1566.7782
A33: Shapiro-Wilk (notebook) | C33: 0.3944 | D33: Residuals normal | M33: =Data!B31 -> 45078 | N33: =Data!I31 -> 4080 | O33: =Data!N31 -> 830 | P33: =Data!L31 -> 109.2 | Q33: =Data!G31 -> 0 | R33: =$B$21+$B$22*O33+$B$23*P33+$B$24*Q33 -> 4085.7001 | S33: =N33-R33 -> -5.7001168 | T33: =S33/$B$7 -> -5.7166941 | U33: =S33^2 -> 32.491332 | V33: =(S33-S32)^2 -> 3728.3644
M34: =Data!B32 -> 45108 | N34: =Data!I32 -> 4140 | O34: =Data!N32 -> 870 | P34: =Data!L32 -> 109.5 | Q34: =Data!G32 -> 0 | R34: =$B$21+$B$22*O34+$B$23*P34+$B$24*Q34 -> 4160.6659 | S34: =N34-R34 -> -20.665876 | T34: =S34/$B$7 -> -20.725977 | U34: =S34^2 -> 427.07843 | V34: =(S34-S33)^2 -> 223.97395
A35: Multicollinearity — VIF = diagonal of the inverse correlation matrix of predictors | M35: =Data!B33 -> 45139 | N35: =Data!I33 -> 4330 | O35: =Data!N33 -> 960 | P35: =Data!L33 -> 109.7 | Q35: =Data!G33 -> 0 | R35: =$B$21+$B$22*O35+$B$23*P35+$B$24*Q35 -> 4314.4498 | S35: =N35-R35 -> 15.550182 | T35: =S35/$B$7 -> 15.595405 | U35: =S35^2 -> 241.80816 | V35: =(S35-S34)^2 -> 1311.6029
A36: r | B36: Flu_Resp_Cases | C36: Pop_Density_Idx | D36: Winter | M36: =Data!B34 -> 45170 | N36: =Data!I34 -> 4690 | O36: =Data!N34 -> 1210 | P36: =Data!L34 -> 110 | Q36: =Data!G34 -> 0 | R36: =$B$21+$B$22*O36+$B$23*P36+$B$24*Q36 -> 4733.617 | S36: =N36-R36 -> -43.61697 | T36: =S36/$B$7 -> -43.743818 | U36: =S36^2 -> 1902.4401 | V36: =(S36-S35)^2 -> 3500.7519
A37: Flu_Resp_Cases | B37: =CORREL(O4:O51,O4:O51) -> 1 | C37: =CORREL(O4:O51,P4:P51) -> 0.34868759 | D37: =CORREL(O4:O51,Q4:Q51) -> 0.71787021 | M37: =Data!B35 -> 45200 | N37: =Data!I35 -> 5090 | O37: =Data!N35 -> 1420 | P37: =Data!L35 -> 110.3 | Q37: =Data!G35 -> 0 | R37: =$B$21+$B$22*O37+$B$23*P37+$B$24*Q37 -> 5087.222 | S37: =N37-R37 -> 2.7780483 | T37: =S37/$B$7 -> 2.7861275 | U37: =S37^2 -> 7.7175523 | V37: =(S37-S36)^2 -> 2152.4977
A38: Pop_Density_Idx | B38: =CORREL(P4:P51,O4:O51) -> 0.34868759 | C38: =CORREL(P4:P51,P4:P51) -> 1 | D38: =CORREL(P4:P51,Q4:Q51) -> -0.063098605 | M38: =Data!B36 -> 45231 | N38: =Data!I36 -> 5560 | O38: =Data!N36 -> 1700 | P38: =Data!L36 -> 110.6 | Q38: =Data!G36 -> 0 | R38: =$B$21+$B$22*O38+$B$23*P38+$B$24*Q38 -> 5555.5607 | S38: =N38-R38 -> 4.439269 | T38: =S38/$B$7 -> 4.4521794 | U38: =S38^2 -> 19.707109 | V38: =(S38-S37)^2 -> 2.7596542
A39: Winter | B39: =CORREL(Q4:Q51,O4:O51) -> 0.71787021 | C39: =CORREL(Q4:Q51,P4:P51) -> -0.063098605 | D39: =CORREL(Q4:Q51,Q4:Q51) -> 1 | M39: =Data!B37 -> 45261 | N39: =Data!I37 -> 6020 | O39: =Data!N37 -> 1990 | P39: =Data!L37 -> 110.8 | Q39: =Data!G37 -> 1 | R39: =$B$21+$B$22*O39+$B$23*P39+$B$24*Q39 -> 6059.8555 | S39: =N39-R39 -> -39.855543 | T39: =S39/$B$7 -> -39.971453 | U39: =S39^2 -> 1588.4643 | V39: =(S39-S38)^2 -> 1962.0304
M40: =Data!B38 -> 45292 | N40: =Data!I38 -> 6310 | O40: =Data!N38 -> 2140 | P40: =Data!L38 -> 111.1 | Q40: =Data!G38 -> 1 | R40: =$B$21+$B$22*O40+$B$23*P40+$B$24*Q40 -> 6315.1173 | S40: =N40-R40 -> -5.1172703 | T40: =S40/$B$7 -> -5.1321525 | U40: =S40^2 -> 26.186455 | V40: =(S40-S39)^2 -> 1206.7476
A41: Predictor | B41: VIF | C41: Tolerance (1/VIF) | D41: Assessment | M41: =Data!B39 -> 45323 | N41: =Data!I39 -> 5780 | O41: =Data!N39 -> 1820 | P41: =Data!L39 -> 111.4 | Q41: =Data!G39 -> 1 | R41: =$B$21+$B$22*O41+$B$23*P41+$B$24*Q41 -> 5800.0235 | S41: =N41-R41 -> -20.023499 | T41: =S41/$B$7 -> -20.081732 | U41: =S41^2 -> 400.94053 | V41: =(S41-S40)^2 -> 222.19567
A42: Flu_Resp_Cases | B42: =INDEX(MINVERSE($B$37:$D$39),1,1) -> 3.041193 | C42: =1/B42 -> 0.32881833 | D42: =IF(B42>10,"Severe multicollinearity (VIF>10)",IF(B42>5,"Moderate (5–10)","Acceptable (<5)")) -> Acceptable (<5) | M42: =Data!B40 -> 45352 | N42: =Data!I40 -> 5150 | O42: =Data!N40 -> 1370 | P42: =Data!L40 -> 111.7 | Q42: =Data!G40 -> 0 | R42: =$B$21+$B$22*O42+$B$23*P42+$B$24*Q42 -> 5049.1527 | S42: =N42-R42 -> 100.84734 | T42: =S42/$B$7 -> 101.14063 | U42: =S42^2 -> 10170.187 | V42: =(S42-S41)^2 -> 14609.761
A43: Pop_Density_Idx | B43: =INDEX(MINVERSE($B$37:$D$39),2,2) -> 1.4798437 | C43: =1/B43 -> 0.67574705 | D43: =IF(B43>10,"Severe multicollinearity (VIF>10)",IF(B43>5,"Moderate (5–10)","Acceptable (<5)")) -> Acceptable (<5) | M43: =Data!B41 -> 45383 | N43: =Data!I41 -> 4690 | O43: =Data!N41 -> 1090 | P43: =Data!L41 -> 111.9 | Q43: =Data!G41 -> 0 | R43: =$B$21+$B$22*O43+$B$23*P43+$B$24*Q43 -> 4596.4865 | S43: =N43-R43 -> 93.513475 | T43: =S43/$B$7 -> 93.785434 | U43: =S43^2 -> 8744.77 | V43: =(S43-S42)^2 -> 53.785641
A44: Winter | B44: =INDEX(MINVERSE($B$37:$D$39),3,3) -> 2.6821142 | C44: =1/B44 -> 0.3728402 | D44: =IF(B44>10,"Severe multicollinearity (VIF>10)",IF(B44>5,"Moderate (5–10)","Acceptable (<5)")) -> Acceptable (<5) | M44: =Data!B42 -> 45413 | N44: =Data!I42 -> 4450 | O44: =Data!N42 -> 960 | P44: =Data!L42 -> 112.2 | Q44: =Data!G42 -> 0 | R44: =$B$21+$B$22*O44+$B$23*P44+$B$24*Q44 -> 4392.8131 | S44: =N44-R44 -> 57.186938 | T44: =S44/$B$7 -> 57.353251 | U44: =S44^2 -> 3270.3459 | V44: =(S44-S43)^2 -> 1319.6173
M45: =Data!B43 -> 45444 | N45: =Data!I43 -> 4290 | O45: =Data!N43 -> 900 | P45: =Data!L43 -> 112.5 | Q45: =Data!G43 -> 0 | R45: =$B$21+$B$22*O45+$B$23*P45+$B$24*Q45 -> 4303.8734 | S45: =N45-R45 -> -13.873396 | T45: =S45/$B$7 -> -13.913743 | U45: =S45^2 -> 192.47112 | V45: =(S45-S44)^2 -> 5049.5711
M46: =Data!B44 -> 45474 | N46: =Data!I44 -> 4360 | O46: =Data!N44 -> 940 | P46: =Data!L44 -> 112.8 | Q46: =Data!G44 -> 0 | R46: =$B$21+$B$22*O46+$B$23*P46+$B$24*Q46 -> 4378.8392 | S46: =N46-R46 -> -18.839155 | T46: =S46/$B$7 -> -18.893944 | U46: =S46^2 -> 354.91377 | V46: =(S46-S45)^2 -> 24.658765
M47: =Data!B45 -> 45505 | N47: =Data!I45 -> 4560 | O47: =Data!N45 -> 1040 | P47: =Data!L45 -> 113 | Q47: =Data!G45 -> 0 | R47: =$B$21+$B$22*O47+$B$23*P47+$B$24*Q47 -> 4549.0136 | S47: =N47-R47 -> 10.98636 | T47: =S47/$B$7 -> 11.018311 | U47: =S47^2 -> 120.70011 | V47: =(S47-S46)^2 -> 889.56137
M48: =Data!B46 -> 45536 | N48: =Data!I46 -> 4940 | O48: =Data!N46 -> 1310 | P48: =Data!L46 -> 113.3 | Q48: =Data!G46 -> 0 | R48: =$B$21+$B$22*O48+$B$23*P48+$B$24*Q48 -> 5000.9619 | S48: =N48-R48 -> -60.961877 | T48: =S48/$B$7 -> -61.139168 | U48: =S48^2 -> 3716.3504 | V48: =(S48-S47)^2 -> 5176.5488
M49: =Data!B47 -> 45566 | N49: =Data!I47 -> 5360 | O49: =Data!N47 -> 1540 | P49: =Data!L47 -> 113.6 | Q49: =Data!G47 -> 0 | R49: =$B$21+$B$22*O49+$B$23*P49+$B$24*Q49 -> 5387.3479 | S49: =N49-R49 -> -27.347943 | T49: =S49/$B$7 -> -27.427478 | U49: =S49^2 -> 747.91001 | V49: =(S49-S48)^2 -> 1129.8965
M50: =Data!B48 -> 45597 | N50: =Data!I48 -> 5850 | O50: =Data!N48 -> 1840 | P50: =Data!L48 -> 113.9 | Q50: =Data!G48 -> 0 | R50: =$B$21+$B$22*O50+$B$23*P50+$B$24*Q50 -> 5888.4678 | S50: =N50-R50 -> -38.467808 | T50: =S50/$B$7 -> -38.579681 | U50: =S50^2 -> 1479.7722 | V50: =(S50-S49)^2 -> 123.65138
M51: =Data!B49 -> 45627 | N51: =Data!I49 -> 6340 | O51: =Data!N49 -> 2160 | P51: =Data!L49 -> 114.2 | Q51: =Data!G49 -> 1 | R51: =$B$21+$B$22*O51+$B$23*P51+$B$24*Q51 -> 6445.0688 | S51: =N51-R51 -> -105.06878 | T51: =S51/$B$7 -> -105.37434 | U51: =S51^2 -> 11039.448 | V51: =(S51-S50)^2 -> 4435.6892

Sheet SMA
A1: Unit 6 · Simple moving averages (3- and 6-month) and benchmark forecasts
A2: SMA forecast for month t = average of the k months before t. Flat 12-step forecasts use the last k months of 2023.
A4: Date | B4: ER visits | C4: SMA(3) | D4: SMA(6) | E4: SMA3 1-step forecast | F4: SMA6 1-step forecast | G4: SMA3 flat 12-step (2024) | H4: SMA6 flat 12-step (2024) | I4: Seasonal naïve (Y t−12)
A5: =Data!B2 -> 44197 | B5: =Data!I2 -> 4820
A6: =Data!B3 -> 44228 | B6: =Data!I3 -> 4510
A7: =Data!B4 -> 44256 | B7: =Data!I4 -> 4180 | C7: =AVERAGE(B5:B7) -> 4503.3333
A8: =Data!B5 -> 44287 | B8: =Data!I5 -> 3920 | C8: =AVERAGE(B6:B8) -> 4203.3333 | E8: =C7 -> 4503.3333
A9: =Data!B6 -> 44317 | B9: =Data!I6 -> 3710 | C9: =AVERAGE(B7:B9) -> 3936.6667 | E9: =C8 -> 4203.3333
A10: =Data!B7 -> 44348 | B10: =Data!I7 -> 3580 | C10: =AVERAGE(B8:B10) -> 3736.6667 | D10: =AVERAGE(B5:B10) -> 4120 | E10: =C9 -> 3936.6667
A11: =Data!B8 -> 44378 | B11: =Data!I8 -> 3620 | C11: =AVERAGE(B9:B11) -> 3636.6667 | D11: =AVERAGE(B6:B11) -> 3920 | E11: =C10 -> 3736.6667 | F11: =D10 -> 4120
A12: =Data!B9 -> 44409 | B12: =Data!I9 -> 3790 | C12: =AVERAGE(B10:B12) -> 3663.3333 | D12: =AVERAGE(B7:B12) -> 3800 | E12: =C11 -> 3636.6667 | F12: =D11 -> 3920
A13: =Data!B10 -> 44440 | B13: =Data!I10 -> 4120 | C13: =AVERAGE(B11:B13) -> 3843.3333 | D13: =AVERAGE(B8:B13) -> 3790 | E13: =C12 -> 3663.3333 | F13: =D12 -> 3800
A14: =Data!B11 -> 44470 | B14: =Data!I11 -> 4480 | C14: =AVERAGE(B12:B14) -> 4130 | D14: =AVERAGE(B9:B14) -> 3883.3333 | E14: =C13 -> 3843.3333 | F14: =D13 -> 3790
A15: =Data!B12 -> 44501 | B15: =Data!I12 -> 4910 | C15: =AVERAGE(B13:B15) -> 4503.3333 | D15: =AVERAGE(B10:B15) -> 4083.3333 | E15: =C14 -> 4130 | F15: =D14 -> 3883.3333
A16: =Data!B13 -> 44531 | B16: =Data!I13 -> 5340 | C16: =AVERAGE(B14:B16) -> 4910 | D16: =AVERAGE(B11:B16) -> 4376.6667 | E16: =C15 -> 4503.3333 | F16: =D15 -> 4083.3333
A17: =Data!B14 -> 44562 | B17: =Data!I14 -> 5620 | C17: =AVERAGE(B15:B17) -> 5290 | D17: =AVERAGE(B12:B17) -> 4710 | E17: =C16 -> 4910 | F17: =D16 -> 4376.6667 | I17: =B5 -> 4820
A18: =Data!B15 -> 44593 | B18: =Data!I15 -> 5180 | C18: =AVERAGE(B16:B18) -> 5380 | D18: =AVERAGE(B13:B18) -> 4941.6667 | E18: =C17 -> 5290 | F18: =D17 -> 4710 | I18: =B6 -> 4510
A19: =Data!B16 -> 44621 | B19: =Data!I16 -> 4610 | C19: =AVERAGE(B17:B19) -> 5136.6667 | D19: =AVERAGE(B14:B19) -> 5023.3333 | E19: =C18 -> 5380 | F19: =D18 -> 4941.6667 | I19: =B7 -> 4180
A20: =Data!B17 -> 44652 | B20: =Data!I17 -> 4230 | C20: =AVERAGE(B18:B20) -> 4673.3333 | D20: =AVERAGE(B15:B20) -> 4981.6667 | E20: =C19 -> 5136.6667 | F20: =D19 -> 5023.3333 | I20: =B8 -> 3920
A21: =Data!B18 -> 44682 | B21: =Data!I18 -> 4010 | C21: =AVERAGE(B19:B21) -> 4283.3333 | D21: =AVERAGE(B16:B21) -> 4831.6667 | E21: =C20 -> 4673.3333 | F21: =D20 -> 4981.6667 | I21: =B9 -> 3710
A22: =Data!B19 -> 44713 | B22: =Data!I19 -> 3860 | C22: =AVERAGE(B20:B22) -> 4033.3333 | D22: =AVERAGE(B17:B22) -> 4585 | E22: =C21 -> 4283.3333 | F22: =D21 -> 4831.6667 | I22: =B10 -> 3580
A23: =Data!B20 -> 44743 | B23: =Data!I20 -> 3910 | C23: =AVERAGE(B21:B23) -> 3926.6667 | D23: =AVERAGE(B18:B23) -> 4300 | E23: =C22 -> 4033.3333 | F23: =D22 -> 4585 | I23: =B11 -> 3620
A24: =Data!B21 -> 44774 | B24: =Data!I21 -> 4090 | C24: =AVERAGE(B22:B24) -> 3953.3333 | D24: =AVERAGE(B19:B24) -> 4118.3333 | E24: =C23 -> 3926.6667 | F24: =D23 -> 4300 | I24: =B12 -> 3790
A25: =Data!B22 -> 44805 | B25: =Data!I22 -> 4430 | C25: =AVERAGE(B23:B25) -> 4143.3333 | D25: =AVERAGE(B20:B25) -> 4088.3333 | E25: =C24 -> 3953.3333 | F25: =D24 -> 4118.3333 | I25: =B13 -> 4120
A26: =Data!B23 -> 44835 | B26: =Data!I23 -> 4820 | C26: =AVERAGE(B24:B26) -> 4446.6667 | D26: =AVERAGE(B21:B26) -> 4186.6667 | E26: =C25 -> 4143.3333 | F26: =D25 -> 4088.3333 | I26: =B14 -> 4480
A27: =Data!B24 -> 44866 | B27: =Data!I24 -> 5270 | C27: =AVERAGE(B25:B27) -> 4840 | D27: =AVERAGE(B22:B27) -> 4396.6667 | E27: =C26 -> 4446.6667 | F27: =D26 -> 4186.6667 | I27: =B15 -> 4910
A28: =Data!B25 -> 44896 | B28: =Data!I25 -> 5710 | C28: =AVERAGE(B26:B28) -> 5266.6667 | D28: =AVERAGE(B23:B28) -> 4705 | E28: =C27 -> 4840 | F28: =D27 -> 4396.6667 | I28: =B16 -> 5340
... A40: =Data!B37 -> 45261 | B40: =Data!I37 -> 6020 | C40: =AVERAGE(B38:B40) -> 5556.6667 | D40: =AVERAGE(B35:B40) -> 4971.6667 | E40: =C39 -> 5113.3333 | F40: =D39 -> 4648.3333 | I40: =B28 -> 5710
A41: =Data!B38 -> 45292 | B41: =Data!I38 -> 6310 | C41: =AVERAGE(B39:B41) -> 5963.3333 | D41: =AVERAGE(B36:B41) -> 5333.3333 | E41: =C40 -> 5556.6667 | F41: =D40 -> 4971.6667 | G41: =AVERAGE($B$38:$B$40) -> 5556.6667 | H41: =AVERAGE($B$35:$B$40) -> 4971.6667 | I41: =B29 -> 5980
A42: =Data!B39 -> 45323 | B42: =Data!I39 -> 5780 | C42: =AVERAGE(B40:B42) -> 6036.6667 | D42: =AVERAGE(B37:B42) -> 5575 | E42: =C41 -> 5963.3333 | F42: =D41 -> 5333.3333 | G42: =AVERAGE($B$38:$B$40) -> 5556.6667 | H42: =AVERAGE($B$35:$B$40) -> 4971.6667 | I42: =B30 -> 5490
A43: =Data!B40 -> 45352 | B43: =Data!I40 -> 5150 | C43: =AVERAGE(B41:B43) -> 5746.6667 | D43: =AVERAGE(B38:B43) -> 5651.6667 | E43: =C42 -> 6036.6667 | F43: =D42 -> 5575 | G43: =AVERAGE($B$38:$B$40) -> 5556.6667 | H43: =AVERAGE($B$35:$B$40) -> 4971.6667 | I43: =B31 -> 4890
A44: =Data!B41 -> 45383 | B44: =Data!I41 -> 4690 | C44: =AVERAGE(B42:B44) -> 5206.6667 | D44: =AVERAGE(B39:B44) -> 5585 | E44: =C43 -> 5746.6667 | F44: =D43 -> 5651.6667 | G44: =AVERAGE($B$38:$B$40) -> 5556.6667 | H44: =AVERAGE($B$35:$B$40) -> 4971.6667 | I44: =B32 -> 4460
A45: =Data!B42 -> 45413 | B45: =Data!I42 -> 4450 | C45: =AVERAGE(B43:B45) -> 4763.3333 | D45: =AVERAGE(B40:B45) -> 5400 | E45: =C44 -> 5206.6667 | F45: =D44 -> 5585 | G45: =AVERAGE($B$38:$B$40) -> 5556.6667 | H45: =AVERAGE($B$35:$B$40) -> 4971.6667 | I45: =B33 -> 4230
A46: =Data!B43 -> 45444 | B46: =Data!I43 -> 4290 | C46: =AVERAGE(B44:B46) -> 4476.6667 | D46: =AVERAGE(B41:B46) -> 5111.6667 | E46: =C45 -> 4763.3333 | F46: =D45 -> 5400 | G46: =AVERAGE($B$38:$B$40) -> 5556.6667 | H46: =AVERAGE($B$35:$B$40) -> 4971.6667 | I46: =B34 -> 4080
A47: =Data!B44 -> 45474 | B47: =Data!I44 -> 4360 | C47: =AVERAGE(B45:B47) -> 4366.6667 | D47: =AVERAGE(B42:B47) -> 4786.6667 | E47: =C46 -> 4476.6667 | F47: =D46 -> 5111.6667 | G47: =AVERAGE($B$38:$B$40) -> 5556.6667 | H47: =AVERAGE($B$35:$B$40) -> 4971.6667 | I47: =B35 -> 4140
A48: =Data!B45 -> 45505 | B48: =Data!I45 -> 4560 | C48: =AVERAGE(B46:B48) -> 4403.3333 | D48: =AVERAGE(B43:B48) -> 4583.3333 | E48: =C47 -> 4366.6667 | F48: =D47 -> 4786.6667 | G48: =AVERAGE($B$38:$B$40) -> 5556.6667 | H48: =AVERAGE($B$35:$B$40) -> 4971.6667 | I48: =B36 -> 4330
A49: =Data!B46 -> 45536 | B49: =Data!I46 -> 4940 | C49: =AVERAGE(B47:B49) -> 4620 | D49: =AVERAGE(B44:B49) -> 4548.3333 | E49: =C48 -> 4403.3333 | F49: =D48 -> 4583.3333 | G49: =AVERAGE($B$38:$B$40) -> 5556.6667 | H49: =AVERAGE($B$35:$B$40) -> 4971.6667 | I49: =B37 -> 4690
A50: =Data!B47 -> 45566 | B50: =Data!I47 -> 5360 | C50: =AVERAGE(B48:B50) -> 4953.3333 | D50: =AVERAGE(B45:B50) -> 4660 | E50: =C49 -> 4620 | F50: =D49 -> 4548.3333 | G50: =AVERAGE($B$38:$B$40) -> 5556.6667 | H50: =AVERAGE($B$35:$B$40) -> 4971.6667 | I50: =B38 -> 5090
A51: =Data!B48 -> 45597 | B51: =Data!I48 -> 5850 | C51: =AVERAGE(B49:B51) -> 5383.3333 | D51: =AVERAGE(B46:B51) -> 4893.3333 | E51: =C50 -> 4953.3333 | F51: =D50 -> 4660 | G51: =AVERAGE($B$38:$B$40) -> 5556.6667 | H51: =AVERAGE($B$35:$B$40) -> 4971.6667 | I51: =B39 -> 5560
A52: =Data!B49 -> 45627 | B52: =Data!I49 -> 6340 | C52: =AVERAGE(B50:B52) -> 5850 | D52: =AVERAGE(B47:B52) -> 5235 | E52: =C51 -> 5383.3333 | F52: =D51 -> 4893.3333 | G52: =AVERAGE($B$38:$B$40) -> 5556.6667 | H52: =AVERAGE($B$35:$B$40) -> 4971.6667 | I52: =B40 -> 6020

Sheet HW_Holdout
A1: Unit 6 · Holt-Winters multiplicative (level, trend, seasonality) — trained on 2021–2023, tested on 2024
A2: L_t = α·Y_t/S_{t−12} + (1−α)(L_{t−1}+T_{t−1}); T_t = β(L_t−L_{t−1}) + (1−β)T_{t−1}; S_t = γ·Y_t/L_t + (1−γ)S_{t−12}; Ŷ_{t+h} = (L_t + h·T_t)·S_{t+h−12}
A4: Parameters | D4: Fit statistics
A5: α (level) | B5: 0.99 | D5: SSE (in-sample, Solver target) | E5: =SUMXMY2(C26:C61,G26:G61) -> 145651.28
A6: β (trend) | B6: 0.01 | D6: In-sample MAPE | E6: =AVERAGE(I26:I61) -> 0.0057784191
A7: γ (seasonality) | B7: 0.440078 | D7: In-sample RMSE | E7: =SQRT(E5/COUNT(C26:C61)) -> 63.607145
A8: Initial level L0 | B8: 4088.0517 | D8: Hold-out (2024) MAPE | E8: =AVERAGE(I62:I73) -> 0.0079112427
A9: Initial trend T0 | B9: 28.003031 | D9: Hold-out (2024) RMSE | E9: =SQRT(SUMXMY2(C62:C73,G62:G73)/12) -> 43.38783
A13: t | B13: Date | C13: Actual Y | D13: Level L | E13: Trend T | F13: Season S | G13: Fitted / Forecast | H13: Error | I13: APE
A14: -11 | B14: Init Jan | F14: 1.249125
A15: -10 | B15: Init Feb | F15: 1.143584
A16: -9 | B16: Init Mar | F16: 1.013128
A17: -8 | B17: Init Apr | F17: 0.921973
A18: -7 | B18: Init May | F18: 0.869357
A19: -6 | B19: Init Jun | F19: 0.832792
A20: -5 | B20: Init Jul | F20: 0.841873
A21: -4 | B21: Init Aug | F21: 0.872169
A22: -3 | B22: Init Sep | F22: 0.938976
A23: -2 | B23: Init Oct | F23: 1.015478
A24: -1 | B24: Init Nov | F24: 1.106242
A25: 0 | B25: Init Dec | D25: =B8 -> 4088.0517 | E25: =B9 -> 28.003031 | F25: 1.195304
A26: 1 | B26: =Data!B2 -> 44197 | C26: =Data!I2 -> 4820 | D26: =$B$5*C26/F14+(1-$B$5)*(D25+E25) -> 3861.2746 | E26: =$B$6*(D26-D25)+(1-$B$6)*E25 -> 25.45523 | F26: =$B$7*C26/D26+(1-$B$7)*F14 -> 1.2487586 | G26: =(D25+E25)*F14 -> 5141.4668 | H26: =C26-G26 -> -321.46681 | I26: =ABS(H26)/C26 -> 0.066694358
A27: 2 | B27: =Data!B3 -> 44228 | C27: =Data!I3 -> 4510 | D27: =$B$5*C27/F15+(1-$B$5)*(D26+E26) -> 3943.1717 | E27: =$B$6*(D27-D26)+(1-$B$6)*E26 -> 26.019648 | F27: =$B$7*C27/D27+(1-$B$7)*F15 -> 1.1436568 | G27: =(D26+E26)*F15 -> 4444.8021 | H27: =C27-G27 -> 65.197923 | I27: =ABS(H27)/C27 -> 0.014456302
A28: 3 | B28: =Data!B4 -> 44256 | C28: =Data!I4 -> 4180 | D28: =$B$5*C28/F16+(1-$B$5)*(D27+E27) -> 4124.2696 | E28: =$B$6*(D28-D27)+(1-$B$6)*E27 -> 27.570431 | F28: =$B$7*C28/D28+(1-$B$7)*F16 -> 1.0132973 | G28: =(D27+E27)*F16 -> 4021.2989 | H28: =C28-G28 -> 158.70115 | I28: =ABS(H28)/C28 -> 0.037966782
A29: 4 | B29: =Data!B5 -> 44287 | C29: =Data!I5 -> 3920 | D29: =$B$5*C29/F17+(1-$B$5)*(D28+E28) -> 4250.7523 | E29: =$B$6*(D29-D28)+(1-$B$6)*E28 -> 28.559554 | F29: =$B$7*C29/D29+(1-$B$7)*F17 -> 0.92206837 | G29: =(D28+E28)*F17 -> 3827.8844 | H29: =C29-G29 -> 92.115612 | I29: =ABS(H29)/C29 -> 0.023498881
A30: 5 | B30: =Data!B6 -> 44317 | C30: =Data!I6 -> 3710 | D30: =$B$5*C30/F18+(1-$B$5)*(D29+E29) -> 4267.6398 | E30: =$B$6*(D30-D29)+(1-$B$6)*E29 -> 28.442833 | F30: =$B$7*C30/D30+(1-$B$7)*F18 -> 0.86934643 | G30: =(D29+E29)*F18 -> 3720.2497 | H30: =C30-G30 -> -10.249709 | I30: =ABS(H30)/C30 -> 0.0027627249
A31: 6 | B31: =Data!B7 -> 44348 | C31: =Data!I7 -> 3580 | D31: =$B$5*C31/F19+(1-$B$5)*(D30+E30) -> 4298.7654 | E31: =$B$6*(D31-D30)+(1-$B$6)*E30 -> 28.469661 | F31: =$B$7*C31/D31+(1-$B$7)*F19 -> 0.83279431 | G31: =(D30+E30)*F19 -> 3577.7432 | H31: =C31-G31 -> 2.2567868 | I31: =ABS(H31)/C31 -> 0.00063038737
A32: 7 | B32: =Data!B8 -> 44378 | C32: =Data!I8 -> 3620 | D32: =$B$5*C32/F20+(1-$B$5)*(D31+E31) -> 4300.209 | E32: =$B$6*(D32-D31)+(1-$B$6)*E31 -> 28.1994 | F32: =$B$7*C32/D32+(1-$B$7)*F20 -> 0.84184948 | G32: =(D31+E31)*F20 -> 3642.9824 | H32: =C32-G32 -> -22.98236 | I32: =ABS(H32)/C32 -> 0.0063487182
A33: 8 | B33: =Data!B9 -> 44409 | C33: =Data!I9 -> 3790 | D33: =$B$5*C33/F21+(1-$B$5)*(D32+E32) -> 4345.3173 | E33: =$B$6*(D33-D32)+(1-$B$6)*E32 -> 28.368489 | F33: =$B$7*C33/D33+(1-$B$7)*F21 -> 0.87218409 | G33: =(D32+E32)*F21 -> 3775.1036 | H33: =C33-G33 -> 14.896403 | I33: =ABS(H33)/C33 -> 0.0039304493
A34: 9 | B34: =Data!B10 -> 44440 | C34: =Data!I10 -> 4120 | D34: =$B$5*C34/F22+(1-$B$5)*(D33+E33) -> 4387.6179 | E34: =$B$6*(D34-D33)+(1-$B$6)*E33 -> 28.50781 | F34: =$B$7*C34/D34+(1-$B$7)*F22 -> 0.93898925 | G34: =(D33+E33)*F22 -> 4106.786 | H34: =C34-G34 -> 13.214021 | I34: =ABS(H34)/C34 -> 0.0032072867
A35: 10 | B35: =Data!B11 -> 44470 | C35: =Data!I11 -> 4480 | D35: =$B$5*C35/F23+(1-$B$5)*(D34+E34) -> 4411.7596 | E35: =$B$6*(D35-D34)+(1-$B$6)*E34 -> 28.464149 | F35: =$B$7*C35/D35+(1-$B$7)*F23 -> 1.0154735 | G35: =(D34+E34)*F23 -> 4484.4785 | H35: =C35-G35 -> -4.4784548 | I35: =ABS(H35)/C35 -> 0.00099965508
A36: 11 | B36: =Data!B12 -> 44501 | C36: =Data!I12 -> 4910 | D36: =$B$5*C36/F24+(1-$B$5)*(D35+E35) -> 4438.4679 | E36: =$B$6*(D36-D35)+(1-$B$6)*E35 -> 28.446591 | F36: =$B$7*C36/D36+(1-$B$7)*F24 -> 1.1062401 | G36: =(D35+E35)*F24 -> 4911.962 | H36: =C36-G36 -> -1.9619676 | I36: =ABS(H36)/C36 -> 0.00039958606
A37: 12 | B37: =Data!B13 -> 44531 | C37: =Data!I13 -> 5340 | D37: =$B$5*C37/F25+(1-$B$5)*(D36+E36) -> 4467.4771 | E37: =$B$6*(D37-D36)+(1-$B$6)*E36 -> 28.452217 | F37: =$B$7*C37/D37+(1-$B$7)*F25 -> 1.1953047 | G37: =(D36+E36)*F25 -> 5339.3208 | H37: =C37-G37 -> 0.67922691 | I37: =ABS(H37)/C37 -> 0.00012719605
... A61: 36 | B61: =Data!B37 -> 45261 | C61: =Data!I37 -> 6020 | D61: =$B$5*C61/F49+(1-$B$5)*(D60+E60) -> 5036.6172 | E61: =$B$6*(D61-D60)+(1-$B$6)*E60 -> 27.402207 | F61: =$B$7*C61/D61+(1-$B$7)*F49 -> 1.1952697 | G61: =(D60+E60)*F49 -> 6040.747 | H61: =C61-G61 -> -20.746996 | I61: =ABS(H61)/C61 -> 0.0034463448
A62: 37 | B62: =DATE(YEAR(B61),MONTH(B61)+1,1) -> 45292 | C62: =Data!I38 -> 6310 | G62: =($D$61+1*$E$61)*F50 -> 6323.6696 | H62: =C62-G62 -> -13.669637 | I62: =ABS(H62)/C62 -> 0.002166345
A63: 38 | B63: =DATE(YEAR(B61),MONTH(B61)+2,1) -> 45323 | C63: =Data!I39 -> 5780 | G63: =($D$61+2*$E$61)*F51 -> 5822.7531 | H63: =C63-G63 -> -42.753134 | I63: =ABS(H63)/C63 -> 0.007396736
A64: 39 | B64: =DATE(YEAR(B61),MONTH(B61)+3,1) -> 45352 | C64: =Data!I40 -> 5150 | G64: =($D$61+3*$E$61)*F52 -> 5186.837 | H64: =C64-G64 -> -36.83703 | I64: =ABS(H64)/C64 -> 0.0071528214
A65: 40 | B65: =DATE(YEAR(B61),MONTH(B61)+4,1) -> 45383 | C65: =Data!I41 -> 4690 | G65: =($D$61+4*$E$61)*F53 -> 4745.1431 | H65: =C65-G65 -> -55.143131 | I65: =ABS(H65)/C65 -> 0.011757597
A66: 41 | B66: =DATE(YEAR(B61),MONTH(B61)+5,1) -> 45413 | C66: =Data!I42 -> 4450 | G66: =($D$61+5*$E$61)*F54 -> 4497.6655 | H66: =C66-G66 -> -47.66549 | I66: =ABS(H66)/C66 -> 0.010711346
A67: 42 | B67: =DATE(YEAR(B61),MONTH(B61)+6,1) -> 45444 | C67: =Data!I43 -> 4290 | G67: =($D$61+6*$E$61)*F55 -> 4331.3859 | H67: =C67-G67 -> -41.38591 | I67: =ABS(H67)/C67 -> 0.0096470652
A68: 43 | B68: =DATE(YEAR(B61),MONTH(B61)+7,1) -> 45474 | C68: =Data!I44 -> 4360 | G68: =($D$61+7*$E$61)*F56 -> 4401.4389 | H68: =C68-G68 -> -41.438908 | I68: =ABS(H68)/C68 -> 0.0095043368
A69: 44 | B69: =DATE(YEAR(B61),MONTH(B61)+8,1) -> 45505 | C69: =Data!I45 -> 4560 | G69: =($D$61+8*$E$61)*F57 -> 4584.2032 | H69: =C69-G69 -> -24.203208 | I69: =ABS(H69)/C69 -> 0.005307721
A70: 45 | B70: =DATE(YEAR(B61),MONTH(B61)+9,1) -> 45536 | C70: =Data!I46 -> 4940 | G70: =($D$61+9*$E$61)*F58 -> 4960.9156 | H70: =C70-G70 -> -20.915572 | I70: =ABS(H70)/C70 -> 0.0042339214
A71: 46 | B71: =DATE(YEAR(B61),MONTH(B61)+10,1) -> 45566 | C71: =Data!I47 -> 5360 | G71: =($D$61+10*$E$61)*F59 -> 5392.7675 | H71: =C71-G71 -> -32.767541 | I71: =ABS(H71)/C71 -> 0.0061133473
A72: 47 | B72: =DATE(YEAR(B61),MONTH(B61)+11,1) -> 45597 | C72: =Data!I48 -> 5850 | G72: =($D$61+11*$E$61)*F60 -> 5905.0217 | H72: =C72-G72 -> -55.021725 | I72: =ABS(H72)/C72 -> 0.0094054231
A73: 48 | B73: =DATE(YEAR(B61),MONTH(B61)+12,1) -> 45627 | C73: =Data!I49 -> 6340 | G73: =($D$61+12*$E$61)*F61 -> 6413.1525 | H73: =C73-G73 -> -73.152514 | I73: =ABS(H73)/C73 -> 0.011538251

Sheet HW_Final_2025
A1: Unit 6 · Holt-Winters multiplicative (level, trend, seasonality) — all 48 months, forecasting 2025
A2: L_t = α·Y_t/S_{t−12} + (1−α)(L_{t−1}+T_{t−1}); T_t = β(L_t−L_{t−1}) + (1−β)T_{t−1}; S_t = γ·Y_t/L_t + (1−γ)S_{t−12}; Ŷ_{t+h} = (L_t + h·T_t)·S_{t+h−12}
A4: Parameters | D4: Fit statistics
A5: α (level) | B5: 0.99 | D5: SSE (in-sample, Solver target) | E5: =SUMXMY2(C26:C73,G26:G73) -> 177181.26
A6: β (trend) | B6: 0.01 | D6: In-sample MAPE | E6: =AVERAGE(I26:I73) -> 0.0048625399
A7: γ (seasonality) | B7: 0.187509 | D7: In-sample RMSE | E7: =SQRT(E5/COUNT(C26:C73)) -> 60.755874
A8: Initial level L0 | B8: =Decomposition!R34 -> 4123.89 | D8: 2025 total forecast | E8: =SUM(G74:G85) -> 65574.049
A9: Initial trend T0 | B9: =Decomposition!R35 -> 25.476711 | D9: Growth vs 2024 | E9: =E8/SUM(Data!I38:I49)-1 -> 0.05628301
A13: t | B13: Date | C13: Actual Y | D13: Level L | E13: Trend T | F13: Season S | G13: Fitted / Forecast | H13: Error | I13: APE
A14: -11 | B14: Init Jan | F14: =Decomposition!S6 -> 1.2492676
A15: -10 | B15: Init Feb | F15: =Decomposition!S7 -> 1.1425117
A16: -9 | B16: Init Mar | F16: =Decomposition!S8 -> 1.0127776
A17: -8 | B17: Init Apr | F17: =Decomposition!S9 -> 0.92057255
A18: -7 | B18: Init May | F18: =Decomposition!S10 -> 0.86852134
A19: -6 | B19: Init Jun | F19: =Decomposition!S11 -> 0.83238286
A20: -5 | B20: Init Jul | F20: =Decomposition!S12 -> 0.84139027
A21: -4 | B21: Init Aug | F21: =Decomposition!S13 -> 0.8729157
A22: -3 | B22: Init Sep | F22: =Decomposition!S14 -> 0.94023262
A23: -2 | B23: Init Oct | F23: =Decomposition!S15 -> 1.0166416
A24: -1 | B24: Init Nov | F24: =Decomposition!S16 -> 1.1071271
A25: 0 | B25: Init Dec | D25: =B8 -> 4123.89 | E25: =B9 -> 25.476711 | F25: =Decomposition!S17 -> 1.195659
A26: 1 | B26: =Data!B2 -> 44197 | C26: =Data!I2 -> 4820 | D26: =$B$5*C26/F14+(1-$B$5)*(D25+E25) -> 3861.1716 | E26: =$B$6*(D26-D25)+(1-$B$6)*E25 -> 22.594759 | F26: =$B$7*C26/D26+(1-$B$7)*F14 -> 1.249091 | G26: =(D25+E25)*F14 -> 5183.6696 | H26: =C26-G26 -> -363.66959 | I26: =ABS(H26)/C26 -> 0.075450123
A27: 2 | B27: =Data!B3 -> 44228 | C27: =Data!I3 -> 4510 | D27: =$B$5*C27/F15+(1-$B$5)*(D26+E26) -> 3946.8065 | E27: =$B$6*(D27-D26)+(1-$B$6)*E26 -> 23.22516 | F27: =$B$7*C27/D27+(1-$B$7)*F15 -> 1.1425462 | G27: =(D26+E26)*F15 -> 4437.2484 | H27: =C27-G27 -> 72.751609 | I27: =ABS(H27)/C27 -> 0.016131177
A28: 3 | B28: =Data!B4 -> 44256 | C28: =Data!I4 -> 4180 | D28: =$B$5*C28/F16+(1-$B$5)*(D27+E27) -> 4125.6912 | E28: =$B$6*(D28-D27)+(1-$B$6)*E27 -> 24.781756 | F28: =$B$7*C28/D28+(1-$B$7)*F16 -> 1.01285 | G28: =(D27+E27)*F16 -> 4020.759 | H28: =C28-G28 -> 159.24095 | I28: =ABS(H28)/C28 -> 0.038095922
A29: 4 | B29: =Data!B5 -> 44287 | C29: =Data!I5 -> 3920 | D29: =$B$5*C29/F17+(1-$B$5)*(D28+E28) -> 4257.1421 | E29: =$B$6*(D29-D28)+(1-$B$6)*E28 -> 25.848447 | F29: =$B$7*C29/D29+(1-$B$7)*F17 -> 0.92061624 | G29: =(D28+E28)*F17 -> 3820.8115 | H29: =C29-G29 -> 99.188527 | I29: =ABS(H29)/C29 -> 0.025303196
A30: 5 | B30: =Data!B6 -> 44317 | C30: =Data!I6 -> 3710 | D30: =$B$5*C30/F18+(1-$B$5)*(D29+E29) -> 4271.7416 | E30: =$B$6*(D30-D29)+(1-$B$6)*E29 -> 25.735958 | F30: =$B$7*C30/D30+(1-$B$7)*F18 -> 0.868517 | G30: =(D29+E29)*F18 -> 3719.8686 | H30: =C30-G30 -> -9.8686444 | I30: =ABS(H30)/C30 -> 0.002660012
A31: 6 | B31: =Data!B7 -> 44348 | C31: =Data!I7 -> 3580 | D31: =$B$5*C31/F19+(1-$B$5)*(D30+E30) -> 4300.8712 | E31: =$B$6*(D31-D30)+(1-$B$6)*E30 -> 25.769894 | F31: =$B$7*C31/D31+(1-$B$7)*F19 -> 0.8323841 | G31: =(D30+E30)*F19 -> 3577.1466 | H31: =C31-G31 -> 2.8533715 | I31: =ABS(H31)/C31 -> 0.00079703113
A32: 7 | B32: =Data!B8 -> 44378 | C32: =Data!I8 -> 3620 | D32: =$B$5*C32/F20+(1-$B$5)*(D31+E31) -> 4302.6453 | E32: =$B$6*(D32-D31)+(1-$B$6)*E31 -> 25.529937 | F32: =$B$7*C32/D32+(1-$B$7)*F20 -> 0.84138139 | G32: =(D31+E31)*F20 -> 3640.3937 | H32: =C32-G32 -> -20.393731 | I32: =ABS(H32)/C32 -> 0.0056336273
A33: 8 | B33: =Data!B9 -> 44409 | C33: =Data!I9 -> 3790 | D33: =$B$5*C33/F21+(1-$B$5)*(D32+E32) -> 4341.635 | E33: =$B$6*(D33-D32)+(1-$B$6)*E32 -> 25.664534 | F33: =$B$7*C33/D33+(1-$B$7)*F21 -> 0.87292082 | G33: =(D32+E32)*F21 -> 3778.1321 | H33: =C33-G33 -> 11.867874 | I33: =ABS(H33)/C33 -> 0.003131365
A34: 9 | B34: =Data!B10 -> 44440 | C34: =Data!I10 -> 4120 | D34: =$B$5*C34/F22+(1-$B$5)*(D33+E33) -> 4381.7484 | E34: =$B$6*(D34-D33)+(1-$B$6)*E33 -> 25.809023 | F34: =$B$7*C34/D34+(1-$B$7)*F22 -> 0.94023849 | G34: =(D33+E33)*F22 -> 4106.2775 | H34: =C34-G34 -> 13.722542 | I34: =ABS(H34)/C34 -> 0.0033307141
A35: 10 | B35: =Data!B11 -> 44470 | C35: =Data!I11 -> 4480 | D35: =$B$5*C35/F23+(1-$B$5)*(D34+E34) -> 4406.6748 | E35: =$B$6*(D35-D34)+(1-$B$6)*E34 -> 25.800196 | F35: =$B$7*C35/D35+(1-$B$7)*F23 -> 1.0166413 | G35: =(D34+E34)*F23 -> 4480.9064 | H35: =C35-G35 -> -0.90640492 | I35: =ABS(H35)/C35 -> 0.00020232253
A36: 11 | B36: =Data!B12 -> 44501 | C36: =Data!I12 -> 4910 | D36: =$B$5*C36/F24+(1-$B$5)*(D35+E35) -> 4434.8774 | E36: =$B$6*(D36-D35)+(1-$B$6)*E35 -> 25.824221 | F36: =$B$7*C36/D36+(1-$B$7)*F24 -> 1.1071283 | G36: =(D35+E35)*F24 -> 4907.3133 | H36: =C36-G36 -> 2.6866626 | I36: =ABS(H36)/C36 -> 0.00054718179
A37: 12 | B37: =Data!B13 -> 44531 | C37: =Data!I13 -> 5340 | D37: =$B$5*C37/F25+(1-$B$5)*(D36+E36) -> 4466.1018 | E37: =$B$6*(D37-D36)+(1-$B$6)*E36 -> 25.878223 | F37: =$B$7*C37/D37+(1-$B$7)*F25 -> 1.1956617 | G37: =(D36+E36)*F25 -> 5333.478 | H37: =C37-G37 -> 6.5220283 | I37: =ABS(H37)/C37 -> 0.0012213536
... A73: 48 | B73: =Data!B49 -> 45627 | C73: =Data!I49 -> 6340 | D73: =$B$5*C73/F61+(1-$B$5)*(D72+E72) -> 5302.6167 | E73: =$B$6*(D73-D72)+(1-$B$6)*E72 -> 25.03203 | F73: =$B$7*C73/D73+(1-$B$7)*F61 -> 1.1956483 | G73: =(D72+E72)*F61 -> 6347.9623 | H73: =C73-G73 -> -7.9623312 | I73: =ABS(H73)/C73 -> 0.0012558882
A74: 49 | B74: =DATE(YEAR(B73),MONTH(B73)+1,1) -> 45658 | G74: =($D$73+1*$E$73)*F62 -> 6654.6802
A75: 50 | B75: =DATE(YEAR(B73),MONTH(B73)+2,1) -> 45689 | G75: =($D$73+2*$E$73)*F63 -> 6115.646
A76: 51 | B76: =DATE(YEAR(B73),MONTH(B73)+3,1) -> 45717 | G76: =($D$73+3*$E$73)*F64 -> 5446.793
A77: 52 | B77: =DATE(YEAR(B73),MONTH(B73)+4,1) -> 45748 | G77: =($D$73+4*$E$73)*F65 -> 4973.8439
A78: 53 | B78: =DATE(YEAR(B73),MONTH(B73)+5,1) -> 45778 | G78: =($D$73+5*$E$73)*F66 -> 4714.1171
A79: 54 | B79: =DATE(YEAR(B73),MONTH(B73)+6,1) -> 45809 | G79: =($D$73+6*$E$73)*F67 -> 4538.8391
A80: 55 | B80: =DATE(YEAR(B73),MONTH(B73)+7,1) -> 45839 | G80: =($D$73+7*$E$73)*F68 -> 4608.9168
A81: 56 | B81: =DATE(YEAR(B73),MONTH(B73)+8,1) -> 45870 | G81: =($D$73+8*$E$73)*F69 -> 4803.6507
A82: 57 | B82: =DATE(YEAR(B73),MONTH(B73)+9,1) -> 45901 | G82: =($D$73+9*$E$73)*F70 -> 5197.5635
A83: 58 | B83: =DATE(YEAR(B73),MONTH(B73)+10,1) -> 45931 | G83: =($D$73+10*$E$73)*F71 -> 5645.3238
A84: 59 | B84: =DATE(YEAR(B73),MONTH(B73)+11,1) -> 45962 | G84: =($D$73+11*$E$73)*F72 -> 6175.4565
A85: 60 | B85: =DATE(YEAR(B73),MONTH(B73)+12,1) -> 45992 | G85: =($D$73+12*$E$73)*F73 -> 6699.2187

Sheet Model_Comparison
A1: Unit 6 · Out-of-sample accuracy on the 2024 hold-out (12 months)
A2: MAPE = mean(|A−F|/A); RMSE = √mean((A−F)²); bias = mean(F−A). Lower is better.
A4: Model | B4: MAPE | C4: RMSE | D4: MAE | E4: Bias (mean error) | F4: Rank (MAPE)
A5: Holt-Winters multiplicative (selected) | B5: =SUMPRODUCT(ABS((SMA!$B$41:$B$52-HW_Holdout!$G$62:$G$73)/SMA!$B$41:$B$52))/12 -> 0.0079112427 | C5: =SQRT(SUMXMY2(SMA!$B$41:$B$52,HW_Holdout!$G$62:$G$73)/12) -> 43.38783 | D5: =SUMPRODUCT(ABS(SMA!$B$41:$B$52-HW_Holdout!$G$62:$G$73))/12 -> 40.412817 | E5: =(SUM(HW_Holdout!$G$62:$G$73)-SUM(SMA!$B$41:$B$52))/12 -> 40.412817 | F5: =RANK(B5,$B$5:$B$10,1) -> 1
A6: Seasonal naïve (same month last year) | B6: =SUMPRODUCT(ABS((SMA!$B$41:$B$52-SMA!$I$41:$I$52)/SMA!$B$41:$B$52))/12 -> 0.050192477 | C6: =SQRT(SUMXMY2(SMA!$B$41:$B$52,SMA!$I$41:$I$52)/12) -> 262.86879 | D6: =SUMPRODUCT(ABS(SMA!$B$41:$B$52-SMA!$I$41:$I$52))/12 -> 260 | E6: =(SUM(SMA!$I$41:$I$52)-SUM(SMA!$B$41:$B$52))/12 -> -260 | F6: =RANK(B6,$B$5:$B$10,1) -> 2
A7: SMA(3) rolling 1-step-ahead | B7: =SUMPRODUCT(ABS((SMA!$B$41:$B$52-SMA!$E$41:$E$52)/SMA!$B$41:$B$52))/12 -> 0.12074755 | C7: =SQRT(SUMXMY2(SMA!$B$41:$B$52,SMA!$E$41:$E$52)/12) -> 701.56109 | D7: =SUMPRODUCT(ABS(SMA!$B$41:$B$52-SMA!$E$41:$E$52))/12 -> 629.16667 | E7: =(SUM(SMA!$E$41:$E$52)-SUM(SMA!$B$41:$B$52))/12 -> -50.277778 | F7: =RANK(B7,$B$5:$B$10,1) -> 4
A8: SMA(6) rolling 1-step-ahead | B8: =SUMPRODUCT(ABS((SMA!$B$41:$B$52-SMA!$F$41:$F$52)/SMA!$B$41:$B$52))/12 -> 0.16400675 | C8: =SQRT(SUMXMY2(SMA!$B$41:$B$52,SMA!$F$41:$F$52)/12) -> 936.64912 | D8: =SUMPRODUCT(ABS(SMA!$B$41:$B$52-SMA!$F$41:$F$52))/12 -> 850 | E8: =(SUM(SMA!$F$41:$F$52)-SUM(SMA!$B$41:$B$52))/12 -> -81.666667 | F8: =RANK(B8,$B$5:$B$10,1) -> 6
A9: SMA(3) flat 12-step | B9: =SUMPRODUCT(ABS((SMA!$B$41:$B$52-SMA!$G$41:$G$52)/SMA!$B$41:$B$52))/12 -> 0.14949849 | C9: =SQRT(SUMXMY2(SMA!$B$41:$B$52,SMA!$G$41:$G$52)/12) -> 811.73682 | D9: =SUMPRODUCT(ABS(SMA!$B$41:$B$52-SMA!$G$41:$G$52))/12 -> 725.55556 | E9: =(SUM(SMA!$G$41:$G$52)-SUM(SMA!$B$41:$B$52))/12 -> 383.33333 | F9: =RANK(B9,$B$5:$B$10,1) -> 5
A10: SMA(6) flat 12-step | B10: =SUMPRODUCT(ABS((SMA!$B$41:$B$52-SMA!$H$41:$H$52)/SMA!$B$41:$B$52))/12 -> 0.11651281 | C10: =SQRT(SUMXMY2(SMA!$B$41:$B$52,SMA!$H$41:$H$52)/12) -> 743.39873 | D10: =SUMPRODUCT(ABS(SMA!$B$41:$B$52-SMA!$H$41:$H$52))/12 -> 625 | E10: =(SUM(SMA!$H$41:$H$52)-SUM(SMA!$B$41:$B$52))/12 -> -201.66667 | F10: =RANK(B10,$B$5:$B$10,1) -> 3
A12: Additional (notebook, statsmodels): HW additive MAPE | B12: 0.052371352
A13: Additional (notebook, statsmodels): HW multiplicative MAPE | B13: 0.0095096401
A15: Month 2024 | B15: Actual | C15: Holt-Winters | D15: Seasonal naïve | E15: SMA(3) 1-step | F15: SMA(6) 1-step
A16: =SMA!A41 -> 45292 | B16: =SMA!B41 -> 6310 | C16: =HW_Holdout!G62 -> 6323.6696 | D16: =SMA!I41 -> 5980 | E16: =SMA!E41 -> 5556.6667 | F16: =SMA!F41 -> 4971.6667
A17: =SMA!A42 -> 45323 | B17: =SMA!B42 -> 5780 | C17: =HW_Holdout!G63 -> 5822.7531 | D17: =SMA!I42 -> 5490 | E17: =SMA!E42 -> 5963.3333 | F17: =SMA!F42 -> 5333.3333
A18: =SMA!A43 -> 45352 | B18: =SMA!B43 -> 5150 | C18: =HW_Holdout!G64 -> 5186.837 | D18: =SMA!I43 -> 4890 | E18: =SMA!E43 -> 6036.6667 | F18: =SMA!F43 -> 5575
A19: =SMA!A44 -> 45383 | B19: =SMA!B44 -> 4690 | C19: =HW_Holdout!G65 -> 4745.1431 | D19: =SMA!I44 -> 4460 | E19: =SMA!E44 -> 5746.6667 | F19: =SMA!F44 -> 5651.6667
A20: =SMA!A45 -> 45413 | B20: =SMA!B45 -> 4450 | C20: =HW_Holdout!G66 -> 4497.6655 | D20: =SMA!I45 -> 4230 | E20: =SMA!E45 -> 5206.6667 | F20: =SMA!F45 -> 5585
A21: =SMA!A46 -> 45444 | B21: =SMA!B46 -> 4290 | C21: =HW_Holdout!G67 -> 4331.3859 | D21: =SMA!I46 -> 4080 | E21: =SMA!E46 -> 4763.3333 | F21: =SMA!F46 -> 5400
A22: =SMA!A47 -> 45474 | B22: =SMA!B47 -> 4360 | C22: =HW_Holdout!G68 -> 4401.4389 | D22: =SMA!I47 -> 4140 | E22: =SMA!E47 -> 4476.6667 | F22: =SMA!F47 -> 5111.6667
A23: =SMA!A48 -> 45505 | B23: =SMA!B48 -> 4560 | C23: =HW_Holdout!G69 -> 4584.2032 | D23: =SMA!I48 -> 4330 | E23: =SMA!E48 -> 4366.6667 | F23: =SMA!F48 -> 4786.6667
A24: =SMA!A49 -> 45536 | B24: =SMA!B49 -> 4940 | C24: =HW_Holdout!G70 -> 4960.9156 | D24: =SMA!I49 -> 4690 | E24: =SMA!E49 -> 4403.3333 | F24: =SMA!F49 -> 4583.3333
A25: =SMA!A50 -> 45566 | B25: =SMA!B50 -> 5360 | C25: =HW_Holdout!G71 -> 5392.7675 | D25: =SMA!I50 -> 5090 | E25: =SMA!E50 -> 4620 | F25: =SMA!F50 -> 4548.3333
A26: =SMA!A51 -> 45597 | B26: =SMA!B51 -> 5850 | C26: =HW_Holdout!G72 -> 5905.0217 | D26: =SMA!I51 -> 5560 | E26: =SMA!E51 -> 4953.3333 | F26: =SMA!F51 -> 4660
A27: =SMA!A52 -> 45627 | B27: =SMA!B52 -> 6340 | C27: =HW_Holdout!G73 -> 6413.1525 | D27: =SMA!I52 -> 6020 | E27: =SMA!E52 -> 5383.3333 | F27: =SMA!F52 -> 4893.3333

Sheet Forecast_2025
A1: Section 4 · 2025 forecast translated into staffing, ICU bed capacity and budget
A2: Yellow = assumptions (editable). Relative error SD per horizon comes from rolling-origin cross-validation in the notebook.
A4: Assumptions
A5: ICU safe-occupancy target | B5: 0.85
A6: Severe-season flu shock | B6: 0.15
A7: Flu coefficient (MLR_Refined) | B7: =MLR_Refined!$B$22 -> 1.6390543
A8: Expenditure model intercept $ | B8: =INTERCEPT(Data!$K$2:$K$49,Data!$I$2:$I$49) -> 300480.61
A9: Marginal cost per ER visit $ | B9: =SLOPE(Data!$K$2:$K$49,Data!$I$2:$I$49) -> 199.93384
A10: 2024 average monthly ER visits | B10: =AVERAGE(Data!I38:I49) -> 5173.3333
A12: Month | B12: Days | C12: ER forecast | D12: Rel. error SD | E12: Lo 95% | F12: Lo 80% | G12: Hi 80% | H12: Hi 95% | I12: Same month 2024 | J12: YoY % | K12: Daily visits | L12: Daily visits (P90) | M12: Staffing index (vs 2024 avg) | N12: ICU forecast % | O12: Extra ICU beds to hold target | P12: Expenditure forecast $ | Q12: Above flat budget $ | R12: Flu forecast | S12: Severe: extra ER visits | T12: Severe: ER visits | U12: Severe: ICU % | V12: Severe: extra cost $
A13: =HW_Final_2025!B74 -> 45658 | B13: =DAY(DATE(YEAR(A13),MONTH(A13)+1,0)) -> 31 | C13: =HW_Final_2025!G74 -> 6654.6802 | D13: 0.00323 | E13: =C13*(1-_xlfn.NORM.S.INV(0.975)*D13) -> 6612.5516 | F13: =C13*(1-_xlfn.NORM.S.INV(0.9)*D13) -> 6627.1338 | G13: =C13*(1+_xlfn.NORM.S.INV(0.9)*D13) -> 6682.2267 | H13: =C13*(1+_xlfn.NORM.S.INV(0.975)*D13) -> 6696.8089 | I13: =Data!I38 -> 6310 | J13: =C13/I13-1 -> 0.054624443 | K13: =C13/B13 -> 214.6671 | L13: =G13/B13 -> 215.5557 | M13: =C13/$B$10 -> 1.2863428 | N13: 101.42 | O13: =MAX(0,N13/100/$B$5-1) -> 0.19317647 | P13: =$B$8+$B$9*C13 -> 1630976.4 | Q13: =MAX(0,P13-AVERAGE($P$13:$P$24)) -> 237956.48 | R13: 2333.3 | S13: =$B$7*$B$6*R13 -> 573.66079 | T13: =C13+S13 -> 7228.341 | U13: =N13*T13/C13 -> 110.16282 | V13: =$B$9*S13 -> 114694.2
A14: =HW_Final_2025!B75 -> 45689 | B14: =DAY(DATE(YEAR(A14),MONTH(A14)+1,0)) -> 28 | C14: =HW_Final_2025!G75 -> 6115.646 | D14: 0.00512 | E14: =C14*(1-_xlfn.NORM.S.INV(0.975)*D14) -> 6054.2754 | F14: =C14*(1-_xlfn.NORM.S.INV(0.9)*D14) -> 6075.5179 | G14: =C14*(1+_xlfn.NORM.S.INV(0.9)*D14) -> 6155.7741 | H14: =C14*(1+_xlfn.NORM.S.INV(0.975)*D14) -> 6177.0166 | I14: =Data!I39 -> 5780 | J14: =C14/I14-1 -> 0.058070243 | K14: =C14/B14 -> 218.41593 | L14: =G14/B14 -> 219.84907 | M14: =C14/$B$10 -> 1.1821481 | N14: 93.96 | O14: =MAX(0,N14/100/$B$5-1) -> 0.10541176 | P14: =$B$8+$B$9*C14 -> 1523205.2 | Q14: =MAX(0,P14-AVERAGE($P$13:$P$24)) -> 130185.3 | R14: 1996.1 | S14: =$B$7*$B$6*R14 -> 490.75743 | T14: =C14+S14 -> 6606.4034 | U14: =N14*T14/C14 -> 101.49993 | V14: =$B$9*S14 -> 98119.016
A15: =HW_Final_2025!B76 -> 45717 | B15: =DAY(DATE(YEAR(A15),MONTH(A15)+1,0)) -> 31 | C15: =HW_Final_2025!G76 -> 5446.793 | D15: 0.00673 | E15: =C15*(1-_xlfn.NORM.S.INV(0.975)*D15) -> 5374.9468 | F15: =C15*(1-_xlfn.NORM.S.INV(0.9)*D15) -> 5399.8153 | G15: =C15*(1+_xlfn.NORM.S.INV(0.9)*D15) -> 5493.7707 | H15: =C15*(1+_xlfn.NORM.S.INV(0.975)*D15) -> 5518.6392 | I15: =Data!I40 -> 5150 | J15: =C15/I15-1 -> 0.05762971 | K15: =C15/B15 -> 175.703 | L15: =G15/B15 -> 177.21841 | M15: =C15/$B$10 -> 1.0528595 | N15: 85.21 | O15: =MAX(0,N15/100/$B$5-1) -> 0.0024705882 | P15: =$B$8+$B$9*C15 -> 1389478.8 | Q15: =MAX(0,P15-AVERAGE($P$13:$P$24)) -> 0 | R15: 1505.8 | S15: =$B$7*$B$6*R15 -> 370.21318 | T15: =C15+S15 -> 5817.0062 | U15: =N15*T15/C15 -> 91.00164 | V15: =$B$9*S15 -> 74018.142
A16: =HW_Final_2025!B77 -> 45748 | B16: =DAY(DATE(YEAR(A16),MONTH(A16)+1,0)) -> 30 | C16: =HW_Final_2025!G77 -> 4973.8439 | D16: 0.00836 | E16: =C16*(1-_xlfn.NORM.S.INV(0.975)*D16) -> 4892.3459 | F16: =C16*(1-_xlfn.NORM.S.INV(0.9)*D16) -> 4920.5552 | G16: =C16*(1+_xlfn.NORM.S.INV(0.9)*D16) -> 5027.1325 | H16: =C16*(1+_xlfn.NORM.S.INV(0.975)*D16) -> 5055.3418 | I16: =Data!I41 -> 4690 | J16: =C16/I16-1 -> 0.060521079 | K16: =C16/B16 -> 165.7948 | L16: =G16/B16 -> 167.57108 | M16: =C16/$B$10 -> 0.96143889 | N16: 78.23 | O16: =MAX(0,N16/100/$B$5-1) -> 0 | P16: =$B$8+$B$9*C16 -> 1294920.3 | Q16: =MAX(0,P16-AVERAGE($P$13:$P$24)) -> 0 | R16: 1197.9 | S16: =$B$7*$B$6*R16 -> 294.51346 | T16: =C16+S16 -> 5268.3573 | U16: =N16*T16/C16 -> 82.86219 | V16: =$B$9*S16 -> 58883.207
A17: =HW_Final_2025!B78 -> 45778 | B17: =DAY(DATE(YEAR(A17),MONTH(A17)+1,0)) -> 31 | C17: =HW_Final_2025!G78 -> 4714.1171 | D17: 0.00909 | E17: =C17*(1-_xlfn.NORM.S.INV(0.975)*D17) -> 4630.1301 | F17: =C17*(1-_xlfn.NORM.S.INV(0.9)*D17) -> 4659.2009 | G17: =C17*(1+_xlfn.NORM.S.INV(0.9)*D17) -> 4769.0333 | H17: =C17*(1+_xlfn.NORM.S.INV(0.975)*D17) -> 4798.1042 | I17: =Data!I42 -> 4450 | J17: =C17/I17-1 -> 0.059352163 | K17: =C17/B17 -> 152.06829 | L17: =G17/B17 -> 153.83978 | M17: =C17/$B$10 -> 0.91123398 | N17: 74.08 | O17: =MAX(0,N17/100/$B$5-1) -> 0 | P17: =$B$8+$B$9*C17 -> 1242992.1 | Q17: =MAX(0,P17-AVERAGE($P$13:$P$24)) -> 0 | R17: 1054.3 | S17: =$B$7*$B$6*R17 -> 259.20823 | T17: =C17+S17 -> 4973.3254 | U17: =N17*T17/C17 -> 78.153328 | V17: =$B$9*S17 -> 51824.497
A18: =HW_Final_2025!B79 -> 45809 | B18: =DAY(DATE(YEAR(A18),MONTH(A18)+1,0)) -> 30 | C18: =HW_Final_2025!G79 -> 4538.8391 | D18: 0.00983 | E18: =C18*(1-_xlfn.NORM.S.INV(0.975)*D18) -> 4451.3918 | F18: =C18*(1-_xlfn.NORM.S.INV(0.9)*D18) -> 4481.6604 | G18: =C18*(1+_xlfn.NORM.S.INV(0.9)*D18) -> 4596.0178 | H18: =C18*(1+_xlfn.NORM.S.INV(0.975)*D18) -> 4626.2864 | I18: =Data!I43 -> 4290 | J18: =C18/I18-1 -> 0.058004456 | K18: =C18/B18 -> 151.29464 | L18: =G18/B18 -> 153.20059 | M18: =C18/$B$10 -> 0.87735292 | N18: 71.03 | O18: =MAX(0,N18/100/$B$5-1) -> 0 | P18: =$B$8+$B$9*C18 -> 1207948.1 | Q18: =MAX(0,P18-AVERAGE($P$13:$P$24)) -> 0 | R18: 980.2 | S18: =$B$7*$B$6*R18 -> 240.99015 | T18: =C18+S18 -> 4779.8293 | U18: =N18*T18/C18 -> 74.801345 | V18: =$B$9*S18 -> 48182.085
A19: =HW_Final_2025!B80 -> 45839 | B19: =DAY(DATE(YEAR(A19),MONTH(A19)+1,0)) -> 31 | C19: =HW_Final_2025!G80 -> 4608.9168 | D19: 0.01195 | E19: =C19*(1-_xlfn.NORM.S.INV(0.975)*D19) -> 4500.9687 | F19: =C19*(1-_xlfn.NORM.S.INV(0.9)*D19) -> 4538.3333 | G19: =C19*(1+_xlfn.NORM.S.INV(0.9)*D19) -> 4679.5002 | H19: =C19*(1+_xlfn.NORM.S.INV(0.975)*D19) -> 4716.8648 | I19: =Data!I44 -> 4360 | J19: =C19/I19-1 -> 0.057091003 | K19: =C19/B19 -> 148.67473 | L19: =G19/B19 -> 150.95162 | M19: =C19/$B$10 -> 0.89089886 | N19: 72.02 | O19: =MAX(0,N19/100/$B$5-1) -> 0 | P19: =$B$8+$B$9*C19 -> 1221959 | Q19: =MAX(0,P19-AVERAGE($P$13:$P$24)) -> 0 | R19: 1028.3 | S19: =$B$7*$B$6*R19 -> 252.81592 | T19: =C19+S19 -> 4861.7327 | U19: =N19*T19/C19 -> 75.97056 | V19: =$B$9*S19 -> 50546.457
A20: =HW_Final_2025!B81 -> 45870 | B20: =DAY(DATE(YEAR(A20),MONTH(A20)+1,0)) -> 31 | C20: =HW_Final_2025!G81 -> 4803.6507 | D20: 0.01223 | E20: =C20*(1-_xlfn.NORM.S.INV(0.975)*D20) -> 4688.5054 | F20: =C20*(1-_xlfn.NORM.S.INV(0.9)*D20) -> 4728.3612 | G20: =C20*(1+_xlfn.NORM.S.INV(0.9)*D20) -> 4878.9401 | H20: =C20*(1+_xlfn.NORM.S.INV(0.975)*D20) -> 4918.7959 | I20: =Data!I45 -> 4560 | J20: =C20/I20-1 -> 0.053432163 | K20: =C20/B20 -> 154.95647 | L20: =G20/B20 -> 157.38516 | M20: =C20/$B$10 -> 0.92854072 | N20: 75.94 | O20: =MAX(0,N20/100/$B$5-1) -> 0 | P20: =$B$8+$B$9*C20 -> 1260892.9 | Q20: =MAX(0,P20-AVERAGE($P$13:$P$24)) -> 0 | R20: 1132.9 | S20: =$B$7*$B$6*R20 -> 278.53268 | T20: =C20+S20 -> 5082.1833 | U20: =N20*T20/C20 -> 80.34327 | V20: =$B$9*S20 -> 55688.108
A21: =HW_Final_2025!B82 -> 45901 | B21: =DAY(DATE(YEAR(A21),MONTH(A21)+1,0)) -> 30 | C21: =HW_Final_2025!G82 -> 5197.5635 | D21: 0.01318 | E21: =C21*(1-_xlfn.NORM.S.INV(0.975)*D21) -> 5063.2983 | F21: =C21*(1-_xlfn.NORM.S.INV(0.9)*D21) -> 5109.7722 | G21: =C21*(1+_xlfn.NORM.S.INV(0.9)*D21) -> 5285.3547 | H21: =C21*(1+_xlfn.NORM.S.INV(0.975)*D21) -> 5331.8286 | I21: =Data!I46 -> 4940 | J21: =C21/I21-1 -> 0.052138356 | K21: =C21/B21 -> 173.25212 | L21: =G21/B21 -> 176.17849 | M21: =C21/$B$10 -> 1.0046837 | N21: 81.39 | O21: =MAX(0,N21/100/$B$5-1) -> 0 | P21: =$B$8+$B$9*C21 -> 1339649.4 | Q21: =MAX(0,P21-AVERAGE($P$13:$P$24)) -> 0 | R21: 1418.6 | S21: =$B$7*$B$6*R21 -> 348.77435 | T21: =C21+S21 -> 5546.3378 | U21: =N21*T21/C21 -> 86.851548 | V21: =$B$9*S21 -> 69731.795
A22: =HW_Final_2025!B83 -> 45931 | B22: =DAY(DATE(YEAR(A22),MONTH(A22)+1,0)) -> 31 | C22: =HW_Final_2025!G83 -> 5645.3238 | D22: 0.01476 | E22: =C22*(1-_xlfn.NORM.S.INV(0.975)*D22) -> 5482.0098 | F22: =C22*(1-_xlfn.NORM.S.INV(0.9)*D22) -> 5538.5385 | G22: =C22*(1+_xlfn.NORM.S.INV(0.9)*D22) -> 5752.1091 | H22: =C22*(1+_xlfn.NORM.S.INV(0.975)*D22) -> 5808.6378 | I22: =Data!I47 -> 5360 | J22: =C22/I22-1 -> 0.053232051 | K22: =C22/B22 -> 182.10722 | L22: =G22/B22 -> 185.5519 | M22: =C22/$B$10 -> 1.0912353 | N22: 87.14 | O22: =MAX(0,N22/100/$B$5-1) -> 0.025176471 | P22: =$B$8+$B$9*C22 -> 1429171.9 | Q22: =MAX(0,P22-AVERAGE($P$13:$P$24)) -> 36151.974 | R22: 1657.7 | S22: =$B$7*$B$6*R22 -> 407.55903 | T22: =C22+S22 -> 6052.8828 | U22: =N22*T22/C22 -> 93.430993 | V22: =$B$9*S22 -> 81484.841
A23: =HW_Final_2025!B84 -> 45962 | B23: =DAY(DATE(YEAR(A23),MONTH(A23)+1,0)) -> 30 | C23: =HW_Final_2025!G84 -> 6175.4565 | D23: 0.01689 | E23: =C23*(1-_xlfn.NORM.S.INV(0.975)*D23) -> 5971.0255 | F23: =C23*(1-_xlfn.NORM.S.INV(0.9)*D23) -> 6041.7862 | G23: =C23*(1+_xlfn.NORM.S.INV(0.9)*D23) -> 6309.1268 | H23: =C23*(1+_xlfn.NORM.S.INV(0.975)*D23) -> 6379.8875 | I23: =Data!I48 -> 5850 | J23: =C23/I23-1 -> 0.055633588 | K23: =C23/B23 -> 205.84855 | L23: =G23/B23 -> 210.30423 | M23: =C23/$B$10 -> 1.1937094 | N23: 94.67 | O23: =MAX(0,N23/100/$B$5-1) -> 0.11376471 | P23: =$B$8+$B$9*C23 -> 1535163.3 | Q23: =MAX(0,P23-AVERAGE($P$13:$P$24)) -> 142143.44 | R23: 1984.8 | S23: =$B$7*$B$6*R23 -> 487.97923 | T23: =C23+S23 -> 6663.4357 | U23: =N23*T23/C23 -> 102.15074 | V23: =$B$9*S23 -> 97563.56
A24: =HW_Final_2025!B85 -> 45992 | B24: =DAY(DATE(YEAR(A24),MONTH(A24)+1,0)) -> 31 | C24: =HW_Final_2025!G85 -> 6699.2187 | D24: 0.01897 | E24: =C24*(1-_xlfn.NORM.S.INV(0.975)*D24) -> 6450.1383 | F24: =C24*(1-_xlfn.NORM.S.INV(0.9)*D24) -> 6536.3538 | G24: =C24*(1+_xlfn.NORM.S.INV(0.9)*D24) -> 6862.0837 | H24: =C24*(1+_xlfn.NORM.S.INV(0.975)*D24) -> 6948.2992 | I24: =Data!I49 -> 6340 | J24: =C24/I24-1 -> 0.056659108 | K24: =C24/B24 -> 216.10383 | L24: =G24/B24 -> 221.35754 | M24: =C24/$B$10 -> 1.2949521 | N24: 102.27 | O24: =MAX(0,N24/100/$B$5-1) -> 0.20317647 | P24: =$B$8+$B$9*C24 -> 1639881.1 | Q24: =MAX(0,P24-AVERAGE($P$13:$P$24)) -> 246861.24 | R24: 2336 | S24: =$B$7*$B$6*R24 -> 574.32461 | T24: =C24+S24 -> 7273.5434 | U24: =N24*T24/C24 -> 111.03762 | V24: =$B$9*S24 -> 114826.92
A25: Total / peak | C25: =SUM(C13:C24) -> 65574.049 | I25: =SUM(I13:I24) -> 62080 | J25: =C25/I25-1 -> 0.05628301 | M25: =MAX(M13:M24) -> 1.2949521 | N25: =MAX(N13:N24) -> 102.27 | O25: =MAX(O13:O24) -> 0.20317647 | P25: =SUM(P13:P24) -> 16716239 | Q25: =SUM(Q13:Q24) -> 793298.42 | S25: =SUM(S13:S24) -> 4579.3291 | T25: =SUM(T13:T24) -> 70153.378 | U25: =MAX(U13:U24) -> 111.03762 | V25: =SUM(V13:V24) -> 915562.83
A27: Key results
A28: Peak month (ER) | B28: =INDEX(A13:A24,MATCH(MAX(C13:C24),C13:C24,0)) -> 45992
A29: Trough month (ER) | B29: =INDEX(A13:A24,MATCH(MIN(C13:C24),C13:C24,0)) -> 45809
A30: Peak/trough staffing ratio | B30: =MAX(C13:C24)/MIN(C13:C24) -> 1.4759763
A31: Months ICU forecast > target | B31: =COUNTIF(N13:N24,">"&B5*100) -> 6
A32: Months ICU forecast > 100% | B32: =COUNTIF(N13:N24,">100") -> 2
A33: Winter-surge budget reserve $ | B33: =Q25 -> 793298.42
A34: Severe-season contingency $ | B34: =V25 -> 915562.83
